Workbook
Name CONTRATTO: Elenchi!$A$36:$A$52
Name DESTINAZIONE_CDC: Elenchi!$L$5:$L$228
Name DESTINAZIONE_SOCIETA: Elenchi!$D$5:$D$21
Name DESTINAZIONE_VIA: Elenchi!$G$5:$G$29
Name EMAIL: Elenchi!$A$19:$A$20
Name MANSIONE: Elenchi!$A$84:$A$112
Name MOVIMENTO: Elenchi!$A$5:$A$15
Name ONBOARDING: Elenchi!$A$131:$A$133
Name PROVENIENZA_CDC: Elenchi!$AB$5:$AB$228
Name PROVENIENZA_SOCIETA: Elenchi!$T$5:$T$19
Name PROVENIENZA_VIA: Elenchi!$W$5:$W$27
Name QUALIFICA: Elenchi!$A$56:$A$69
Name SESSO: Elenchi!$A$29:$A$32
Name STATO: Elenchi!$A$73:$A$80
Name TELELAVORO: Elenchi!$A$24:$A$25

Sheet Scheda Movimento
A1: Scheda movimenti PERSONALE
A3: =IF(B3="","","Oggetto e-mail: ") -> Oggetto e-mail: | B3: =IF(C6="","",CONCATENATE("Comunic. ",C6,": ",C7," ",C8," - ",C22," - ",C20," - ",TEXT(C5,"gg.mm.aa"))) -> Comunic. INGRESSO: IACOVELLI ALESSANDRA - DIRIGENTE - MILANO - 16.03.26
A4: Voci movimento | B4: Cod. | C4: Descrizione movimento | D4: Con Elenco
A5: Decorrenza [data] | C5: 46097
A6: Movimento | C6: INGRESSO | D6: ▼
A7: Cognome | C7: IACOVELLI
A8: Nome | C8: ALESSANDRA
A9: Sesso | B9: =Elenchi!B27 -> F | C9: Femminile | D9: ▼
A10: Codice Fiscale | C10: CVLLSN80R49D643R
A11: Data di nascita | C11: 29503
A12: Comune di nascita | C12: FOGGIA
A13: Provincia di nascita | C13: FOGGIA
A14: Nazione di nascita | C14: ITALIA
A15: Società | B15: =IF(C15="","",Elenchi!E3) -> 15 | C15: IL SOLE 24 ORE S.P.A. | D15: ▼
A16: Area | C16: =IF(B18="","",Elenchi!Q3) -> DG I&S - DIR INFORMATION TECHNOLOGY
A17: Sotto Area | C17: =IF(B18="","",Elenchi!O3) -> DIR INFORMATION TECHNOLOGY
A18: Centro di Costo | B18: 415300 | C18: =IF(B18="","",Elenchi!M3) -> DIR INFORMATION TECHNOLOGY | D18: ▼
A19: Indirizzo sede | C19: VIALE SARCA 223 - MILANO (MI) | D19: ▼
A20: Cod. e Città sede | B20: =IF(C19="","",Elenchi!J3) -> 34 | C20: =IF(C19="","",Elenchi!H3) -> MILANO
A21: Contratto (Sicurezza Lavoro*) | B21: =IF(C21="","",Elenchi!B34) -> 02 | C21: Contratto a tempo indeterminato | D21: ▼
A22: Qualifica | B22: =IF(C22="","",Elenchi!B54) -> D | C22: DIRIGENTE | D22: ▼
A23: Codice Oneservice | B23: =IF(C23="","",C23) -> 3176 | C23: 3176
A24: Telelavoro | C24: NO | D24: ▼
A25: E-mail prefisso "EXT" | C25: No | D25: ▼
A26: E-mail suffisso (proposta) | C26: @ilsole24ore.com | D26: ▼
A27: E-mail (proposta) | C27: =IF(C7="","",CONCATENATE(_xlfn.TEXTBEFORE(CONCATENATE(LOWER(REPLACE(C8,1,,""))," ")," "),".",LOWER(REPLACE(C7,1,,"")),C26)) -> alessandra.iacovelli@ilsole24ore.com
A28: Stato (Serv, Mat.; Asp; Usc) | B28: =IF(C28="","",Elenchi!B71) -> S | C28: Servizio (in) | D28: ▼
A29: Data scadenza
A30: Job Title/Mansione
A31: Mansione (Sicurezza Lavoro*) | B31: =IF(C31="","",Elenchi!B82) -> IMP_VDT | C31: IMPIEGATO CON USO VDT | D31: ▼
A32: Formazione Salute e Sicurezza Lav. | C32: =IF(C6="INGRESSO",IF(C21="","",IF(C21="Contratto a Part. IVA","NO","SI")),"") -> SI
A33: Referente diretto | C33: Boromei Paola
A34: Provenienza Società (distacco e trasfer.to) | B34: =IF(C34="","",Elenchi!U3) | D34: ▼
A35: Area | B35: =IF(C35="","",Elenchi!AF3) | C35: =IF(B37="","",Elenchi!AG3)
A36: Sotto Area | B36: =IF(C36="","",Elenchi!AD3) | C36: =IF(B37="","",Elenchi!AE3)
A37: Centro di Costo | C37: =IF(B37="","",Elenchi!AC3) | D37: ▼
A38: Indirizzo sede | D38: ▼
A39: Cod. e Città sede | B39: =IF(C38="","",Elenchi!Z3) | C39: =IF(C38="","",Elenchi!X3)
A40: In caso di uscita è previsto nuovo ingresso come
A41: Nuovo Referente diretto
A42: Attivazione Onboarding | C42: =IF(B42="","",Elenchi!B129)
A43: Note
A44: (*) Preinserimento da HR con verifica e attribuzione definitivo a cura unità Sicurezza e Ambiente
A46: Legenda:
A47: xxx = Campi compilabili

Sheet Sicurezza
A1: COGNOME | B1: NOME | C1: CODICE FISCALE | D1: SESSO | E1: DATA NASCITA | F1: COMUNE | G1: PROV | H1: NAZ | I1: DATA Decorrenza | J1: DATA FINE RAPPORTO | K1: STATO | L1: SOCIETA' | M1: CDC | N1: CITTA DELLA SEDE DI APPARTENENZA | O1: INDIRIZZO SEDE | P1: AREA | Q1: CONTRATTO | R1: QUALIFICA | S1: TELELAVORO | T1: CODICE MANSIONE | U1: DESCRIZIONE MANSIONE | V1: REFERENTE | W1: NOMINA SICUREZZA | X1: DATA ASSEGNAZIONE NOMINA SICUREZZA
A2: =IF('Scheda Movimento'!C7="","",'Scheda Movimento'!C7) -> IACOVELLI | B2: =IF('Scheda Movimento'!C8="","",'Scheda Movimento'!C8) -> ALESSANDRA | C2: =IF('Scheda Movimento'!C10="","",'Scheda Movimento'!C10) -> CVLLSN80R49D643R | D2: =IF('Scheda Movimento'!C9="","",'Scheda Movimento'!B9) -> F | E2: =IF('Scheda Movimento'!C11="","",'Scheda Movimento'!C11) -> 29503 | F2: =IF('Scheda Movimento'!C12="","",'Scheda Movimento'!C12) -> FOGGIA | G2: =IF('Scheda Movimento'!C13="","",'Scheda Movimento'!C13) -> FOGGIA | H2: =IF('Scheda Movimento'!C14="","",'Scheda Movimento'!C14) -> ITALIA | I2: =IF('Scheda Movimento'!C5="","",'Scheda Movimento'!C5) -> 46097 | J2: =IF('Scheda Movimento'!C29="","",'Scheda Movimento'!C29) | K2: =IF('Scheda Movimento'!C28="","",'Scheda Movimento'!B28) -> S | L2: =IF('Scheda Movimento'!C15="","",IF(LEFT('Scheda Movimento'!C15,5)="Stage",SUBSTITUTE('Scheda Movimento'!C15,"Stage ",,1),IF(LEFT('Scheda Movimento'!C15,5)="Colla",SUBSTITUTE('Scheda Movimento'!C15,"Collaboratori - ",,1),IF(LEFT('Scheda Movimento'!C15,5)="Colla",SUBSTITUTE('Scheda Movimento'!C15,"Collaboratori ",,1),IF(LEFT('Scheda Movimento'!C15,5)="Inter",SUBSTITUTE('Scheda Movimento'!C15,"Interinali ",,1),'Scheda Movimento'!C15))))) -> IL SOLE 24 ORE S.P.A. | M2: =IF('Scheda Movimento'!B18="","",'Scheda Movimento'!B18) -> 415300 | N2: =IF('Scheda Movimento'!C20="","",'Scheda Movimento'!C20) -> MILANO | O2: =IF('Scheda Movimento'!C19="","",'Scheda Movimento'!C19) -> VIALE SARCA 223 - MILANO (MI) | P2: =IF('Scheda Movimento'!C16="","",'Scheda Movimento'!C16) -> DG I&S - DIR INFORMATION TECHNOLOGY | Q2: =IF('Scheda Movimento'!C21="","",'Scheda Movimento'!B21) -> 02 | R2: =IF('Scheda Movimento'!B22="","",IF(OR('Scheda Movimento'!B22="I",'Scheda Movimento'!B22="D",'Scheda Movimento'!B22="G",'Scheda Movimento'!B22="O",'Scheda Movimento'!B22="P",),'Scheda Movimento'!B22,"")) -> D | S2: =IF('Scheda Movimento'!C24="","",'Scheda Movimento'!C24) -> NO | T2: =IF('Scheda Movimento'!B31="","",'Scheda Movimento'!B31) -> IMP_VDT | U2: =IF('Scheda Movimento'!C31="","",'Scheda Movimento'!C31) -> IMPIEGATO CON USO VDT | V2: =IF('Scheda Movimento'!C33="","",'Scheda Movimento'!C33) -> Boromei Paola

Sheet Organizz
A1: SocietàOrg | B1: Unità Organizzativa | C1: Unità Organizzativa 2 | D1: Testata GG | E1: Testata 2 | F1: IncaricoSGSL | G1: CdC | H1: CdC2 | I1: ALTRI INCARICHI | J1: Titolare | K1: DettaglioTitolare | L1: Titolare 2 | M1: Cognome 2 | N1: Note Txt | O1: Note Txt 2 | P1: Note su Unità | Q1: Sede | R1: Sede 2 | S1: Tipo Collaborazione | T1: Maternità | U1: Processo | V1: Format | W1: Funzione | X1: AllegatiDip | Y1: Art GG | Z1: Tipo GG | AA1: Fte | AB1: ID | AC1: ReportsTo | AD1: Foto | AE1: Variazioni Posizione | AF1: TxCodFiscale | AG1: Cognome | AH1: Nome | AI1: Società | AJ1: Area | AK1: SottoArea | AL1: CdcAmministrazione | AM1: Descrizione Cdc | AN1: Data-ass | AO1: Data fine rapporto | AP1: Sesso | AQ1: Contratto | AR1: Qualifica | AS1: Livello | AT1: Testata giornalistica | AU1: Indirizzo | AV1: CAP | AW1: Città | AX1: Timb-fir | AY1: Turno | AZ1: RAL | BA1: Data Nascita | BB1: ETA' | BC1: Job-title | BD1: Liv-studio | BE1: Assenza | BF1: Responsabilediretto | BG1: TD-Sost | BH1: Part-time | BI1: email | BJ1: Numero | BK1: Cognome_email | BL1: Nome_email | BM1: email | BN1: INFO email | BO1: Dipendente email | BP1: TOP?verificarli | BQ1: Scelti | BR1: Scelti2 Tutti | BS1: Escluso da TNS | BT1: Popolaz_TNS | BU1: Deltacdc_TNS | BV1: CDC_TNS | BW1: CDC_NEW_TNS | BX1: Tipo Approvatore TNS | BY1: Note Appr NTS | BZ1: Titolare_TNS | CA1: LIVELLO_TNS | CB1: COD_TNS | CC1: PADRE_TNS | CD1: RUOLI_OltreV_TNS | CE1: RUOLI | CF1: Viaggiatore_TNS | CG1: Segr_Redaz_TNS | CH1: Approvatore_TNS | CI1: Cassiere_TNS | CJ1: Visualizzatori_TNS | CK1: Segretario_TNS | CL1: Controllore_TNS | CM1: Amministrazione_TNS | CN1: SegreteriA_Red_Assta_TNS | CO1: SegretariO_Assto_TNS | CP1: Controllore_Assto_TNS | CQ1: RuoliAFC | CR1: RuoliHR | CS1: AltriRuoli | CT1: Sede_TNS | CU1: GruppoSind | CV1: Controllo | CW1: RespAreaCODFIS | CX1: RespAreaCOGN | CY1: RespAreaNOM | CZ1: RespSottoareaCODFIS | DA1: RespSottoareaCOGN | DB1: RespSottoareaNOM | DC1: SBCAP | DD1: Escluso SF | DE1: Popolazione SF | DF1: Cogn | DG1: Nome | DH1: TxCodFisc | DI1: Richiedente SF | DJ1: Ricevente_Cognome | DK1: Ricevente_Nome | DL1: Ricevente_CodFis | DM1: Note | DN1: NO_ORG1e2liv | DO1: New posizione dopo | DP1: Free | DQ1: Titolare_SGSL | DR1: Ruolo_SGSL | DS1: SGSL_SI | DT1: NOME_UNITASGSL | DU1: ID_SGSL | DV1: CODPADRE_SGSL | DW1: Titolare_Privacy | DX1: Ruolo_Privacy | DY1: Privacy_SI | DZ1: NOME_UNITAPrivacy | EA1: ID_Privacy | EB1: CODPADRE_Privacy | EC1: Ruolo in SB/CAP | ED1: Ruolo in GeCo | EE1: Ruolo in procedure IT
A2: =AI2 -> IL SOLE 24 ORE S.P.A. | B2: =AM2 -> DIR INFORMATION TECHNOLOGY | G2: =AL2 -> 415300 | J2: =IF(AG2="","",CONCATENATE(LEFT(AG2,1),LOWER(REPLACE(AG2,1,1,""))," ",LEFT(AH2,1),". ")) -> Iacovelli A. | K2: =IF(OR('Scheda Movimento'!C34<>"",'Scheda Movimento'!B37<>"",'Scheda Movimento'!C40<>"",'Scheda Movimento'!B42<>"",'Scheda Movimento'!C43<>""),CONCATENATE('Scheda Movimento'!C34," - ",'Scheda Movimento'!B37," - ",'Scheda Movimento'!C40," - ",'Scheda Movimento'!B42," - ",'Scheda Movimento'!C43," - ",),"") | X2: =IF(AE2="","",AE2) -> INGRESSO | AB2: =IF(AF2="","",CONCATENATE(AF2,"_ID")) -> CVLLSN80R49D643R_ID | AE2: =IF('Scheda Movimento'!C6="","",'Scheda Movimento'!C6) -> INGRESSO | AF2: =IF('Scheda Movimento'!C10="","",'Scheda Movimento'!C10) -> CVLLSN80R49D643R | AG2: =IF('Scheda Movimento'!C7="","",'Scheda Movimento'!C7) -> IACOVELLI | AH2: =IF('Scheda Movimento'!C8="","",'Scheda Movimento'!C8) -> ALESSANDRA | AI2: =IF('Scheda Movimento'!C15="","",'Scheda Movimento'!C15) -> IL SOLE 24 ORE S.P.A. | AJ2: =IF('Scheda Movimento'!C16="","",'Scheda Movimento'!C16) -> DG I&S - DIR INFORMATION TECHNOLOGY | AK2: =IF('Scheda Movimento'!C17="","",'Scheda Movimento'!C17) -> DIR INFORMATION TECHNOLOGY | AL2: =IF('Scheda Movimento'!B18="","",'Scheda Movimento'!B18) -> 415300 | AM2: =IF('Scheda Movimento'!C18="","",'Scheda Movimento'!C18) -> DIR INFORMATION TECHNOLOGY | AN2: =IF('Scheda Movimento'!C5="","",'Scheda Movimento'!C5) -> 46097 | AO2: =IF('Scheda Movimento'!C29="","",'Scheda Movimento'!C29) | AP2: =IF('Scheda Movimento'!C9="","",'Scheda Movimento'!C9) -> Femminile | AR2: =IF('Scheda Movimento'!C22="","",IF('Scheda Movimento'!C22="Co.Co.Co.","Lav.Prog.",IF('Scheda Movimento'!C22="Co.Co.Pro.","Lav.Prog.",IF('Scheda Movimento'!C22="Contr","C.Somm.",'Scheda Movimento'!C22)))) -> DIRIGENTE | AS2: =IF('Scheda Movimento'!C22="Co.Co.Co.","COCOCO",IF('Scheda Movimento'!C22="Co.Co.Pro.","COLAPRO","")) | AU2: =IF('Scheda Movimento'!C19="","",'Scheda Movimento'!C19) -> VIALE SARCA 223 - MILANO (MI) | AW2: =IF('Scheda Movimento'!C20="","",'Scheda Movimento'!C20) -> MILANO | BC2: =IF('Scheda Movimento'!C30="","",'Scheda Movimento'!C30) | BF2: ='Scheda Movimento'!C33 -> Boromei Paola | BG2: =IF('Scheda Movimento'!C21="","",IF('Scheda Movimento'!C21="Contratto a tempo determinato","T.det","")) | BK2: =AG2 -> IACOVELLI | BL2: =AH2 -> ALESSANDRA | BM2: =IF(AG2="","",CONCATENATE(LEFT(AG2,1),LOWER(REPLACE(AG2,1,1,""))," ",_xlfn.TEXTBEFORE(LOWER(REPLACE(AH2,1,,""))," "))) -> #N/A | BN2: ='Scheda Movimento'!C27 -> alessandra.iacovelli@ilsole24ore.com | BT2: =IF(BS2<>"","",IF(OR(TRIM(AR2)="Dirigente",TRIM(AR2)="Quadro",TRIM(AR2)="Impiegato",TRIM(AR2)="Operaio",TRIM(AR2)="Giornalista"),"SI","")) -> SI | BZ2: =IF(BT2="","",CONCATENATE(TRIM(BK2)," ",TRIM(BL2))) -> IACOVELLI ALESSANDRA | CB2: =IF(BZ2="","",AF2) -> CVLLSN80R49D643R | CF2: =IF(CB2="","",IF(OR(AR2="GIORNALISTA",AR2="PRATICANTE"),"VG",IF(OR(AR2="IMPIEGATO",AR2="DIRIGENTE",AR2="OPERAIO"),"V",""))) -> V

Sheet Indicazioni per compilazione
A1: Indicazioni per la compilazione
B2: Dipendente | I2: Collaboratore
A3: Voci movimento | B3: Ingresso | C3: Ingresso + Distacco | D3: Trasfer.to | E3: Distacco | F3: Proroga | G3: Cambio Contratto | H3: Uscita | I3: Ingresso | J3: Proroga | K3: Cambio Contratto | L3: Uscita | M3: Voci movimento
A4: Decorrenza [data] | M4: Decorrenza [data]
A5: Movimento | M5: Movimento
A6: Cognome | M6: Cognome
A7: Nome | M7: Nome
A8: Sesso | M8: Sesso
A9: Codice Fiscale | M9: Codice Fiscale
A10: Data di nascita | M10: Data di nascita
A11: Comune di nascita | M11: Comune di nascita
A12: Provincia di nascita | M12: Provincia di nascita
A13: Nazione di nascita | M13: Nazione di nascita
A14: Società | M14: Società
A15: Area | M15: Area
... A35: Note | M35: Note
A37: (*) Valore definitivo a cura unità Sicurezza e Ambiente | B37: Legenda
D38: Ok da compilare
D39: Facoltativo
D40: Non necessario

Sheet Elenchi
D1: DESTINAZIONE (da Pivot) | L1: DESTINAZIONE (da Pivot) | R1: Aggiutno a mano | T1: PROVENIENZA (da Pivot) | AB1: PROVENIENZA
D3: ='Scheda Movimento'!C15 -> IL SOLE 24 ORE S.P.A. | E3: =VLOOKUP(D3,D5:E21,2,FALSE) -> 15 | G3: ='Scheda Movimento'!C19 -> VIALE SARCA 223 - MILANO (MI) | H3: =VLOOKUP(G3,G5:J29,2,FALSE) -> MILANO | I3: =VLOOKUP(G3,G5:J29,3,FALSE) -> MILANO | J3: =VLOOKUP(G3,G5:J29,4,FALSE) -> 34 | L3: ='Scheda Movimento'!B18 -> 415300 | M3: =VLOOKUP(L3,L6:M228,2,FALSE) -> DIR INFORMATION TECHNOLOGY | N3: =VLOOKUP(L3,L6:N228,3,FALSE) | O3: =VLOOKUP(L3,L6:O228,4,FALSE) -> DIR INFORMATION TECHNOLOGY | P3: =VLOOKUP(L3,L6:P228,5,FALSE) | Q3: =VLOOKUP(L3,L6:Q228,6,FALSE) -> DG I&S - DIR INFORMATION TECHNOLOGY | T3: ='Scheda Movimento'!C34 -> 0 | U3: =VLOOKUP(T3,T5:U19,2,FALSE) -> #N/A | W3: ='Scheda Movimento'!C38 -> 0 | X3: =VLOOKUP(W3,W5:Z27,2,FALSE) -> #N/A | Y3: =VLOOKUP(W3,W5:Z27,3,FALSE) -> #N/A | Z3: =VLOOKUP(W3,W5:Z27,4,FALSE) -> #N/A | AB3: ='Scheda Movimento'!B37 -> 0 | AC3: =VLOOKUP(AB3,AB6:AC228,2,FALSE) -> #N/A | AD3: =VLOOKUP(AB3,AB6:AD228,3,FALSE) -> #N/A | AE3: =VLOOKUP(AB3,AB6:AE228,4,FALSE) -> #N/A | AF3: =VLOOKUP(AB3,AB6:AF228,5,FALSE) -> #N/A | AG3: =VLOOKUP(AB3,AB6:AG228,6,FALSE) -> #N/A
A4: MOVIMENTI | D4: SOCIETA' | E4: COD SOCIETA' | G4: Via | H4: Citta | I4: Prov | J4: Codice Sede | L4: cdc | M4: descrcdc | N4: Codsottoarea | O4: Sottoare | P4: CodArea | Q4: Area | T4: SOCIETA' | U4: COD SOCIETA' | W4: Via | X4: Citta | Y4: Prov | Z4: Codice Sede | AB4: cdc | AC4: descrcdc | AD4: Codsottoarea | AE4: Sottoare | AF4: CodArea | AG4: Area
W5: =IF(G5="","",G5) | Y5: =IF(I5="","",I5) | Z5: =IF(J5="","",J5)
A6: CAMBIO CONTRATTO | D6: =IF('Pivot elenchi'!D3="","",'Pivot elenchi'!D3) -> IL SOLE 24 ORE S.P.A. | E6: =IF('Pivot elenchi'!C3="","",'Pivot elenchi'!C3) -> 15 | G6: =IF('Pivot elenchi'!I3="","",'Pivot elenchi'!I3) -> VIA TORTONA 56 - MILANO (MI) | H6: MILANO | I6: =IF('Pivot elenchi'!J3="","",'Pivot elenchi'!J3) -> MILANO | J6: =IF('Pivot elenchi'!H3="","",'Pivot elenchi'!H3) -> 19 | L6: =IF(AND('Pivot elenchi'!P5="",'Pivot elenchi'!P6=""),"",IF('Pivot elenchi'!P5="",'Pivot elenchi'!P4="",'Pivot elenchi'!P5)) -> 011000 | M6: =IF(AND('Pivot elenchi'!Q5="",'Pivot elenchi'!Q6=""),"",IF('Pivot elenchi'!Q5="",'Pivot elenchi'!Q4="",'Pivot elenchi'!Q5)) -> CORPORATE | N6: =IF(AND('Pivot elenchi'!R5="",'Pivot elenchi'!R6=""),"",IF('Pivot elenchi'!R5="",'Pivot elenchi'!R4="",'Pivot elenchi'!R5)) | O6: =IF(AND('Pivot elenchi'!S5="",'Pivot elenchi'!S6=""),"",IF('Pivot elenchi'!S5="",'Pivot elenchi'!S4="",'Pivot elenchi'!S5)) -> CORPORATE | P6: =IF(AND('Pivot elenchi'!T5="",'Pivot elenchi'!T6=""),"",IF('Pivot elenchi'!T5="",'Pivot elenchi'!T4="",'Pivot elenchi'!T5)) | Q6: =IF(AND('Pivot elenchi'!U5="",'Pivot elenchi'!U6=""),"",IF('Pivot elenchi'!U5="",'Pivot elenchi'!U4="",'Pivot elenchi'!U5)) -> CORPORATE | R6: @ilsole24ore.com | T6: =IF('Pivot elenchi'!D3="","",'Pivot elenchi'!D3) -> IL SOLE 24 ORE S.P.A. | U6: =IF('Pivot elenchi'!C3="","",'Pivot elenchi'!C3) -> 15 | W6: =IF(G6="","",G6) -> VIA TORTONA 56 - MILANO (MI) | X6: =IF(H6="","",H6) -> MILANO | Y6: =IF(I6="","",I6) -> MILANO | Z6: =IF(J6="","",J6) -> 19 | AB6: =L6 -> 011000 | AC6: =M6 -> CORPORATE | AD6: =N6 | AE6: =O6 -> CORPORATE | AF6: =P6 | AG6: =Q6 -> CORPORATE
A7: DISTACCO | D7: =IF('Pivot elenchi'!D4="","",'Pivot elenchi'!D4) -> 24 ORE CULTURA S.R.L. | E7: =IF('Pivot elenchi'!C4="","",'Pivot elenchi'!C4) -> 28 | G7: =IF('Pivot elenchi'!I4="","",'Pivot elenchi'!I4) -> PIAZZA INDIPENDENZA 23 B/C - ROMA (RM) | H7: ROMA | I7: =IF('Pivot elenchi'!J4="","",'Pivot elenchi'!J4) -> ROMA | J7: =IF('Pivot elenchi'!H4="","",'Pivot elenchi'!H4) -> 31 | L7: =IF(AND('Pivot elenchi'!P6="",'Pivot elenchi'!P7=""),"",IF('Pivot elenchi'!P6="",'Pivot elenchi'!P5="",'Pivot elenchi'!P6)) -> 011200 | M7: =IF(AND('Pivot elenchi'!Q6="",'Pivot elenchi'!Q7=""),"",IF('Pivot elenchi'!Q6="",'Pivot elenchi'!Q5="",'Pivot elenchi'!Q6)) -> DG INNOVAZIONE E SOSTENIBILITA' | N7: =IF(AND('Pivot elenchi'!R6="",'Pivot elenchi'!R7=""),"",IF('Pivot elenchi'!R6="",'Pivot elenchi'!R5="",'Pivot elenchi'!R6)) | O7: =IF(AND('Pivot elenchi'!S6="",'Pivot elenchi'!S7=""),"",IF('Pivot elenchi'!S6="",'Pivot elenchi'!S5="",'Pivot elenchi'!S6)) -> DG INNOVAZIONE E SOSTENIBILITA' | P7: =IF(AND('Pivot elenchi'!T6="",'Pivot elenchi'!T7=""),"",IF('Pivot elenchi'!T6="",'Pivot elenchi'!T5="",'Pivot elenchi'!T6)) | Q7: =IF(AND('Pivot elenchi'!U6="",'Pivot elenchi'!U7=""),"",IF('Pivot elenchi'!U6="",'Pivot elenchi'!U5="",'Pivot elenchi'!U6)) -> DG INNOVAZIONE E SOSTENIBILITA' | R7: @ilsole24ore.com | T7: =IF('Pivot elenchi'!D4="","",'Pivot elenchi'!D4) -> 24 ORE CULTURA S.R.L. | U7: =IF('Pivot elenchi'!C4="","",'Pivot elenchi'!C4) -> 28 | W7: =IF(G7="","",G7) -> PIAZZA INDIPENDENZA 23 B/C - ROMA (RM) | X7: =IF(H7="","",H7) -> ROMA | Y7: =IF(I7="","",I7) -> ROMA | Z7: =IF(J7="","",J7) -> 31 | AB7: =L7 -> 011200 | AC7: =M7 -> DG INNOVAZIONE E SOSTENIBILITA' | AD7: =N7 | AE7: =O7 -> DG INNOVAZIONE E SOSTENIBILITA' | AF7: =P7 | AG7: =Q7 -> DG INNOVAZIONE E SOSTENIBILITA'
A8: DISTACCO - FINE | D8: =IF('Pivot elenchi'!D5="","",'Pivot elenchi'!D5) -> IL SOLE 24 ORE EVENTI S.R.L. | E8: =IF('Pivot elenchi'!C5="","",'Pivot elenchi'!C5) -> 35 | G8: =IF('Pivot elenchi'!I5="","",'Pivot elenchi'!I5) -> VIA NIZZA 142 - ROMA (RM) | H8: ROMA | I8: =IF('Pivot elenchi'!J5="","",'Pivot elenchi'!J5) -> ROMA | J8: =IF('Pivot elenchi'!H5="","",'Pivot elenchi'!H5) -> 33 | L8: =IF(AND('Pivot elenchi'!P7="",'Pivot elenchi'!P8=""),"",IF('Pivot elenchi'!P7="",'Pivot elenchi'!P6="",'Pivot elenchi'!P7)) -> 012000 | M8: =IF(AND('Pivot elenchi'!Q7="",'Pivot elenchi'!Q8=""),"",IF('Pivot elenchi'!Q7="",'Pivot elenchi'!Q6="",'Pivot elenchi'!Q7)) -> AFFARI LEGALI E SOCIETARI | N8: =IF(AND('Pivot elenchi'!R7="",'Pivot elenchi'!R8=""),"",IF('Pivot elenchi'!R7="",'Pivot elenchi'!R6="",'Pivot elenchi'!R7)) | O8: =IF(AND('Pivot elenchi'!S7="",'Pivot elenchi'!S8=""),"",IF('Pivot elenchi'!S7="",'Pivot elenchi'!S6="",'Pivot elenchi'!S7)) -> AFFARI LEGALI E SOCIETARI | P8: =IF(AND('Pivot elenchi'!T7="",'Pivot elenchi'!T8=""),"",IF('Pivot elenchi'!T7="",'Pivot elenchi'!T6="",'Pivot elenchi'!T7)) | Q8: =IF(AND('Pivot elenchi'!U7="",'Pivot elenchi'!U8=""),"",IF('Pivot elenchi'!U7="",'Pivot elenchi'!U6="",'Pivot elenchi'!U7)) -> AFFARI LEGALI E SOCIETARI | R8: @ilsole24ore.com | T8: =IF('Pivot elenchi'!D5="","",'Pivot elenchi'!D5) -> IL SOLE 24 ORE EVENTI S.R.L. | U8: =IF('Pivot elenchi'!C5="","",'Pivot elenchi'!C5) -> 35 | W8: =IF(G8="","",G8) -> VIA NIZZA 142 - ROMA (RM) | X8: =IF(H8="","",H8) -> ROMA | Y8: =IF(I8="","",I8) -> ROMA | Z8: =IF(J8="","",J8) -> 33 | AB8: =L8 -> 012000 | AC8: =M8 -> AFFARI LEGALI E SOCIETARI | AD8: =N8 | AE8: =O8 -> AFFARI LEGALI E SOCIETARI | AF8: =P8 | AG8: =Q8 -> AFFARI LEGALI E SOCIETARI
A9: INGRESSO | D9: =IF('Pivot elenchi'!D6="","",'Pivot elenchi'!D6) -> IL SOLE 24 ORE SPA | E9: =IF('Pivot elenchi'!C6="","",'Pivot elenchi'!C6) -> 2015 | G9: =IF('Pivot elenchi'!I6="","",'Pivot elenchi'!I6) -> VIALE SARCA 223 - MILANO (MI) | H9: MILANO | I9: =IF('Pivot elenchi'!J6="","",'Pivot elenchi'!J6) -> MILANO | J9: =IF('Pivot elenchi'!H6="","",'Pivot elenchi'!H6) -> 34 | L9: =IF(AND('Pivot elenchi'!P8="",'Pivot elenchi'!P9=""),"",IF('Pivot elenchi'!P8="",'Pivot elenchi'!P7="",'Pivot elenchi'!P8)) -> 013000 | M9: =IF(AND('Pivot elenchi'!Q8="",'Pivot elenchi'!Q9=""),"",IF('Pivot elenchi'!Q8="",'Pivot elenchi'!Q7="",'Pivot elenchi'!Q8)) -> INVESTOR RELATIONS | N9: =IF(AND('Pivot elenchi'!R8="",'Pivot elenchi'!R9=""),"",IF('Pivot elenchi'!R8="",'Pivot elenchi'!R7="",'Pivot elenchi'!R8)) | O9: =IF(AND('Pivot elenchi'!S8="",'Pivot elenchi'!S9=""),"",IF('Pivot elenchi'!S8="",'Pivot elenchi'!S7="",'Pivot elenchi'!S8)) -> INVESTOR RELATIONS | P9: =IF(AND('Pivot elenchi'!T8="",'Pivot elenchi'!T9=""),"",IF('Pivot elenchi'!T8="",'Pivot elenchi'!T7="",'Pivot elenchi'!T8)) | Q9: =IF(AND('Pivot elenchi'!U8="",'Pivot elenchi'!U9=""),"",IF('Pivot elenchi'!U8="",'Pivot elenchi'!U7="",'Pivot elenchi'!U8)) -> AMMINISTRAZIONE, FINANZA E CONTROLLO | R9: @ilsole24ore.com | T9: =IF('Pivot elenchi'!D6="","",'Pivot elenchi'!D6) -> IL SOLE 24 ORE SPA | U9: =IF('Pivot elenchi'!C6="","",'Pivot elenchi'!C6) -> 2015 | W9: =IF(G9="","",G9) -> VIALE SARCA 223 - MILANO (MI) | X9: =IF(H9="","",H9) -> MILANO | Y9: =IF(I9="","",I9) -> MILANO | Z9: =IF(J9="","",J9) -> 34 | AB9: =L9 -> 013000 | AC9: =M9 -> INVESTOR RELATIONS | AD9: =N9 | AE9: =O9 -> INVESTOR RELATIONS | AF9: =P9 | AG9: =Q9 -> AMMINISTRAZIONE, FINANZA E CONTROLLO
A10: INGRESSO CON DISTACCO | D10: =IF('Pivot elenchi'!D7="","",'Pivot elenchi'!D7) -> COLLABORATORI 24ORE CULTURA | E10: =IF('Pivot elenchi'!C7="","",'Pivot elenchi'!C7) -> 2028 | G10: =IF('Pivot elenchi'!I7="","",'Pivot elenchi'!I7) -> VIA DAVIDE BERTOLOTTI 7 - TORINO (TO) | H10: TORINO | I10: =IF('Pivot elenchi'!J7="","",'Pivot elenchi'!J7) -> TORINO | J10: =IF('Pivot elenchi'!H7="","",'Pivot elenchi'!H7) -> 50 | L10: =IF(AND('Pivot elenchi'!P9="",'Pivot elenchi'!P10=""),"",IF('Pivot elenchi'!P9="",'Pivot elenchi'!P8="",'Pivot elenchi'!P9)) -> 015000 | M10: =IF(AND('Pivot elenchi'!Q9="",'Pivot elenchi'!Q10=""),"",IF('Pivot elenchi'!Q9="",'Pivot elenchi'!Q8="",'Pivot elenchi'!Q9)) -> DG SERVIZI PROFESSIONALI | N10: =IF(AND('Pivot elenchi'!R9="",'Pivot elenchi'!R10=""),"",IF('Pivot elenchi'!R9="",'Pivot elenchi'!R8="",'Pivot elenchi'!R9)) | O10: =IF(AND('Pivot elenchi'!S9="",'Pivot elenchi'!S10=""),"",IF('Pivot elenchi'!S9="",'Pivot elenchi'!S8="",'Pivot elenchi'!S9)) -> DG SERVIZI PROFESSIONALI E FORMAZIONE | P10: =IF(AND('Pivot elenchi'!T9="",'Pivot elenchi'!T10=""),"",IF('Pivot elenchi'!T9="",'Pivot elenchi'!T8="",'Pivot elenchi'!T9)) | Q10: =IF(AND('Pivot elenchi'!U9="",'Pivot elenchi'!U10=""),"",IF('Pivot elenchi'!U9="",'Pivot elenchi'!U8="",'Pivot elenchi'!U9)) -> DG SERVIZI PROFESSIONALI E FORMAZIONE | R10: @ilsole24ore.com | T10: =IF('Pivot elenchi'!D7="","",'Pivot elenchi'!D7) -> COLLABORATORI 24ORE CULTURA | U10: =IF('Pivot elenchi'!C7="","",'Pivot elenchi'!C7) -> 2028 | W10: =IF(G10="","",G10) -> VIA DAVIDE BERTOLOTTI 7 - TORINO (TO) | X10: =IF(H10="","",H10) -> TORINO | Y10: =IF(I10="","",I10) -> TORINO | Z10: =IF(J10="","",J10) -> 50 | AB10: =L10 -> 015000 | AC10: =M10 -> DG SERVIZI PROFESSIONALI | AD10: =N10 | AE10: =O10 -> DG SERVIZI PROFESSIONALI E FORMAZIONE | AF10: =P10 | AG10: =Q10 -> DG SERVIZI PROFESSIONALI E FORMAZIONE
A11: PROROGA | D11: =IF('Pivot elenchi'!D8="","",'Pivot elenchi'!D8) -> IL SOLE 24 ORE SPA | E11: =IF('Pivot elenchi'!C8="","",'Pivot elenchi'!C8) -> 4015 | G11: =IF('Pivot elenchi'!I8="","",'Pivot elenchi'!I8) -> VIA SOLTERI 38 - TRENTO (TN) | H11: TRENTO | I11: =IF('Pivot elenchi'!J8="","",'Pivot elenchi'!J8) -> TRENTO | J11: =IF('Pivot elenchi'!H8="","",'Pivot elenchi'!H8) -> 65 | L11: =IF(AND('Pivot elenchi'!P10="",'Pivot elenchi'!P11=""),"",IF('Pivot elenchi'!P10="",'Pivot elenchi'!P9="",'Pivot elenchi'!P10)) -> 016100 | M11: =IF(AND('Pivot elenchi'!Q10="",'Pivot elenchi'!Q11=""),"",IF('Pivot elenchi'!Q10="",'Pivot elenchi'!Q9="",'Pivot elenchi'!Q10)) -> INTERNAL AUDITING | N11: =IF(AND('Pivot elenchi'!R10="",'Pivot elenchi'!R11=""),"",IF('Pivot elenchi'!R10="",'Pivot elenchi'!R9="",'Pivot elenchi'!R10)) | O11: =IF(AND('Pivot elenchi'!S10="",'Pivot elenchi'!S11=""),"",IF('Pivot elenchi'!S10="",'Pivot elenchi'!S9="",'Pivot elenchi'!S10)) -> INTERNAL AUDITING | P11: =IF(AND('Pivot elenchi'!T10="",'Pivot elenchi'!T11=""),"",IF('Pivot elenchi'!T10="",'Pivot elenchi'!T9="",'Pivot elenchi'!T10)) | Q11: =IF(AND('Pivot elenchi'!U10="",'Pivot elenchi'!U11=""),"",IF('Pivot elenchi'!U10="",'Pivot elenchi'!U9="",'Pivot elenchi'!U10)) -> CORPORATE | R11: @ilsole24ore.com | T11: =IF('Pivot elenchi'!D8="","",'Pivot elenchi'!D8) -> IL SOLE 24 ORE SPA | U11: =IF('Pivot elenchi'!C8="","",'Pivot elenchi'!C8) -> 4015 | W11: =IF(G11="","",G11) -> VIA SOLTERI 38 - TRENTO (TN) | X11: =IF(H11="","",H11) -> TRENTO | Y11: =IF(I11="","",I11) -> TRENTO | Z11: =IF(J11="","",J11) -> 65 | AB11: =L11 -> 016100 | AC11: =M11 -> INTERNAL AUDITING | AD11: =N11 | AE11: =O11 -> INTERNAL AUDITING | AF11: =P11 | AG11: =Q11 -> CORPORATE
A12: PROROGA DISTACCO | D12: =IF('Pivot elenchi'!D9="","",'Pivot elenchi'!D9) -> SOLE STAGE | E12: =IF('Pivot elenchi'!C9="","",'Pivot elenchi'!C9) -> 1010 | G12: =IF('Pivot elenchi'!I9="","",'Pivot elenchi'!I9) -> DOMICILIO COLLABORATORE - () | I12: =IF('Pivot elenchi'!J9="","",'Pivot elenchi'!J9) | J12: =IF('Pivot elenchi'!H9="","",'Pivot elenchi'!H9) -> 66 | L12: =IF(AND('Pivot elenchi'!P11="",'Pivot elenchi'!P12=""),"",IF('Pivot elenchi'!P11="",'Pivot elenchi'!P10="",'Pivot elenchi'!P11)) -> 016110 | M12: =IF(AND('Pivot elenchi'!Q11="",'Pivot elenchi'!Q12=""),"",IF('Pivot elenchi'!Q11="",'Pivot elenchi'!Q10="",'Pivot elenchi'!Q11)) -> PRIVACY E SICUREZZA DATI | N12: =IF(AND('Pivot elenchi'!R11="",'Pivot elenchi'!R12=""),"",IF('Pivot elenchi'!R11="",'Pivot elenchi'!R10="",'Pivot elenchi'!R11)) | O12: =IF(AND('Pivot elenchi'!S11="",'Pivot elenchi'!S12=""),"",IF('Pivot elenchi'!S11="",'Pivot elenchi'!S10="",'Pivot elenchi'!S11)) -> AFFARI LEGALI E SOCIETARI | P12: =IF(AND('Pivot elenchi'!T11="",'Pivot elenchi'!T12=""),"",IF('Pivot elenchi'!T11="",'Pivot elenchi'!T10="",'Pivot elenchi'!T11)) | Q12: =IF(AND('Pivot elenchi'!U11="",'Pivot elenchi'!U12=""),"",IF('Pivot elenchi'!U11="",'Pivot elenchi'!U10="",'Pivot elenchi'!U11)) -> AFFARI LEGALI E SOCIETARI | R12: @ilsole24ore.com | T12: =IF('Pivot elenchi'!D9="","",'Pivot elenchi'!D9) -> SOLE STAGE | U12: =IF('Pivot elenchi'!C9="","",'Pivot elenchi'!C9) -> 1010 | W12: =IF(G12="","",G12) -> DOMICILIO COLLABORATORE - () | X12: =IF(H12="","",H12) | Y12: =IF(I12="","",I12) | Z12: =IF(J12="","",J12) -> 66 | AB12: =L12 -> 016110 | AC12: =M12 -> PRIVACY E SICUREZZA DATI | AD12: =N12 | AE12: =O12 -> AFFARI LEGALI E SOCIETARI | AF12: =P12 | AG12: =Q12 -> AFFARI LEGALI E SOCIETARI
A13: TRASFERIMENTO | D13: =IF('Pivot elenchi'!D10="","",'Pivot elenchi'!D10) | E13: =IF('Pivot elenchi'!C10="","",'Pivot elenchi'!C10) | G13: =IF('Pivot elenchi'!I10="","",'Pivot elenchi'!I10) -> VIA DELLE LIBERTA' 12 - VENEZIA (VE) | H13: VENEZIA | I13: =IF('Pivot elenchi'!J10="","",'Pivot elenchi'!J10) -> VENEZIA | J13: =IF('Pivot elenchi'!H10="","",'Pivot elenchi'!H10) -> 68 | L13: =IF(AND('Pivot elenchi'!P12="",'Pivot elenchi'!P13=""),"",IF('Pivot elenchi'!P12="",'Pivot elenchi'!P11="",'Pivot elenchi'!P12)) -> 210000 | M13: =IF(AND('Pivot elenchi'!Q12="",'Pivot elenchi'!Q13=""),"",IF('Pivot elenchi'!Q12="",'Pivot elenchi'!Q11="",'Pivot elenchi'!Q12)) -> AMMINISTRAZIONE, FINANZA E CONTROLLO | N13: =IF(AND('Pivot elenchi'!R12="",'Pivot elenchi'!R13=""),"",IF('Pivot elenchi'!R12="",'Pivot elenchi'!R11="",'Pivot elenchi'!R12)) | O13: =IF(AND('Pivot elenchi'!S12="",'Pivot elenchi'!S13=""),"",IF('Pivot elenchi'!S12="",'Pivot elenchi'!S11="",'Pivot elenchi'!S12)) -> AMMINISTRAZIONE, FINANZA E CONTROLLO | P13: =IF(AND('Pivot elenchi'!T12="",'Pivot elenchi'!T13=""),"",IF('Pivot elenchi'!T12="",'Pivot elenchi'!T11="",'Pivot elenchi'!T12)) | Q13: =IF(AND('Pivot elenchi'!U12="",'Pivot elenchi'!U13=""),"",IF('Pivot elenchi'!U12="",'Pivot elenchi'!U11="",'Pivot elenchi'!U12)) -> AMMINISTRAZIONE, FINANZA E CONTROLLO | R13: @ilsole24ore.com | T13: =IF('Pivot elenchi'!D10="","",'Pivot elenchi'!D10) | U13: =IF('Pivot elenchi'!C10="","",'Pivot elenchi'!C10) | W13: =IF(G13="","",G13) -> VIA DELLE LIBERTA' 12 - VENEZIA (VE) | X13: =IF(H13="","",H13) -> VENEZIA | Y13: =IF(I13="","",I13) -> VENEZIA | Z13: =IF(J13="","",J13) -> 68 | AB13: =L13 -> 210000 | AC13: =M13 -> AMMINISTRAZIONE, FINANZA E CONTROLLO | AD13: =N13 | AE13: =O13 -> AMMINISTRAZIONE, FINANZA E CONTROLLO | AF13: =P13 | AG13: =Q13 -> AMMINISTRAZIONE, FINANZA E CONTROLLO
A14: TRASFORMAZIONE CONTRATTO | D14: =IF('Pivot elenchi'!D11="","",'Pivot elenchi'!D11) | E14: =IF('Pivot elenchi'!C11="","",'Pivot elenchi'!C11) | G14: =IF('Pivot elenchi'!I11="","",'Pivot elenchi'!I11) -> VIA ALESSANDRO VOLTA 44 - PALERMO (PA) | H14: PALERMO | I14: =IF('Pivot elenchi'!J11="","",'Pivot elenchi'!J11) -> PALERMO | J14: =IF('Pivot elenchi'!H11="","",'Pivot elenchi'!H11) -> 72 | L14: =IF(AND('Pivot elenchi'!P13="",'Pivot elenchi'!P14=""),"",IF('Pivot elenchi'!P13="",'Pivot elenchi'!P12="",'Pivot elenchi'!P13)) -> 21000001 | M14: =IF(AND('Pivot elenchi'!Q13="",'Pivot elenchi'!Q14=""),"",IF('Pivot elenchi'!Q13="",'Pivot elenchi'!Q12="",'Pivot elenchi'!Q13)) -> FISCALITA' | N14: =IF(AND('Pivot elenchi'!R13="",'Pivot elenchi'!R14=""),"",IF('Pivot elenchi'!R13="",'Pivot elenchi'!R12="",'Pivot elenchi'!R13)) | O14: =IF(AND('Pivot elenchi'!S13="",'Pivot elenchi'!S14=""),"",IF('Pivot elenchi'!S13="",'Pivot elenchi'!S12="",'Pivot elenchi'!S13)) -> FISCALITA' | P14: =IF(AND('Pivot elenchi'!T13="",'Pivot elenchi'!T14=""),"",IF('Pivot elenchi'!T13="",'Pivot elenchi'!T12="",'Pivot elenchi'!T13)) | Q14: =IF(AND('Pivot elenchi'!U13="",'Pivot elenchi'!U14=""),"",IF('Pivot elenchi'!U13="",'Pivot elenchi'!U12="",'Pivot elenchi'!U13)) -> AMMINISTRAZIONE, FINANZA E CONTROLLO | R14: @ilsole24ore.com | T14: =IF('Pivot elenchi'!D11="","",'Pivot elenchi'!D11) | U14: =IF('Pivot elenchi'!C11="","",'Pivot elenchi'!C11) | W14: =IF(G14="","",G14) -> VIA ALESSANDRO VOLTA 44 - PALERMO (PA) | X14: =IF(H14="","",H14) -> PALERMO | Y14: =IF(I14="","",I14) -> PALERMO | Z14: =IF(J14="","",J14) -> 72 | AB14: =L14 -> 21000001 | AC14: =M14 -> FISCALITA' | AD14: =N14 | AE14: =O14 -> FISCALITA' | AF14: =P14 | AG14: =Q14 -> AMMINISTRAZIONE, FINANZA E CONTROLLO
A15: USCITA | D15: =IF('Pivot elenchi'!D12="","",'Pivot elenchi'!D12) | E15: =IF('Pivot elenchi'!C12="","",'Pivot elenchi'!C12) | G15: =IF('Pivot elenchi'!I12="","",'Pivot elenchi'!I12) -> PIAZZA DEI MARTIRI 58 - NAPOLI (NA) | H15: NAPOLI | I15: =IF('Pivot elenchi'!J12="","",'Pivot elenchi'!J12) -> NAPOLI | J15: =IF('Pivot elenchi'!H12="","",'Pivot elenchi'!H12) -> 79 | L15: =IF(AND('Pivot elenchi'!P14="",'Pivot elenchi'!P15=""),"",IF('Pivot elenchi'!P14="",'Pivot elenchi'!P13="",'Pivot elenchi'!P14)) -> 214000 | M15: =IF(AND('Pivot elenchi'!Q14="",'Pivot elenchi'!Q15=""),"",IF('Pivot elenchi'!Q14="",'Pivot elenchi'!Q13="",'Pivot elenchi'!Q14)) -> PIANIFICAZIONE E CONTROLLO DI G | N15: =IF(AND('Pivot elenchi'!R14="",'Pivot elenchi'!R15=""),"",IF('Pivot elenchi'!R14="",'Pivot elenchi'!R13="",'Pivot elenchi'!R14)) | O15: =IF(AND('Pivot elenchi'!S14="",'Pivot elenchi'!S15=""),"",IF('Pivot elenchi'!S14="",'Pivot elenchi'!S13="",'Pivot elenchi'!S14)) -> PIANIFICAZIONE E CONTROLLO | P15: =IF(AND('Pivot elenchi'!T14="",'Pivot elenchi'!T15=""),"",IF('Pivot elenchi'!T14="",'Pivot elenchi'!T13="",'Pivot elenchi'!T14)) | Q15: =IF(AND('Pivot elenchi'!U14="",'Pivot elenchi'!U15=""),"",IF('Pivot elenchi'!U14="",'Pivot elenchi'!U13="",'Pivot elenchi'!U14)) -> AMMINISTRAZIONE, FINANZA E CONTROLLO | R15: @ilsole24ore.com | T15: =IF('Pivot elenchi'!D12="","",'Pivot elenchi'!D12) | U15: =IF('Pivot elenchi'!C12="","",'Pivot elenchi'!C12) | W15: =IF(G15="","",G15) -> PIAZZA DEI MARTIRI 58 - NAPOLI (NA) | X15: =IF(H15="","",H15) -> NAPOLI | Y15: =IF(I15="","",I15) -> NAPOLI | Z15: =IF(J15="","",J15) -> 79 | AB15: =L15 -> 214000 | AC15: =M15 -> PIANIFICAZIONE E CONTROLLO DI G | AD15: =N15 | AE15: =O15 -> PIANIFICAZIONE E CONTROLLO | AF15: =P15 | AG15: =Q15 -> AMMINISTRAZIONE, FINANZA E CONTROLLO
D16: =IF('Pivot elenchi'!D13="","",'Pivot elenchi'!D13) | E16: =IF('Pivot elenchi'!C13="","",'Pivot elenchi'!C13) | G16: =IF('Pivot elenchi'!I13="","",'Pivot elenchi'!I13) -> VIALE IV NOVEMBRE 6 - GENOVA (GE) | H16: GENOVA | I16: =IF('Pivot elenchi'!J13="","",'Pivot elenchi'!J13) -> GENOVA | J16: =IF('Pivot elenchi'!H13="","",'Pivot elenchi'!H13) -> 80 | L16: =IF(AND('Pivot elenchi'!P15="",'Pivot elenchi'!P16=""),"",IF('Pivot elenchi'!P15="",'Pivot elenchi'!P14="",'Pivot elenchi'!P15)) -> 215000 | M16: =IF(AND('Pivot elenchi'!Q15="",'Pivot elenchi'!Q16=""),"",IF('Pivot elenchi'!Q15="",'Pivot elenchi'!Q14="",'Pivot elenchi'!Q15)) -> BILANCIO | N16: =IF(AND('Pivot elenchi'!R15="",'Pivot elenchi'!R16=""),"",IF('Pivot elenchi'!R15="",'Pivot elenchi'!R14="",'Pivot elenchi'!R15)) | O16: =IF(AND('Pivot elenchi'!S15="",'Pivot elenchi'!S16=""),"",IF('Pivot elenchi'!S15="",'Pivot elenchi'!S14="",'Pivot elenchi'!S15)) -> AMMINISTRAZIONE E BILANCIO | P16: =IF(AND('Pivot elenchi'!T15="",'Pivot elenchi'!T16=""),"",IF('Pivot elenchi'!T15="",'Pivot elenchi'!T14="",'Pivot elenchi'!T15)) | Q16: =IF(AND('Pivot elenchi'!U15="",'Pivot elenchi'!U16=""),"",IF('Pivot elenchi'!U15="",'Pivot elenchi'!U14="",'Pivot elenchi'!U15)) -> AMMINISTRAZIONE, FINANZA E CONTROLLO | R16: @ilsole24ore.com | T16: =IF('Pivot elenchi'!D13="","",'Pivot elenchi'!D13) | U16: =IF('Pivot elenchi'!C13="","",'Pivot elenchi'!C13) | W16: =IF(G16="","",G16) -> VIALE IV NOVEMBRE 6 - GENOVA (GE) | X16: =IF(H16="","",H16) -> GENOVA | Y16: =IF(I16="","",I16) -> GENOVA | Z16: =IF(J16="","",J16) -> 80 | AB16: =L16 -> 215000 | AC16: =M16 -> BILANCIO | AD16: =N16 | AE16: =O16 -> AMMINISTRAZIONE E BILANCIO | AF16: =P16 | AG16: =Q16 -> AMMINISTRAZIONE, FINANZA E CONTROLLO
D17: =IF('Pivot elenchi'!D14="","",'Pivot elenchi'!D14) | E17: =IF('Pivot elenchi'!C14="","",'Pivot elenchi'!C14) | G17: =IF('Pivot elenchi'!I14="","",'Pivot elenchi'!I14) -> Corrisp. ESTERO | H17: EE | I17: =IF('Pivot elenchi'!J14="","",'Pivot elenchi'!J14) -> EE | J17: =IF('Pivot elenchi'!H14="","",'Pivot elenchi'!H14) -> 99 | L17: =IF(AND('Pivot elenchi'!P16="",'Pivot elenchi'!P17=""),"",IF('Pivot elenchi'!P16="",'Pivot elenchi'!P15="",'Pivot elenchi'!P16)) -> 215100 | M17: =IF(AND('Pivot elenchi'!Q16="",'Pivot elenchi'!Q17=""),"",IF('Pivot elenchi'!Q16="",'Pivot elenchi'!Q15="",'Pivot elenchi'!Q16)) -> CREDIT MANAGEMENT | N17: =IF(AND('Pivot elenchi'!R16="",'Pivot elenchi'!R17=""),"",IF('Pivot elenchi'!R16="",'Pivot elenchi'!R15="",'Pivot elenchi'!R16)) | O17: =IF(AND('Pivot elenchi'!S16="",'Pivot elenchi'!S17=""),"",IF('Pivot elenchi'!S16="",'Pivot elenchi'!S15="",'Pivot elenchi'!S16)) -> FINANZA, TESORERIA E RISK MANAGEMENT | P17: =IF(AND('Pivot elenchi'!T16="",'Pivot elenchi'!T17=""),"",IF('Pivot elenchi'!T16="",'Pivot elenchi'!T15="",'Pivot elenchi'!T16)) | Q17: =IF(AND('Pivot elenchi'!U16="",'Pivot elenchi'!U17=""),"",IF('Pivot elenchi'!U16="",'Pivot elenchi'!U15="",'Pivot elenchi'!U16)) -> AMMINISTRAZIONE, FINANZA E CONTROLLO | R17: @ilsole24ore.com | T17: =IF('Pivot elenchi'!D14="","",'Pivot elenchi'!D14) | U17: =IF('Pivot elenchi'!C14="","",'Pivot elenchi'!C14) | W17: =IF(G17="","",G17) -> Corrisp. ESTERO | X17: =IF(H17="","",H17) -> EE | Y17: =IF(I17="","",I17) -> EE | Z17: =IF(J17="","",J17) -> 99 | AB17: =L17 -> 215100 | AC17: =M17 -> CREDIT MANAGEMENT | AD17: =N17 | AE17: =O17 -> FINANZA, TESORERIA E RISK MANAGEMENT | AF17: =P17 | AG17: =Q17 -> AMMINISTRAZIONE, FINANZA E CONTROLLO
A18: E-mail prefisso "EXT." | D18: =IF('Pivot elenchi'!D15="","",'Pivot elenchi'!D15) | E18: =IF('Pivot elenchi'!C15="","",'Pivot elenchi'!C15) | G18: =IF('Pivot elenchi'!I15="","",'Pivot elenchi'!I15) | I18: =IF('Pivot elenchi'!J15="","",'Pivot elenchi'!J15) | J18: =IF('Pivot elenchi'!H15="","",'Pivot elenchi'!H15) | L18: =IF(AND('Pivot elenchi'!P17="",'Pivot elenchi'!P18=""),"",IF('Pivot elenchi'!P17="",'Pivot elenchi'!P16="",'Pivot elenchi'!P17)) -> 21520011 | M18: =IF(AND('Pivot elenchi'!Q17="",'Pivot elenchi'!Q18=""),"",IF('Pivot elenchi'!Q17="",'Pivot elenchi'!Q16="",'Pivot elenchi'!Q17)) -> CONTABILITA' GENERALE | N18: =IF(AND('Pivot elenchi'!R17="",'Pivot elenchi'!R18=""),"",IF('Pivot elenchi'!R17="",'Pivot elenchi'!R16="",'Pivot elenchi'!R17)) | O18: =IF(AND('Pivot elenchi'!S17="",'Pivot elenchi'!S18=""),"",IF('Pivot elenchi'!S17="",'Pivot elenchi'!S16="",'Pivot elenchi'!S17)) -> AMMINISTRAZIONE E BILANCIO | P18: =IF(AND('Pivot elenchi'!T17="",'Pivot elenchi'!T18=""),"",IF('Pivot elenchi'!T17="",'Pivot elenchi'!T16="",'Pivot elenchi'!T17)) | Q18: =IF(AND('Pivot elenchi'!U17="",'Pivot elenchi'!U18=""),"",IF('Pivot elenchi'!U17="",'Pivot elenchi'!U16="",'Pivot elenchi'!U17)) -> AMMINISTRAZIONE, FINANZA E CONTROLLO | R18: @ilsole24ore.com | T18: =IF('Pivot elenchi'!D15="","",'Pivot elenchi'!D15) | U18: =IF('Pivot elenchi'!C15="","",'Pivot elenchi'!C15) | W18: =IF(G18="","",G18) | X18: =IF(H18="","",H18) | Y18: =IF(I18="","",I18) | Z18: =IF(J18="","",J18) | AB18: =L18 -> 21520011 | AC18: =M18 -> CONTABILITA' GENERALE | AD18: =N18 | AE18: =O18 -> AMMINISTRAZIONE E BILANCIO | AF18: =P18 | AG18: =Q18 -> AMMINISTRAZIONE, FINANZA E CONTROLLO
A19: Si EXT. | D19: =IF('Pivot elenchi'!D16="","",'Pivot elenchi'!D16) | E19: =IF('Pivot elenchi'!C16="","",'Pivot elenchi'!C16) | G19: =IF('Pivot elenchi'!I16="","",'Pivot elenchi'!I16) | I19: =IF('Pivot elenchi'!J16="","",'Pivot elenchi'!J16) | J19: =IF('Pivot elenchi'!H16="","",'Pivot elenchi'!H16) | L19: =IF(AND('Pivot elenchi'!P18="",'Pivot elenchi'!P19=""),"",IF('Pivot elenchi'!P18="",'Pivot elenchi'!P17="",'Pivot elenchi'!P18)) -> 21520012 | M19: =IF(AND('Pivot elenchi'!Q18="",'Pivot elenchi'!Q19=""),"",IF('Pivot elenchi'!Q18="",'Pivot elenchi'!Q17="",'Pivot elenchi'!Q18)) -> CONTABILITA' FORNITORI | N19: =IF(AND('Pivot elenchi'!R18="",'Pivot elenchi'!R19=""),"",IF('Pivot elenchi'!R18="",'Pivot elenchi'!R17="",'Pivot elenchi'!R18)) | O19: =IF(AND('Pivot elenchi'!S18="",'Pivot elenchi'!S19=""),"",IF('Pivot elenchi'!S18="",'Pivot elenchi'!S17="",'Pivot elenchi'!S18)) -> AMMINISTRAZIONE E BILANCIO | P19: =IF(AND('Pivot elenchi'!T18="",'Pivot elenchi'!T19=""),"",IF('Pivot elenchi'!T18="",'Pivot elenchi'!T17="",'Pivot elenchi'!T18)) | Q19: =IF(AND('Pivot elenchi'!U18="",'Pivot elenchi'!U19=""),"",IF('Pivot elenchi'!U18="",'Pivot elenchi'!U17="",'Pivot elenchi'!U18)) -> AMMINISTRAZIONE, FINANZA E CONTROLLO | R19: @ilsole24ore.com | T19: =IF('Pivot elenchi'!D16="","",'Pivot elenchi'!D16) | U19: =IF('Pivot elenchi'!C16="","",'Pivot elenchi'!C16) | W19: =IF(G19="","",G19) | X19: =IF(H19="","",H19) | Y19: =IF(I19="","",I19) | Z19: =IF(J19="","",J19) | AB19: =L19 -> 21520012 | AC19: =M19 -> CONTABILITA' FORNITORI | AD19: =N19 | AE19: =O19 -> AMMINISTRAZIONE E BILANCIO | AF19: =P19 | AG19: =Q19 -> AMMINISTRAZIONE, FINANZA E CONTROLLO
A20: NO | D20: =IF('Pivot elenchi'!D17="","",'Pivot elenchi'!D17) | E20: =IF('Pivot elenchi'!C17="","",'Pivot elenchi'!C17) | G20: Altra Sede | J20: np | L20: =IF(AND('Pivot elenchi'!P19="",'Pivot elenchi'!P20=""),"",IF('Pivot elenchi'!P19="",'Pivot elenchi'!P18="",'Pivot elenchi'!P19)) -> 21520013 | M20: =IF(AND('Pivot elenchi'!Q19="",'Pivot elenchi'!Q20=""),"",IF('Pivot elenchi'!Q19="",'Pivot elenchi'!Q18="",'Pivot elenchi'!Q19)) -> CONTABILITA' CLIENTI | N20: =IF(AND('Pivot elenchi'!R19="",'Pivot elenchi'!R20=""),"",IF('Pivot elenchi'!R19="",'Pivot elenchi'!R18="",'Pivot elenchi'!R19)) | O20: =IF(AND('Pivot elenchi'!S19="",'Pivot elenchi'!S20=""),"",IF('Pivot elenchi'!S19="",'Pivot elenchi'!S18="",'Pivot elenchi'!S19)) -> AMMINISTRAZIONE E BILANCIO | P20: =IF(AND('Pivot elenchi'!T19="",'Pivot elenchi'!T20=""),"",IF('Pivot elenchi'!T19="",'Pivot elenchi'!T18="",'Pivot elenchi'!T19)) | Q20: =IF(AND('Pivot elenchi'!U19="",'Pivot elenchi'!U20=""),"",IF('Pivot elenchi'!U19="",'Pivot elenchi'!U18="",'Pivot elenchi'!U19)) -> AMMINISTRAZIONE, FINANZA E CONTROLLO | R20: @ilsole24ore.com | W20: =IF(G20="","",G20) -> Altra Sede | X20: =IF(H20="","",H20) | Y20: =IF(I20="","",I20) | Z20: =IF(J20="","",J20) -> np | AB20: =L20 -> 21520013 | AC20: =M20 -> CONTABILITA' CLIENTI | AD20: =N20 | AE20: =O20 -> AMMINISTRAZIONE E BILANCIO | AF20: =P20 | AG20: =Q20 -> AMMINISTRAZIONE, FINANZA E CONTROLLO
D21: =IF('Pivot elenchi'!D18="","",'Pivot elenchi'!D18) | E21: =IF('Pivot elenchi'!C18="","",'Pivot elenchi'!C18) | G21: =IF('Pivot elenchi'!I18="","",'Pivot elenchi'!I18) | I21: =IF('Pivot elenchi'!J18="","",'Pivot elenchi'!J18) | J21: =IF('Pivot elenchi'!H18="","",'Pivot elenchi'!H18) | L21: =IF(AND('Pivot elenchi'!P20="",'Pivot elenchi'!P21=""),"",IF('Pivot elenchi'!P20="",'Pivot elenchi'!P19="",'Pivot elenchi'!P20)) -> 215500 | M21: =IF(AND('Pivot elenchi'!Q20="",'Pivot elenchi'!Q21=""),"",IF('Pivot elenchi'!Q20="",'Pivot elenchi'!Q19="",'Pivot elenchi'!Q20)) -> FINANZA, TESORERIA E RISK MAN | N21: =IF(AND('Pivot elenchi'!R20="",'Pivot elenchi'!R21=""),"",IF('Pivot elenchi'!R20="",'Pivot elenchi'!R19="",'Pivot elenchi'!R20)) | O21: =IF(AND('Pivot elenchi'!S20="",'Pivot elenchi'!S21=""),"",IF('Pivot elenchi'!S20="",'Pivot elenchi'!S19="",'Pivot elenchi'!S20)) -> FINANZA, TESORERIA E RISK MANAGEMENT | P21: =IF(AND('Pivot elenchi'!T20="",'Pivot elenchi'!T21=""),"",IF('Pivot elenchi'!T20="",'Pivot elenchi'!T19="",'Pivot elenchi'!T20)) | Q21: =IF(AND('Pivot elenchi'!U20="",'Pivot elenchi'!U21=""),"",IF('Pivot elenchi'!U20="",'Pivot elenchi'!U19="",'Pivot elenchi'!U20)) -> AMMINISTRAZIONE, FINANZA E CONTROLLO | R21: @ilsole24ore.com | W21: =IF(G21="","",G21) | X21: =IF(H21="","",H21) | Y21: =IF(I21="","",I21) | Z21: =IF(J21="","",J21) | AB21: =L21 -> 215500 | AC21: =M21 -> FINANZA, TESORERIA E RISK MAN | AD21: =N21 | AE21: =O21 -> FINANZA, TESORERIA E RISK MANAGEMENT | AF21: =P21 | AG21: =Q21 -> AMMINISTRAZIONE, FINANZA E CONTROLLO
G22: =IF('Pivot elenchi'!I19="","",'Pivot elenchi'!I19) | I22: =IF('Pivot elenchi'!J19="","",'Pivot elenchi'!J19) | J22: =IF('Pivot elenchi'!H19="","",'Pivot elenchi'!H19) | L22: =IF(AND('Pivot elenchi'!P21="",'Pivot elenchi'!P22=""),"",IF('Pivot elenchi'!P21="",'Pivot elenchi'!P20="",'Pivot elenchi'!P21)) -> 21550001 | M22: =IF(AND('Pivot elenchi'!Q21="",'Pivot elenchi'!Q22=""),"",IF('Pivot elenchi'!Q21="",'Pivot elenchi'!Q20="",'Pivot elenchi'!Q21)) -> TESORERIA E RISK MANAGEMENT | N22: =IF(AND('Pivot elenchi'!R21="",'Pivot elenchi'!R22=""),"",IF('Pivot elenchi'!R21="",'Pivot elenchi'!R20="",'Pivot elenchi'!R21)) | O22: =IF(AND('Pivot elenchi'!S21="",'Pivot elenchi'!S22=""),"",IF('Pivot elenchi'!S21="",'Pivot elenchi'!S20="",'Pivot elenchi'!S21)) -> FINANZA, TESORERIA E RISK MANAGEMENT | P22: =IF(AND('Pivot elenchi'!T21="",'Pivot elenchi'!T22=""),"",IF('Pivot elenchi'!T21="",'Pivot elenchi'!T20="",'Pivot elenchi'!T21)) | Q22: =IF(AND('Pivot elenchi'!U21="",'Pivot elenchi'!U22=""),"",IF('Pivot elenchi'!U21="",'Pivot elenchi'!U20="",'Pivot elenchi'!U21)) -> AMMINISTRAZIONE, FINANZA E CONTROLLO | R22: @ilsole24ore.com | W22: =IF(G22="","",G22) | X22: =IF(H22="","",H22) | Y22: =IF(I22="","",I22) | Z22: =IF(J22="","",J22) | AB22: =L22 -> 21550001 | AC22: =M22 -> TESORERIA E RISK MANAGEMENT | AD22: =N22 | AE22: =O22 -> FINANZA, TESORERIA E RISK MANAGEMENT | AF22: =P22 | AG22: =Q22 -> AMMINISTRAZIONE, FINANZA E CONTROLLO
A23: Telelavoro | G23: =IF('Pivot elenchi'!I20="","",'Pivot elenchi'!I20) | I23: =IF('Pivot elenchi'!J20="","",'Pivot elenchi'!J20) | J23: =IF('Pivot elenchi'!H20="","",'Pivot elenchi'!H20) | L23: =IF(AND('Pivot elenchi'!P22="",'Pivot elenchi'!P23=""),"",IF('Pivot elenchi'!P22="",'Pivot elenchi'!P21="",'Pivot elenchi'!P22)) -> 310000 | M23: =IF(AND('Pivot elenchi'!Q22="",'Pivot elenchi'!Q23=""),"",IF('Pivot elenchi'!Q22="",'Pivot elenchi'!Q21="",'Pivot elenchi'!Q22)) -> DIR. CENTR. PERSONALE E ORG. | N23: =IF(AND('Pivot elenchi'!R22="",'Pivot elenchi'!R23=""),"",IF('Pivot elenchi'!R22="",'Pivot elenchi'!R21="",'Pivot elenchi'!R22)) | O23: =IF(AND('Pivot elenchi'!S22="",'Pivot elenchi'!S23=""),"",IF('Pivot elenchi'!S22="",'Pivot elenchi'!S21="",'Pivot elenchi'!S22)) -> DIREZIONE PERSONALE | P23: =IF(AND('Pivot elenchi'!T22="",'Pivot elenchi'!T23=""),"",IF('Pivot elenchi'!T22="",'Pivot elenchi'!T21="",'Pivot elenchi'!T22)) | Q23: =IF(AND('Pivot elenchi'!U22="",'Pivot elenchi'!U23=""),"",IF('Pivot elenchi'!U22="",'Pivot elenchi'!U21="",'Pivot elenchi'!U22)) -> DIREZIONE CENTRALE PERSONALE E ORGANIZZA | R23: @ilsole24ore.com | W23: =IF(G23="","",G23) | X23: =IF(H23="","",H23) | Y23: =IF(I23="","",I23) | Z23: =IF(J23="","",J23) | AB23: =L23 -> 310000 | AC23: =M23 -> DIR. CENTR. PERSONALE E ORG. | AD23: =N23 | AE23: =O23 -> DIREZIONE PERSONALE | AF23: =P23 | AG23: =Q23 -> DIREZIONE CENTRALE PERSONALE E ORGANIZZA
A24: NO | G24: =IF('Pivot elenchi'!I21="","",'Pivot elenchi'!I21) | I24: =IF('Pivot elenchi'!J21="","",'Pivot elenchi'!J21) | J24: =IF('Pivot elenchi'!H21="","",'Pivot elenchi'!H21) | L24: =IF(AND('Pivot elenchi'!P23="",'Pivot elenchi'!P24=""),"",IF('Pivot elenchi'!P23="",'Pivot elenchi'!P22="",'Pivot elenchi'!P23)) -> 31000010 | M24: =IF(AND('Pivot elenchi'!Q23="",'Pivot elenchi'!Q24=""),"",IF('Pivot elenchi'!Q23="",'Pivot elenchi'!Q22="",'Pivot elenchi'!Q23)) -> GEST.PERSONALE DIR.FUNZ.CENTR. | N24: =IF(AND('Pivot elenchi'!R23="",'Pivot elenchi'!R24=""),"",IF('Pivot elenchi'!R23="",'Pivot elenchi'!R22="",'Pivot elenchi'!R23)) | O24: =IF(AND('Pivot elenchi'!S23="",'Pivot elenchi'!S24=""),"",IF('Pivot elenchi'!S23="",'Pivot elenchi'!S22="",'Pivot elenchi'!S23)) -> DIREZIONE PERSONALE | P24: =IF(AND('Pivot elenchi'!T23="",'Pivot elenchi'!T24=""),"",IF('Pivot elenchi'!T23="",'Pivot elenchi'!T22="",'Pivot elenchi'!T23)) | Q24: =IF(AND('Pivot elenchi'!U23="",'Pivot elenchi'!U24=""),"",IF('Pivot elenchi'!U23="",'Pivot elenchi'!U22="",'Pivot elenchi'!U23)) -> DIREZIONE CENTRALE PERSONALE E ORGANIZZA | R24: @ilsole24ore.com | W24: =IF(G26="","",G26) | X24: =IF(H26="","",H26) | Y24: =IF(I26="","",I26) | Z24: =IF(J26="","",J26) | AB24: =L24 -> 31000010 | AC24: =M24 -> GEST.PERSONALE DIR.FUNZ.CENTR. | AD24: =N24 | AE24: =O24 -> DIREZIONE PERSONALE | AF24: =P24 | AG24: =Q24 -> DIREZIONE CENTRALE PERSONALE E ORGANIZZA
A25: SI | L25: =IF(AND('Pivot elenchi'!P24="",'Pivot elenchi'!P25=""),"",IF('Pivot elenchi'!P24="",'Pivot elenchi'!P23="",'Pivot elenchi'!P24)) -> 31000020 | M25: =IF(AND('Pivot elenchi'!Q24="",'Pivot elenchi'!Q25=""),"",IF('Pivot elenchi'!Q24="",'Pivot elenchi'!Q23="",'Pivot elenchi'!Q24)) -> ORGANIZZAZIONE | N25: =IF(AND('Pivot elenchi'!R24="",'Pivot elenchi'!R25=""),"",IF('Pivot elenchi'!R24="",'Pivot elenchi'!R23="",'Pivot elenchi'!R24)) | O25: =IF(AND('Pivot elenchi'!S24="",'Pivot elenchi'!S25=""),"",IF('Pivot elenchi'!S24="",'Pivot elenchi'!S23="",'Pivot elenchi'!S24)) -> DIREZIONE PERSONALE | P25: =IF(AND('Pivot elenchi'!T24="",'Pivot elenchi'!T25=""),"",IF('Pivot elenchi'!T24="",'Pivot elenchi'!T23="",'Pivot elenchi'!T24)) | Q25: =IF(AND('Pivot elenchi'!U24="",'Pivot elenchi'!U25=""),"",IF('Pivot elenchi'!U24="",'Pivot elenchi'!U23="",'Pivot elenchi'!U24)) -> DIREZIONE CENTRALE PERSONALE E ORGANIZZA | R25: @ilsole24ore.com | W25: =IF(G27="","",G27) | X25: =IF(H27="","",H27) | Y25: =IF(I27="","",I27) | Z25: =IF(J27="","",J27) | AB25: =L25 -> 31000020 | AC25: =M25 -> ORGANIZZAZIONE | AD25: =N25 | AE25: =O25 -> DIREZIONE PERSONALE | AF25: =P25 | AG25: =Q25 -> DIREZIONE CENTRALE PERSONALE E ORGANIZZA
L26: =IF(AND('Pivot elenchi'!P25="",'Pivot elenchi'!P26=""),"",IF('Pivot elenchi'!P25="",'Pivot elenchi'!P24="",'Pivot elenchi'!P25)) -> 311000 | M26: =IF(AND('Pivot elenchi'!Q25="",'Pivot elenchi'!Q26=""),"",IF('Pivot elenchi'!Q25="",'Pivot elenchi'!Q24="",'Pivot elenchi'!Q25)) -> GEST.PERSONALE DIR.IT E BUSINES | N26: =IF(AND('Pivot elenchi'!R25="",'Pivot elenchi'!R26=""),"",IF('Pivot elenchi'!R25="",'Pivot elenchi'!R24="",'Pivot elenchi'!R25)) | O26: =IF(AND('Pivot elenchi'!S25="",'Pivot elenchi'!S26=""),"",IF('Pivot elenchi'!S25="",'Pivot elenchi'!S24="",'Pivot elenchi'!S25)) -> DIREZIONE PERSONALE | P26: =IF(AND('Pivot elenchi'!T25="",'Pivot elenchi'!T26=""),"",IF('Pivot elenchi'!T25="",'Pivot elenchi'!T24="",'Pivot elenchi'!T25)) | Q26: =IF(AND('Pivot elenchi'!U25="",'Pivot elenchi'!U26=""),"",IF('Pivot elenchi'!U25="",'Pivot elenchi'!U24="",'Pivot elenchi'!U25)) -> DIREZIONE CENTRALE PERSONALE E ORGANIZZA | R26: @ilsole24ore.com | W26: =IF(G28="","",G28) | X26: =IF(H28="","",H28) | Y26: =IF(I28="","",I28) | Z26: =IF(J28="","",J28) | AB26: =L26 -> 311000 | AC26: =M26 -> GEST.PERSONALE DIR.IT E BUSINES | AD26: =N26 | AE26: =O26 -> DIREZIONE PERSONALE | AF26: =P26 | AG26: =Q26 -> DIREZIONE CENTRALE PERSONALE E ORGANIZZA
A27: =IF('Scheda Movimento'!C9="","",'Scheda Movimento'!C9) -> Femminile | B27: =IF(A27="","",VLOOKUP(A27,A29:B32,2,FALSE)) -> F | L27: =IF(AND('Pivot elenchi'!P26="",'Pivot elenchi'!P27=""),"",IF('Pivot elenchi'!P26="",'Pivot elenchi'!P25="",'Pivot elenchi'!P26)) -> 312000 | M27: =IF(AND('Pivot elenchi'!Q26="",'Pivot elenchi'!Q27=""),"",IF('Pivot elenchi'!Q26="",'Pivot elenchi'!Q25="",'Pivot elenchi'!Q26)) -> NORME E AMMINISTR DEL PERSONALE | N27: =IF(AND('Pivot elenchi'!R26="",'Pivot elenchi'!R27=""),"",IF('Pivot elenchi'!R26="",'Pivot elenchi'!R25="",'Pivot elenchi'!R26)) | O27: =IF(AND('Pivot elenchi'!S26="",'Pivot elenchi'!S27=""),"",IF('Pivot elenchi'!S26="",'Pivot elenchi'!S25="",'Pivot elenchi'!S26)) -> DIREZIONE PERSONALE | P27: =IF(AND('Pivot elenchi'!T26="",'Pivot elenchi'!T27=""),"",IF('Pivot elenchi'!T26="",'Pivot elenchi'!T25="",'Pivot elenchi'!T26)) | Q27: =IF(AND('Pivot elenchi'!U26="",'Pivot elenchi'!U27=""),"",IF('Pivot elenchi'!U26="",'Pivot elenchi'!U25="",'Pivot elenchi'!U26)) -> DIREZIONE CENTRALE PERSONALE E ORGANIZZA | R27: @ilsole24ore.com | W27: =IF(G29="","",G29) | X27: =IF(H29="","",H29) | Y27: =IF(I29="","",I29) | Z27: =IF(J29="","",J29) | AB27: =L27 -> 312000 | AC27: =M27 -> NORME E AMMINISTR DEL PERSONALE | AD27: =N27 | AE27: =O27 -> DIREZIONE PERSONALE | AF27: =P27 | AG27: =Q27 -> DIREZIONE CENTRALE PERSONALE E ORGANIZZA
A28: Sesso | B28: COD | D28: Suffissi email | L28: =IF(AND('Pivot elenchi'!P27="",'Pivot elenchi'!P28=""),"",IF('Pivot elenchi'!P27="",'Pivot elenchi'!P26="",'Pivot elenchi'!P27)) -> 412620 | M28: =IF(AND('Pivot elenchi'!Q27="",'Pivot elenchi'!Q28=""),"",IF('Pivot elenchi'!Q27="",'Pivot elenchi'!Q26="",'Pivot elenchi'!Q27)) -> COORDINAMENTO TECNICO PRODUTTIV | N28: =IF(AND('Pivot elenchi'!R27="",'Pivot elenchi'!R28=""),"",IF('Pivot elenchi'!R27="",'Pivot elenchi'!R26="",'Pivot elenchi'!R27)) | O28: =IF(AND('Pivot elenchi'!S27="",'Pivot elenchi'!S28=""),"",IF('Pivot elenchi'!S27="",'Pivot elenchi'!S26="",'Pivot elenchi'!S27)) -> OPERATIONS DG P&D | P28: =IF(AND('Pivot elenchi'!T27="",'Pivot elenchi'!T28=""),"",IF('Pivot elenchi'!T27="",'Pivot elenchi'!T26="",'Pivot elenchi'!T27)) | Q28: =IF(AND('Pivot elenchi'!U27="",'Pivot elenchi'!U28=""),"",IF('Pivot elenchi'!U27="",'Pivot elenchi'!U26="",'Pivot elenchi'!U27)) -> DG M&B - DG PUBLISHING & DIGITAL | R28: @ilsole24ore.com | AB28: =L28 -> 412620 | AC28: =M28 -> COORDINAMENTO TECNICO PRODUTTIV | AD28: =N28 | AE28: =O28 -> OPERATIONS DG P&D | AF28: =P28 | AG28: =Q28 -> DG M&B - DG PUBLISHING & DIGITAL
L29: =IF(AND('Pivot elenchi'!P28="",'Pivot elenchi'!P29=""),"",IF('Pivot elenchi'!P28="",'Pivot elenchi'!P27="",'Pivot elenchi'!P28)) -> 412700 | M29: =IF(AND('Pivot elenchi'!Q28="",'Pivot elenchi'!Q29=""),"",IF('Pivot elenchi'!Q28="",'Pivot elenchi'!Q27="",'Pivot elenchi'!Q28)) -> PREP. EDITORIALE PROFESSIONALE | N29: =IF(AND('Pivot elenchi'!R28="",'Pivot elenchi'!R29=""),"",IF('Pivot elenchi'!R28="",'Pivot elenchi'!R27="",'Pivot elenchi'!R28)) | O29: =IF(AND('Pivot elenchi'!S28="",'Pivot elenchi'!S29=""),"",IF('Pivot elenchi'!S28="",'Pivot elenchi'!S27="",'Pivot elenchi'!S28)) -> OPERATIONS E CUSTOMER ENGAGEMENT | P29: =IF(AND('Pivot elenchi'!T28="",'Pivot elenchi'!T29=""),"",IF('Pivot elenchi'!T28="",'Pivot elenchi'!T27="",'Pivot elenchi'!T28)) | Q29: =IF(AND('Pivot elenchi'!U28="",'Pivot elenchi'!U29=""),"",IF('Pivot elenchi'!U28="",'Pivot elenchi'!U27="",'Pivot elenchi'!U28)) -> DG SERVIZI PROFESSIONALI E FORMAZIONE | R29: @ilsole24ore.com | AB29: =L29 -> 412700 | AC29: =M29 -> PREP. EDITORIALE PROFESSIONALE | AD29: =N29 | AE29: =O29 -> OPERATIONS E CUSTOMER ENGAGEMENT | AF29: =P29 | AG29: =Q29 -> DG SERVIZI PROFESSIONALI E FORMAZIONE
A30: Maschile | B30: M | D30: @ilsole24ore.com | L30: =IF(AND('Pivot elenchi'!P29="",'Pivot elenchi'!P30=""),"",IF('Pivot elenchi'!P29="",'Pivot elenchi'!P28="",'Pivot elenchi'!P29)) -> 413000 | M30: =IF(AND('Pivot elenchi'!Q29="",'Pivot elenchi'!Q30=""),"",IF('Pivot elenchi'!Q29="",'Pivot elenchi'!Q28="",'Pivot elenchi'!Q29)) -> ACQUISTI | N30: =IF(AND('Pivot elenchi'!R29="",'Pivot elenchi'!R30=""),"",IF('Pivot elenchi'!R29="",'Pivot elenchi'!R28="",'Pivot elenchi'!R29)) | O30: =IF(AND('Pivot elenchi'!S29="",'Pivot elenchi'!S30=""),"",IF('Pivot elenchi'!S29="",'Pivot elenchi'!S28="",'Pivot elenchi'!S29)) -> ACQUISTI | P30: =IF(AND('Pivot elenchi'!T29="",'Pivot elenchi'!T30=""),"",IF('Pivot elenchi'!T29="",'Pivot elenchi'!T28="",'Pivot elenchi'!T29)) | Q30: =IF(AND('Pivot elenchi'!U29="",'Pivot elenchi'!U30=""),"",IF('Pivot elenchi'!U29="",'Pivot elenchi'!U28="",'Pivot elenchi'!U29)) -> DIREZIONE CENTRALE PERSONALE E ORGANIZZA | R30: @ilsole24ore.com | AB30: =L30 -> 413000 | AC30: =M30 -> ACQUISTI | AD30: =N30 | AE30: =O30 -> ACQUISTI | AF30: =P30 | AG30: =Q30 -> DIREZIONE CENTRALE PERSONALE E ORGANIZZA
A31: Femminile | B31: F | D31: @24orecultura.com | L31: =IF(AND('Pivot elenchi'!P30="",'Pivot elenchi'!P31=""),"",IF('Pivot elenchi'!P30="",'Pivot elenchi'!P29="",'Pivot elenchi'!P30)) -> 414000 | M31: =IF(AND('Pivot elenchi'!Q30="",'Pivot elenchi'!Q31=""),"",IF('Pivot elenchi'!Q30="",'Pivot elenchi'!Q29="",'Pivot elenchi'!Q30)) -> SERVIZI GENERALI SICUREZZA E AM | N31: =IF(AND('Pivot elenchi'!R30="",'Pivot elenchi'!R31=""),"",IF('Pivot elenchi'!R30="",'Pivot elenchi'!R29="",'Pivot elenchi'!R30)) | O31: =IF(AND('Pivot elenchi'!S30="",'Pivot elenchi'!S31=""),"",IF('Pivot elenchi'!S30="",'Pivot elenchi'!S29="",'Pivot elenchi'!S30)) -> SERVIZI GENERALI SICUREZZA E AMBIENTE | P31: =IF(AND('Pivot elenchi'!T30="",'Pivot elenchi'!T31=""),"",IF('Pivot elenchi'!T30="",'Pivot elenchi'!T29="",'Pivot elenchi'!T30)) | Q31: =IF(AND('Pivot elenchi'!U30="",'Pivot elenchi'!U31=""),"",IF('Pivot elenchi'!U30="",'Pivot elenchi'!U29="",'Pivot elenchi'!U30)) -> DIREZIONE CENTRALE PERSONALE E ORGANIZZA | R31: @ilsole24ore.com | AB31: =L31 -> 414000 | AC31: =M31 -> SERVIZI GENERALI SICUREZZA E AM | AD31: =N31 | AE31: =O31 -> SERVIZI GENERALI SICUREZZA E AMBIENTE | AF31: =P31 | AG31: =Q31 -> DIREZIONE CENTRALE PERSONALE E ORGANIZZA
D32: @radio24.it | L32: =IF(AND('Pivot elenchi'!P31="",'Pivot elenchi'!P32=""),"",IF('Pivot elenchi'!P31="",'Pivot elenchi'!P30="",'Pivot elenchi'!P31)) -> 41400001 | M32: =IF(AND('Pivot elenchi'!Q31="",'Pivot elenchi'!Q32=""),"",IF('Pivot elenchi'!Q31="",'Pivot elenchi'!Q30="",'Pivot elenchi'!Q31)) -> SUPPORTO TECNICO E HSE | N32: =IF(AND('Pivot elenchi'!R31="",'Pivot elenchi'!R32=""),"",IF('Pivot elenchi'!R31="",'Pivot elenchi'!R30="",'Pivot elenchi'!R31)) | O32: =IF(AND('Pivot elenchi'!S31="",'Pivot elenchi'!S32=""),"",IF('Pivot elenchi'!S31="",'Pivot elenchi'!S30="",'Pivot elenchi'!S31)) -> SERVIZI GENERALI SICUREZZA E AMBIENTE | P32: =IF(AND('Pivot elenchi'!T31="",'Pivot elenchi'!T32=""),"",IF('Pivot elenchi'!T31="",'Pivot elenchi'!T30="",'Pivot elenchi'!T31)) | Q32: =IF(AND('Pivot elenchi'!U31="",'Pivot elenchi'!U32=""),"",IF('Pivot elenchi'!U31="",'Pivot elenchi'!U30="",'Pivot elenchi'!U31)) -> DIREZIONE CENTRALE PERSONALE E ORGANIZZA | R32: @ilsole24ore.com | AB32: =L32 -> 41400001 | AC32: =M32 -> SUPPORTO TECNICO E HSE | AD32: =N32 | AE32: =O32 -> SERVIZI GENERALI SICUREZZA E AMBIENTE | AF32: =P32 | AG32: =Q32 -> DIREZIONE CENTRALE PERSONALE E ORGANIZZA
L33: =IF(AND('Pivot elenchi'!P32="",'Pivot elenchi'!P33=""),"",IF('Pivot elenchi'!P32="",'Pivot elenchi'!P31="",'Pivot elenchi'!P32)) -> 414100 | M33: =IF(AND('Pivot elenchi'!Q32="",'Pivot elenchi'!Q33=""),"",IF('Pivot elenchi'!Q32="",'Pivot elenchi'!Q31="",'Pivot elenchi'!Q32)) -> COORDINAMENTO OPERATIVO | N33: =IF(AND('Pivot elenchi'!R32="",'Pivot elenchi'!R33=""),"",IF('Pivot elenchi'!R32="",'Pivot elenchi'!R31="",'Pivot elenchi'!R32)) | O33: =IF(AND('Pivot elenchi'!S32="",'Pivot elenchi'!S33=""),"",IF('Pivot elenchi'!S32="",'Pivot elenchi'!S31="",'Pivot elenchi'!S32)) -> SERVIZI GENERALI SICUREZZA E AMBIENTE | P33: =IF(AND('Pivot elenchi'!T32="",'Pivot elenchi'!T33=""),"",IF('Pivot elenchi'!T32="",'Pivot elenchi'!T31="",'Pivot elenchi'!T32)) | Q33: =IF(AND('Pivot elenchi'!U32="",'Pivot elenchi'!U33=""),"",IF('Pivot elenchi'!U32="",'Pivot elenchi'!U31="",'Pivot elenchi'!U32)) -> DIREZIONE CENTRALE PERSONALE E ORGANIZZA | R33: @ilsole24ore.com | AB33: =L33 -> 414100 | AC33: =M33 -> COORDINAMENTO OPERATIVO | AD33: =N33 | AE33: =O33 -> SERVIZI GENERALI SICUREZZA E AMBIENTE | AF33: =P33 | AG33: =Q33 -> DIREZIONE CENTRALE PERSONALE E ORGANIZZA
A34: =IF('Scheda Movimento'!C21="","",'Scheda Movimento'!C21) -> Contratto a tempo indeterminato | B34: =IF(A34="","",VLOOKUP(A34,A36:B52,2,FALSE)) -> 02 | L34: =IF(AND('Pivot elenchi'!P33="",'Pivot elenchi'!P34=""),"",IF('Pivot elenchi'!P33="",'Pivot elenchi'!P32="",'Pivot elenchi'!P33)) -> 415110 | M34: =IF(AND('Pivot elenchi'!Q33="",'Pivot elenchi'!Q34=""),"",IF('Pivot elenchi'!Q33="",'Pivot elenchi'!Q32="",'Pivot elenchi'!Q33)) -> SISTEMI INFORMATICI GESTIONALI | N34: =IF(AND('Pivot elenchi'!R33="",'Pivot elenchi'!R34=""),"",IF('Pivot elenchi'!R33="",'Pivot elenchi'!R32="",'Pivot elenchi'!R33)) | O34: =IF(AND('Pivot elenchi'!S33="",'Pivot elenchi'!S34=""),"",IF('Pivot elenchi'!S33="",'Pivot elenchi'!S32="",'Pivot elenchi'!S33)) -> SISTEMI INFORMATICI GESTIONALI | P34: =IF(AND('Pivot elenchi'!T33="",'Pivot elenchi'!T34=""),"",IF('Pivot elenchi'!T33="",'Pivot elenchi'!T32="",'Pivot elenchi'!T33)) | Q34: =IF(AND('Pivot elenchi'!U33="",'Pivot elenchi'!U34=""),"",IF('Pivot elenchi'!U33="",'Pivot elenchi'!U32="",'Pivot elenchi'!U33)) -> DG I&S - DIR INFORMATION TECHNOLOGY | R34: @ilsole24ore.com | AB34: =L34 -> 415110 | AC34: =M34 -> SISTEMI INFORMATICI GESTIONALI | AD34: =N34 | AE34: =O34 -> SISTEMI INFORMATICI GESTIONALI | AF34: =P34 | AG34: =Q34 -> DG I&S - DIR INFORMATION TECHNOLOGY
A35: CONTRATTO | B35: COD | L35: =IF(AND('Pivot elenchi'!P34="",'Pivot elenchi'!P35=""),"",IF('Pivot elenchi'!P34="",'Pivot elenchi'!P33="",'Pivot elenchi'!P34)) -> 415120 | M35: =IF(AND('Pivot elenchi'!Q34="",'Pivot elenchi'!Q35=""),"",IF('Pivot elenchi'!Q34="",'Pivot elenchi'!Q33="",'Pivot elenchi'!Q34)) -> INFRASTRUTTURE E IT NETWORKING | N35: =IF(AND('Pivot elenchi'!R34="",'Pivot elenchi'!R35=""),"",IF('Pivot elenchi'!R34="",'Pivot elenchi'!R33="",'Pivot elenchi'!R34)) | O35: =IF(AND('Pivot elenchi'!S34="",'Pivot elenchi'!S35=""),"",IF('Pivot elenchi'!S34="",'Pivot elenchi'!S33="",'Pivot elenchi'!S34)) -> INFRAST, IT NETWORK. E AREA TECN RADIO24 | P35: =IF(AND('Pivot elenchi'!T34="",'Pivot elenchi'!T35=""),"",IF('Pivot elenchi'!T34="",'Pivot elenchi'!T33="",'Pivot elenchi'!T34)) | Q35: =IF(AND('Pivot elenchi'!U34="",'Pivot elenchi'!U35=""),"",IF('Pivot elenchi'!U34="",'Pivot elenchi'!U33="",'Pivot elenchi'!U34)) -> DG I&S - DIR INFORMATION TECHNOLOGY | R35: @ilsole24ore.com | AB35: =L35 -> 415120 | AC35: =M35 -> INFRASTRUTTURE E IT NETWORKING | AD35: =N35 | AE35: =O35 -> INFRAST, IT NETWORK. E AREA TECN RADIO24 | AF35: =P35 | AG35: =Q35 -> DG I&S - DIR INFORMATION TECHNOLOGY
L36: =IF(AND('Pivot elenchi'!P35="",'Pivot elenchi'!P36=""),"",IF('Pivot elenchi'!P35="",'Pivot elenchi'!P34="",'Pivot elenchi'!P35)) -> 415130 | M36: =IF(AND('Pivot elenchi'!Q35="",'Pivot elenchi'!Q36=""),"",IF('Pivot elenchi'!Q35="",'Pivot elenchi'!Q34="",'Pivot elenchi'!Q35)) -> HELP DESK 1 LIV | N36: =IF(AND('Pivot elenchi'!R35="",'Pivot elenchi'!R36=""),"",IF('Pivot elenchi'!R35="",'Pivot elenchi'!R34="",'Pivot elenchi'!R35)) | O36: =IF(AND('Pivot elenchi'!S35="",'Pivot elenchi'!S36=""),"",IF('Pivot elenchi'!S35="",'Pivot elenchi'!S34="",'Pivot elenchi'!S35)) -> SISTEMI EDITORIALI | P36: =IF(AND('Pivot elenchi'!T35="",'Pivot elenchi'!T36=""),"",IF('Pivot elenchi'!T35="",'Pivot elenchi'!T34="",'Pivot elenchi'!T35)) | Q36: =IF(AND('Pivot elenchi'!U35="",'Pivot elenchi'!U36=""),"",IF('Pivot elenchi'!U35="",'Pivot elenchi'!U34="",'Pivot elenchi'!U35)) -> DG I&S - DIR INFORMATION TECHNOLOGY | R36: @ilsole24ore.com | AB36: =L36 -> 415130 | AC36: =M36 -> HELP DESK 1 LIV | AD36: =N36 | AE36: =O36 -> SISTEMI EDITORIALI | AF36: =P36 | AG36: =Q36 -> DG I&S - DIR INFORMATION TECHNOLOGY
A37: Contratto a tempo determinato | B37: 01 | L37: =IF(AND('Pivot elenchi'!P36="",'Pivot elenchi'!P37=""),"",IF('Pivot elenchi'!P36="",'Pivot elenchi'!P35="",'Pivot elenchi'!P36)) -> 415200 | M37: =IF(AND('Pivot elenchi'!Q36="",'Pivot elenchi'!Q37=""),"",IF('Pivot elenchi'!Q36="",'Pivot elenchi'!Q35="",'Pivot elenchi'!Q36)) -> E-COMMERCE & DIGITAL TRANSFORMA | N37: =IF(AND('Pivot elenchi'!R36="",'Pivot elenchi'!R37=""),"",IF('Pivot elenchi'!R36="",'Pivot elenchi'!R35="",'Pivot elenchi'!R36)) | O37: =IF(AND('Pivot elenchi'!S36="",'Pivot elenchi'!S37=""),"",IF('Pivot elenchi'!S36="",'Pivot elenchi'!S35="",'Pivot elenchi'!S36)) -> TECNOLOGIE DI PRODOTTO | P37: =IF(AND('Pivot elenchi'!T36="",'Pivot elenchi'!T37=""),"",IF('Pivot elenchi'!T36="",'Pivot elenchi'!T35="",'Pivot elenchi'!T36)) | Q37: =IF(AND('Pivot elenchi'!U36="",'Pivot elenchi'!U37=""),"",IF('Pivot elenchi'!U36="",'Pivot elenchi'!U35="",'Pivot elenchi'!U36)) -> DG I&S - DIR INFORMATION TECHNOLOGY | R37: @ilsole24ore.com | AB37: =L37 -> 415200 | AC37: =M37 -> E-COMMERCE & DIGITAL TRANSFORMA | AD37: =N37 | AE37: =O37 -> TECNOLOGIE DI PRODOTTO | AF37: =P37 | AG37: =Q37 -> DG I&S - DIR INFORMATION TECHNOLOGY
A38: Contratto a tempo indeterminato | B38: 02 | L38: =IF(AND('Pivot elenchi'!P37="",'Pivot elenchi'!P38=""),"",IF('Pivot elenchi'!P37="",'Pivot elenchi'!P36="",'Pivot elenchi'!P37)) -> 415230 | M38: =IF(AND('Pivot elenchi'!Q37="",'Pivot elenchi'!Q38=""),"",IF('Pivot elenchi'!Q37="",'Pivot elenchi'!Q36="",'Pivot elenchi'!Q37)) -> PROD. AREA PROF.LE E GEST.PIATT | N38: =IF(AND('Pivot elenchi'!R37="",'Pivot elenchi'!R38=""),"",IF('Pivot elenchi'!R37="",'Pivot elenchi'!R36="",'Pivot elenchi'!R37)) | O38: =IF(AND('Pivot elenchi'!S37="",'Pivot elenchi'!S38=""),"",IF('Pivot elenchi'!S37="",'Pivot elenchi'!S36="",'Pivot elenchi'!S37)) -> TECNOLOGIE DI PRODOTTO | P38: =IF(AND('Pivot elenchi'!T37="",'Pivot elenchi'!T38=""),"",IF('Pivot elenchi'!T37="",'Pivot elenchi'!T36="",'Pivot elenchi'!T37)) | Q38: =IF(AND('Pivot elenchi'!U37="",'Pivot elenchi'!U38=""),"",IF('Pivot elenchi'!U37="",'Pivot elenchi'!U36="",'Pivot elenchi'!U37)) -> DG I&S - DIR INFORMATION TECHNOLOGY | R38: @ilsole24ore.com | AB38: =L38 -> 415230 | AC38: =M38 -> PROD. AREA PROF.LE E GEST.PIATT | AD38: =N38 | AE38: =O38 -> TECNOLOGIE DI PRODOTTO | AF38: =P38 | AG38: =Q38 -> DG I&S - DIR INFORMATION TECHNOLOGY
A39: Contratto a tempo parziale | B39: 03 | L39: =IF(AND('Pivot elenchi'!P38="",'Pivot elenchi'!P39=""),"",IF('Pivot elenchi'!P38="",'Pivot elenchi'!P37="",'Pivot elenchi'!P38)) -> 415300 | M39: =IF(AND('Pivot elenchi'!Q38="",'Pivot elenchi'!Q39=""),"",IF('Pivot elenchi'!Q38="",'Pivot elenchi'!Q37="",'Pivot elenchi'!Q38)) -> DIR INFORMATION TECHNOLOGY | N39: =IF(AND('Pivot elenchi'!R38="",'Pivot elenchi'!R39=""),"",IF('Pivot elenchi'!R38="",'Pivot elenchi'!R37="",'Pivot elenchi'!R38)) | O39: =IF(AND('Pivot elenchi'!S38="",'Pivot elenchi'!S39=""),"",IF('Pivot elenchi'!S38="",'Pivot elenchi'!S37="",'Pivot elenchi'!S38)) -> DIR INFORMATION TECHNOLOGY | P39: =IF(AND('Pivot elenchi'!T38="",'Pivot elenchi'!T39=""),"",IF('Pivot elenchi'!T38="",'Pivot elenchi'!T37="",'Pivot elenchi'!T38)) | Q39: =IF(AND('Pivot elenchi'!U38="",'Pivot elenchi'!U39=""),"",IF('Pivot elenchi'!U38="",'Pivot elenchi'!U37="",'Pivot elenchi'!U38)) -> DG I&S - DIR INFORMATION TECHNOLOGY | R39: @ilsole24ore.com | AB39: =L39 -> 415300 | AC39: =M39 -> DIR INFORMATION TECHNOLOGY | AD39: =N39 | AE39: =O39 -> DIR INFORMATION TECHNOLOGY | AF39: =P39 | AG39: =Q39 -> DG I&S - DIR INFORMATION TECHNOLOGY
A40: Contratto di apprendiistato | B40: 04 | L40: =IF(AND('Pivot elenchi'!P39="",'Pivot elenchi'!P40=""),"",IF('Pivot elenchi'!P39="",'Pivot elenchi'!P38="",'Pivot elenchi'!P39)) -> 41530001 | M40: =IF(AND('Pivot elenchi'!Q39="",'Pivot elenchi'!Q40=""),"",IF('Pivot elenchi'!Q39="",'Pivot elenchi'!Q38="",'Pivot elenchi'!Q39)) -> PRODOTTI PUBLISHING & DIGITAL | N40: =IF(AND('Pivot elenchi'!R39="",'Pivot elenchi'!R40=""),"",IF('Pivot elenchi'!R39="",'Pivot elenchi'!R38="",'Pivot elenchi'!R39)) | O40: =IF(AND('Pivot elenchi'!S39="",'Pivot elenchi'!S40=""),"",IF('Pivot elenchi'!S39="",'Pivot elenchi'!S38="",'Pivot elenchi'!S39)) -> TECNOLOGIE DI PRODOTTO | P40: =IF(AND('Pivot elenchi'!T39="",'Pivot elenchi'!T40=""),"",IF('Pivot elenchi'!T39="",'Pivot elenchi'!T38="",'Pivot elenchi'!T39)) | Q40: =IF(AND('Pivot elenchi'!U39="",'Pivot elenchi'!U40=""),"",IF('Pivot elenchi'!U39="",'Pivot elenchi'!U38="",'Pivot elenchi'!U39)) -> DG I&S - DIR INFORMATION TECHNOLOGY | R40: @ilsole24ore.com | AB40: =L40 -> 41530001 | AC40: =M40 -> PRODOTTI PUBLISHING & DIGITAL | AD40: =N40 | AE40: =O40 -> TECNOLOGIE DI PRODOTTO | AF40: =P40 | AG40: =Q40 -> DG I&S - DIR INFORMATION TECHNOLOGY
A41: Contratto di associazione in partecipazione | B41: 05 | L41: =IF(AND('Pivot elenchi'!P40="",'Pivot elenchi'!P41=""),"",IF('Pivot elenchi'!P40="",'Pivot elenchi'!P39="",'Pivot elenchi'!P40)) -> 41530010 | M41: =IF(AND('Pivot elenchi'!Q40="",'Pivot elenchi'!Q41=""),"",IF('Pivot elenchi'!Q40="",'Pivot elenchi'!Q39="",'Pivot elenchi'!Q40)) -> DATA PLATFORM | N41: =IF(AND('Pivot elenchi'!R40="",'Pivot elenchi'!R41=""),"",IF('Pivot elenchi'!R40="",'Pivot elenchi'!R39="",'Pivot elenchi'!R40)) | O41: =IF(AND('Pivot elenchi'!S40="",'Pivot elenchi'!S41=""),"",IF('Pivot elenchi'!S40="",'Pivot elenchi'!S39="",'Pivot elenchi'!S40)) -> DIR INFORMATION TECHNOLOGY | P41: =IF(AND('Pivot elenchi'!T40="",'Pivot elenchi'!T41=""),"",IF('Pivot elenchi'!T40="",'Pivot elenchi'!T39="",'Pivot elenchi'!T40)) | Q41: =IF(AND('Pivot elenchi'!U40="",'Pivot elenchi'!U41=""),"",IF('Pivot elenchi'!U40="",'Pivot elenchi'!U39="",'Pivot elenchi'!U40)) -> DG I&S - DIR INFORMATION TECHNOLOGY | R41: @ilsole24ore.com | AB41: =L41 -> 41530010 | AC41: =M41 -> DATA PLATFORM | AD41: =N41 | AE41: =O41 -> DIR INFORMATION TECHNOLOGY | AF41: =P41 | AG41: =Q41 -> DG I&S - DIR INFORMATION TECHNOLOGY
A42: Contratto di Co.Co.Co. e Pro. | B42: 06 | L42: =IF(AND('Pivot elenchi'!P41="",'Pivot elenchi'!P42=""),"",IF('Pivot elenchi'!P41="",'Pivot elenchi'!P40="",'Pivot elenchi'!P41)) -> 41530020 | M42: =IF(AND('Pivot elenchi'!Q41="",'Pivot elenchi'!Q42=""),"",IF('Pivot elenchi'!Q41="",'Pivot elenchi'!Q40="",'Pivot elenchi'!Q41)) -> CONTROLLO QUALITA' | N42: =IF(AND('Pivot elenchi'!R41="",'Pivot elenchi'!R42=""),"",IF('Pivot elenchi'!R41="",'Pivot elenchi'!R40="",'Pivot elenchi'!R41)) | O42: =IF(AND('Pivot elenchi'!S41="",'Pivot elenchi'!S42=""),"",IF('Pivot elenchi'!S41="",'Pivot elenchi'!S40="",'Pivot elenchi'!S41)) -> TECNOLOGIE DI PRODOTTO | P42: =IF(AND('Pivot elenchi'!T41="",'Pivot elenchi'!T42=""),"",IF('Pivot elenchi'!T41="",'Pivot elenchi'!T40="",'Pivot elenchi'!T41)) | Q42: =IF(AND('Pivot elenchi'!U41="",'Pivot elenchi'!U42=""),"",IF('Pivot elenchi'!U41="",'Pivot elenchi'!U40="",'Pivot elenchi'!U41)) -> DG I&S - DIR INFORMATION TECHNOLOGY | R42: @ilsole24ore.com | AB42: =L42 -> 41530020 | AC42: =M42 -> CONTROLLO QUALITA' | AD42: =N42 | AE42: =O42 -> TECNOLOGIE DI PRODOTTO | AF42: =P42 | AG42: =Q42 -> DG I&S - DIR INFORMATION TECHNOLOGY
A43: Contratto di lavoro somministrato (ex interinale) | B43: 07 | L43: =IF(AND('Pivot elenchi'!P42="",'Pivot elenchi'!P43=""),"",IF('Pivot elenchi'!P42="",'Pivot elenchi'!P41="",'Pivot elenchi'!P42)) -> 511100 | M43: =IF(AND('Pivot elenchi'!Q42="",'Pivot elenchi'!Q43=""),"",IF('Pivot elenchi'!Q42="",'Pivot elenchi'!Q41="",'Pivot elenchi'!Q42)) -> SISTEMI EDITORIALI | N43: =IF(AND('Pivot elenchi'!R42="",'Pivot elenchi'!R43=""),"",IF('Pivot elenchi'!R42="",'Pivot elenchi'!R41="",'Pivot elenchi'!R42)) | O43: =IF(AND('Pivot elenchi'!S42="",'Pivot elenchi'!S43=""),"",IF('Pivot elenchi'!S42="",'Pivot elenchi'!S41="",'Pivot elenchi'!S42)) -> SISTEMI EDITORIALI | P43: =IF(AND('Pivot elenchi'!T42="",'Pivot elenchi'!T43=""),"",IF('Pivot elenchi'!T42="",'Pivot elenchi'!T41="",'Pivot elenchi'!T42)) | Q43: =IF(AND('Pivot elenchi'!U42="",'Pivot elenchi'!U43=""),"",IF('Pivot elenchi'!U42="",'Pivot elenchi'!U41="",'Pivot elenchi'!U42)) -> DG I&S - DIR INFORMATION TECHNOLOGY | R43: @ilsole24ore.com | AB43: =L43 -> 511100 | AC43: =M43 -> SISTEMI EDITORIALI | AD43: =N43 | AE43: =O43 -> SISTEMI EDITORIALI | AF43: =P43 | AG43: =Q43 -> DG I&S - DIR INFORMATION TECHNOLOGY
A44: Contratto di lavoro intermittente (a chiamata) | B44: 08 | L44: =IF(AND('Pivot elenchi'!P43="",'Pivot elenchi'!P44=""),"",IF('Pivot elenchi'!P43="",'Pivot elenchi'!P42="",'Pivot elenchi'!P43)) -> 511200 | M44: =IF(AND('Pivot elenchi'!Q43="",'Pivot elenchi'!Q44=""),"",IF('Pivot elenchi'!Q43="",'Pivot elenchi'!Q42="",'Pivot elenchi'!Q43)) -> AREA PRODUZIONE | N44: =IF(AND('Pivot elenchi'!R43="",'Pivot elenchi'!R44=""),"",IF('Pivot elenchi'!R43="",'Pivot elenchi'!R42="",'Pivot elenchi'!R43)) | O44: =IF(AND('Pivot elenchi'!S43="",'Pivot elenchi'!S44=""),"",IF('Pivot elenchi'!S43="",'Pivot elenchi'!S42="",'Pivot elenchi'!S43)) -> OPERATIONS DG P&D | P44: =IF(AND('Pivot elenchi'!T43="",'Pivot elenchi'!T44=""),"",IF('Pivot elenchi'!T43="",'Pivot elenchi'!T42="",'Pivot elenchi'!T43)) | Q44: =IF(AND('Pivot elenchi'!U43="",'Pivot elenchi'!U44=""),"",IF('Pivot elenchi'!U43="",'Pivot elenchi'!U42="",'Pivot elenchi'!U43)) -> DG M&B - DG PUBLISHING & DIGITAL | R44: @ilsole24ore.com | AB44: =L44 -> 511200 | AC44: =M44 -> AREA PRODUZIONE | AD44: =N44 | AE44: =O44 -> OPERATIONS DG P&D | AF44: =P44 | AG44: =Q44 -> DG M&B - DG PUBLISHING & DIGITAL
A45: Contratto di inserimento | B45: 09 | L45: =IF(AND('Pivot elenchi'!P44="",'Pivot elenchi'!P45=""),"",IF('Pivot elenchi'!P44="",'Pivot elenchi'!P43="",'Pivot elenchi'!P44)) -> 51120001 | M45: =IF(AND('Pivot elenchi'!Q44="",'Pivot elenchi'!Q45=""),"",IF('Pivot elenchi'!Q44="",'Pivot elenchi'!Q43="",'Pivot elenchi'!Q44)) -> PROGR. PROD. E GEST. CARTA | N45: =IF(AND('Pivot elenchi'!R44="",'Pivot elenchi'!R45=""),"",IF('Pivot elenchi'!R44="",'Pivot elenchi'!R43="",'Pivot elenchi'!R44)) | O45: =IF(AND('Pivot elenchi'!S44="",'Pivot elenchi'!S45=""),"",IF('Pivot elenchi'!S44="",'Pivot elenchi'!S43="",'Pivot elenchi'!S44)) -> OPERATIONS DG P&D | P45: =IF(AND('Pivot elenchi'!T44="",'Pivot elenchi'!T45=""),"",IF('Pivot elenchi'!T44="",'Pivot elenchi'!T43="",'Pivot elenchi'!T44)) | Q45: =IF(AND('Pivot elenchi'!U44="",'Pivot elenchi'!U45=""),"",IF('Pivot elenchi'!U44="",'Pivot elenchi'!U43="",'Pivot elenchi'!U44)) -> DG M&B - DG PUBLISHING & DIGITAL | R45: @ilsole24ore.com | AB45: =L45 -> 51120001 | AC45: =M45 -> PROGR. PROD. E GEST. CARTA | AD45: =N45 | AE45: =O45 -> OPERATIONS DG P&D | AF45: =P45 | AG45: =Q45 -> DG M&B - DG PUBLISHING & DIGITAL
A46: Lavoro stagionale | B46: 10 | L46: =IF(AND('Pivot elenchi'!P45="",'Pivot elenchi'!P46=""),"",IF('Pivot elenchi'!P45="",'Pivot elenchi'!P44="",'Pivot elenchi'!P45)) -> 51130012 | M46: =IF(AND('Pivot elenchi'!Q45="",'Pivot elenchi'!Q46=""),"",IF('Pivot elenchi'!Q45="",'Pivot elenchi'!Q44="",'Pivot elenchi'!Q45)) -> ASSISTENTI EDITORIALI | N46: =IF(AND('Pivot elenchi'!R45="",'Pivot elenchi'!R46=""),"",IF('Pivot elenchi'!R45="",'Pivot elenchi'!R44="",'Pivot elenchi'!R45)) | O46: =IF(AND('Pivot elenchi'!S45="",'Pivot elenchi'!S46=""),"",IF('Pivot elenchi'!S45="",'Pivot elenchi'!S44="",'Pivot elenchi'!S45)) -> OPERATIONS DG P&D | P46: =IF(AND('Pivot elenchi'!T45="",'Pivot elenchi'!T46=""),"",IF('Pivot elenchi'!T45="",'Pivot elenchi'!T44="",'Pivot elenchi'!T45)) | Q46: =IF(AND('Pivot elenchi'!U45="",'Pivot elenchi'!U46=""),"",IF('Pivot elenchi'!U45="",'Pivot elenchi'!U44="",'Pivot elenchi'!U45)) -> DG M&B - DG PUBLISHING & DIGITAL | R46: @ilsole24ore.com | AB46: =L46 -> 51130012 | AC46: =M46 -> ASSISTENTI EDITORIALI | AD46: =N46 | AE46: =O46 -> OPERATIONS DG P&D | AF46: =P46 | AG46: =Q46 -> DG M&B - DG PUBLISHING & DIGITAL
A47: Lavoro ripartito | B47: 11 | L47: =IF(AND('Pivot elenchi'!P46="",'Pivot elenchi'!P47=""),"",IF('Pivot elenchi'!P46="",'Pivot elenchi'!P45="",'Pivot elenchi'!P46)) -> 51130013 | M47: =IF(AND('Pivot elenchi'!Q46="",'Pivot elenchi'!Q47=""),"",IF('Pivot elenchi'!Q46="",'Pivot elenchi'!Q45="",'Pivot elenchi'!Q46)) -> GRAFICI DI REDAZIONE | N47: =IF(AND('Pivot elenchi'!R46="",'Pivot elenchi'!R47=""),"",IF('Pivot elenchi'!R46="",'Pivot elenchi'!R45="",'Pivot elenchi'!R46)) | O47: =IF(AND('Pivot elenchi'!S46="",'Pivot elenchi'!S47=""),"",IF('Pivot elenchi'!S46="",'Pivot elenchi'!S45="",'Pivot elenchi'!S46)) -> OPERATIONS DG P&D | P47: =IF(AND('Pivot elenchi'!T46="",'Pivot elenchi'!T47=""),"",IF('Pivot elenchi'!T46="",'Pivot elenchi'!T45="",'Pivot elenchi'!T46)) | Q47: =IF(AND('Pivot elenchi'!U46="",'Pivot elenchi'!U47=""),"",IF('Pivot elenchi'!U46="",'Pivot elenchi'!U45="",'Pivot elenchi'!U46)) -> DG M&B - DG PUBLISHING & DIGITAL | R47: @ilsole24ore.com | AB47: =L47 -> 51130013 | AC47: =M47 -> GRAFICI DI REDAZIONE | AD47: =N47 | AE47: =O47 -> OPERATIONS DG P&D | AF47: =P47 | AG47: =Q47 -> DG M&B - DG PUBLISHING & DIGITAL
A48: Stage/tirocinio | B48: 12 | L48: =IF(AND('Pivot elenchi'!P47="",'Pivot elenchi'!P48=""),"",IF('Pivot elenchi'!P47="",'Pivot elenchi'!P46="",'Pivot elenchi'!P47)) -> 51130014 | M48: =IF(AND('Pivot elenchi'!Q47="",'Pivot elenchi'!Q48=""),"",IF('Pivot elenchi'!Q47="",'Pivot elenchi'!Q46="",'Pivot elenchi'!Q47)) -> LAB24 | N48: =IF(AND('Pivot elenchi'!R47="",'Pivot elenchi'!R48=""),"",IF('Pivot elenchi'!R47="",'Pivot elenchi'!R46="",'Pivot elenchi'!R47)) | O48: =IF(AND('Pivot elenchi'!S47="",'Pivot elenchi'!S48=""),"",IF('Pivot elenchi'!S47="",'Pivot elenchi'!S46="",'Pivot elenchi'!S47)) -> OPERATIONS DG P&D | P48: =IF(AND('Pivot elenchi'!T47="",'Pivot elenchi'!T48=""),"",IF('Pivot elenchi'!T47="",'Pivot elenchi'!T46="",'Pivot elenchi'!T47)) | Q48: =IF(AND('Pivot elenchi'!U47="",'Pivot elenchi'!U48=""),"",IF('Pivot elenchi'!U47="",'Pivot elenchi'!U46="",'Pivot elenchi'!U47)) -> DG M&B - DG PUBLISHING & DIGITAL | R48: @ilsole24ore.com | AB48: =L48 -> 51130014 | AC48: =M48 -> LAB24 | AD48: =N48 | AE48: =O48 -> OPERATIONS DG P&D | AF48: =P48 | AG48: =Q48 -> DG M&B - DG PUBLISHING & DIGITAL
A49: Contratto a Part. IVA | B49: 99 | L49: =IF(AND('Pivot elenchi'!P48="",'Pivot elenchi'!P49=""),"",IF('Pivot elenchi'!P48="",'Pivot elenchi'!P47="",'Pivot elenchi'!P48)) -> 51130015 | M49: =IF(AND('Pivot elenchi'!Q48="",'Pivot elenchi'!Q49=""),"",IF('Pivot elenchi'!Q48="",'Pivot elenchi'!Q47="",'Pivot elenchi'!Q48)) -> GRAFICI INFOGRAFICI | N49: =IF(AND('Pivot elenchi'!R48="",'Pivot elenchi'!R49=""),"",IF('Pivot elenchi'!R48="",'Pivot elenchi'!R47="",'Pivot elenchi'!R48)) | O49: =IF(AND('Pivot elenchi'!S48="",'Pivot elenchi'!S49=""),"",IF('Pivot elenchi'!S48="",'Pivot elenchi'!S47="",'Pivot elenchi'!S48)) -> OPERATIONS DG P&D | P49: =IF(AND('Pivot elenchi'!T48="",'Pivot elenchi'!T49=""),"",IF('Pivot elenchi'!T48="",'Pivot elenchi'!T47="",'Pivot elenchi'!T48)) | Q49: =IF(AND('Pivot elenchi'!U48="",'Pivot elenchi'!U49=""),"",IF('Pivot elenchi'!U48="",'Pivot elenchi'!U47="",'Pivot elenchi'!U48)) -> DG M&B - DG PUBLISHING & DIGITAL | R49: @ilsole24ore.com | AB49: =L49 -> 51130015 | AC49: =M49 -> GRAFICI INFOGRAFICI | AD49: =N49 | AE49: =O49 -> OPERATIONS DG P&D | AF49: =P49 | AG49: =Q49 -> DG M&B - DG PUBLISHING & DIGITAL
L50: =IF(AND('Pivot elenchi'!P49="",'Pivot elenchi'!P50=""),"",IF('Pivot elenchi'!P49="",'Pivot elenchi'!P48="",'Pivot elenchi'!P49)) -> 511305 | M50: =IF(AND('Pivot elenchi'!Q49="",'Pivot elenchi'!Q50=""),"",IF('Pivot elenchi'!Q49="",'Pivot elenchi'!Q48="",'Pivot elenchi'!Q49)) -> SUPPORTI REDAZIONALI | N50: =IF(AND('Pivot elenchi'!R49="",'Pivot elenchi'!R50=""),"",IF('Pivot elenchi'!R49="",'Pivot elenchi'!R48="",'Pivot elenchi'!R49)) | O50: =IF(AND('Pivot elenchi'!S49="",'Pivot elenchi'!S50=""),"",IF('Pivot elenchi'!S49="",'Pivot elenchi'!S48="",'Pivot elenchi'!S49)) -> SERVIZI GENERALI SICUREZZA E AMBIENTE | P50: =IF(AND('Pivot elenchi'!T49="",'Pivot elenchi'!T50=""),"",IF('Pivot elenchi'!T49="",'Pivot elenchi'!T48="",'Pivot elenchi'!T49)) | Q50: =IF(AND('Pivot elenchi'!U49="",'Pivot elenchi'!U50=""),"",IF('Pivot elenchi'!U49="",'Pivot elenchi'!U48="",'Pivot elenchi'!U49)) -> DIREZIONE CENTRALE PERSONALE E ORGANIZZA | R50: @ilsole24ore.com | AB50: =L50 -> 511305 | AC50: =M50 -> SUPPORTI REDAZIONALI | AD50: =N50 | AE50: =O50 -> SERVIZI GENERALI SICUREZZA E AMBIENTE | AF50: =P50 | AG50: =Q50 -> DIREZIONE CENTRALE PERSONALE E ORGANIZZA
L51: =IF(AND('Pivot elenchi'!P50="",'Pivot elenchi'!P51=""),"",IF('Pivot elenchi'!P50="",'Pivot elenchi'!P49="",'Pivot elenchi'!P50)) -> 51130501 | M51: =IF(AND('Pivot elenchi'!Q50="",'Pivot elenchi'!Q51=""),"",IF('Pivot elenchi'!Q50="",'Pivot elenchi'!Q49="",'Pivot elenchi'!Q50)) -> SEGRETERIE REDAZIONE MILANO | N51: =IF(AND('Pivot elenchi'!R50="",'Pivot elenchi'!R51=""),"",IF('Pivot elenchi'!R50="",'Pivot elenchi'!R49="",'Pivot elenchi'!R50)) | O51: =IF(AND('Pivot elenchi'!S50="",'Pivot elenchi'!S51=""),"",IF('Pivot elenchi'!S50="",'Pivot elenchi'!S49="",'Pivot elenchi'!S50)) -> SERVIZI GENERALI SICUREZZA E AMBIENTE | P51: =IF(AND('Pivot elenchi'!T50="",'Pivot elenchi'!T51=""),"",IF('Pivot elenchi'!T50="",'Pivot elenchi'!T49="",'Pivot elenchi'!T50)) | Q51: =IF(AND('Pivot elenchi'!U50="",'Pivot elenchi'!U51=""),"",IF('Pivot elenchi'!U50="",'Pivot elenchi'!U49="",'Pivot elenchi'!U50)) -> DIREZIONE CENTRALE PERSONALE E ORGANIZZA | R51: @ilsole24ore.com | AB51: =L51 -> 51130501 | AC51: =M51 -> SEGRETERIE REDAZIONE MILANO | AD51: =N51 | AE51: =O51 -> SERVIZI GENERALI SICUREZZA E AMBIENTE | AF51: =P51 | AG51: =Q51 -> DIREZIONE CENTRALE PERSONALE E ORGANIZZA
L52: =IF(AND('Pivot elenchi'!P51="",'Pivot elenchi'!P52=""),"",IF('Pivot elenchi'!P51="",'Pivot elenchi'!P50="",'Pivot elenchi'!P51)) -> 51130502 | M52: =IF(AND('Pivot elenchi'!Q51="",'Pivot elenchi'!Q52=""),"",IF('Pivot elenchi'!Q51="",'Pivot elenchi'!Q50="",'Pivot elenchi'!Q51)) -> SEGRETERIE REDAZIONE ROMA | N52: =IF(AND('Pivot elenchi'!R51="",'Pivot elenchi'!R52=""),"",IF('Pivot elenchi'!R51="",'Pivot elenchi'!R50="",'Pivot elenchi'!R51)) | O52: =IF(AND('Pivot elenchi'!S51="",'Pivot elenchi'!S52=""),"",IF('Pivot elenchi'!S51="",'Pivot elenchi'!S50="",'Pivot elenchi'!S51)) -> SERVIZI GENERALI SICUREZZA E AMBIENTE | P52: =IF(AND('Pivot elenchi'!T51="",'Pivot elenchi'!T52=""),"",IF('Pivot elenchi'!T51="",'Pivot elenchi'!T50="",'Pivot elenchi'!T51)) | Q52: =IF(AND('Pivot elenchi'!U51="",'Pivot elenchi'!U52=""),"",IF('Pivot elenchi'!U51="",'Pivot elenchi'!U50="",'Pivot elenchi'!U51)) -> DIREZIONE CENTRALE PERSONALE E ORGANIZZA | R52: @ilsole24ore.com | AB52: =L52 -> 51130502 | AC52: =M52 -> SEGRETERIE REDAZIONE ROMA | AD52: =N52 | AE52: =O52 -> SERVIZI GENERALI SICUREZZA E AMBIENTE | AF52: =P52 | AG52: =Q52 -> DIREZIONE CENTRALE PERSONALE E ORGANIZZA
L53: =IF(AND('Pivot elenchi'!P52="",'Pivot elenchi'!P53=""),"",IF('Pivot elenchi'!P52="",'Pivot elenchi'!P51="",'Pivot elenchi'!P52)) -> 511600 | M53: =IF(AND('Pivot elenchi'!Q52="",'Pivot elenchi'!Q53=""),"",IF('Pivot elenchi'!Q52="",'Pivot elenchi'!Q51="",'Pivot elenchi'!Q52)) -> DATI BORSE E MERCATI | N53: =IF(AND('Pivot elenchi'!R52="",'Pivot elenchi'!R53=""),"",IF('Pivot elenchi'!R52="",'Pivot elenchi'!R51="",'Pivot elenchi'!R52)) | O53: =IF(AND('Pivot elenchi'!S52="",'Pivot elenchi'!S53=""),"",IF('Pivot elenchi'!S52="",'Pivot elenchi'!S51="",'Pivot elenchi'!S52)) -> OPERATIONS DG P&D | P53: =IF(AND('Pivot elenchi'!T52="",'Pivot elenchi'!T53=""),"",IF('Pivot elenchi'!T52="",'Pivot elenchi'!T51="",'Pivot elenchi'!T52)) | Q53: =IF(AND('Pivot elenchi'!U52="",'Pivot elenchi'!U53=""),"",IF('Pivot elenchi'!U52="",'Pivot elenchi'!U51="",'Pivot elenchi'!U52)) -> DG M&B - DG PUBLISHING & DIGITAL | R53: @ilsole24ore.com | AB53: =L53 -> 511600 | AC53: =M53 -> DATI BORSE E MERCATI | AD53: =N53 | AE53: =O53 -> OPERATIONS DG P&D | AF53: =P53 | AG53: =Q53 -> DG M&B - DG PUBLISHING & DIGITAL
A54: =IF('Scheda Movimento'!C22="","",'Scheda Movimento'!C22) -> DIRIGENTE | B54: =IF(A54="","",VLOOKUP(A54,A56:B69,2,FALSE)) -> D | L54: =IF(AND('Pivot elenchi'!P53="",'Pivot elenchi'!P54=""),"",IF('Pivot elenchi'!P53="",'Pivot elenchi'!P52="",'Pivot elenchi'!P53)) -> 512000 | M54: =IF(AND('Pivot elenchi'!Q53="",'Pivot elenchi'!Q54=""),"",IF('Pivot elenchi'!Q53="",'Pivot elenchi'!Q52="",'Pivot elenchi'!Q53)) -> MARKETING EDITORIALE | N54: =IF(AND('Pivot elenchi'!R53="",'Pivot elenchi'!R54=""),"",IF('Pivot elenchi'!R53="",'Pivot elenchi'!R52="",'Pivot elenchi'!R53)) | O54: =IF(AND('Pivot elenchi'!S53="",'Pivot elenchi'!S54=""),"",IF('Pivot elenchi'!S53="",'Pivot elenchi'!S52="",'Pivot elenchi'!S53)) -> DG PUBLISHING & DIGITAL | P54: =IF(AND('Pivot elenchi'!T53="",'Pivot elenchi'!T54=""),"",IF('Pivot elenchi'!T53="",'Pivot elenchi'!T52="",'Pivot elenchi'!T53)) | Q54: =IF(AND('Pivot elenchi'!U53="",'Pivot elenchi'!U54=""),"",IF('Pivot elenchi'!U53="",'Pivot elenchi'!U52="",'Pivot elenchi'!U53)) -> DG M&B - DG PUBLISHING & DIGITAL | R54: @ilsole24ore.com | AB54: =L54 -> 512000 | AC54: =M54 -> MARKETING EDITORIALE | AD54: =N54 | AE54: =O54 -> DG PUBLISHING & DIGITAL | AF54: =P54 | AG54: =Q54 -> DG M&B - DG PUBLISHING & DIGITAL
A55: QUALIFICA | B55: COD | L55: =IF(AND('Pivot elenchi'!P54="",'Pivot elenchi'!P55=""),"",IF('Pivot elenchi'!P54="",'Pivot elenchi'!P53="",'Pivot elenchi'!P54)) -> 512100 | M55: =IF(AND('Pivot elenchi'!Q54="",'Pivot elenchi'!Q55=""),"",IF('Pivot elenchi'!Q54="",'Pivot elenchi'!Q53="",'Pivot elenchi'!Q54)) -> DG PUBLISHING E DIGITAL | N55: =IF(AND('Pivot elenchi'!R54="",'Pivot elenchi'!R55=""),"",IF('Pivot elenchi'!R54="",'Pivot elenchi'!R53="",'Pivot elenchi'!R54)) | O55: =IF(AND('Pivot elenchi'!S54="",'Pivot elenchi'!S55=""),"",IF('Pivot elenchi'!S54="",'Pivot elenchi'!S53="",'Pivot elenchi'!S54)) -> DG PUBLISHING & DIGITAL | P55: =IF(AND('Pivot elenchi'!T54="",'Pivot elenchi'!T55=""),"",IF('Pivot elenchi'!T54="",'Pivot elenchi'!T53="",'Pivot elenchi'!T54)) | Q55: =IF(AND('Pivot elenchi'!U54="",'Pivot elenchi'!U55=""),"",IF('Pivot elenchi'!U54="",'Pivot elenchi'!U53="",'Pivot elenchi'!U54)) -> DG M&B - DG PUBLISHING & DIGITAL | R55: @ilsole24ore.com | AB55: =L55 -> 512100 | AC55: =M55 -> DG PUBLISHING E DIGITAL | AD55: =N55 | AE55: =O55 -> DG PUBLISHING & DIGITAL | AF55: =P55 | AG55: =Q55 -> DG M&B - DG PUBLISHING & DIGITAL
L56: =IF(AND('Pivot elenchi'!P55="",'Pivot elenchi'!P56=""),"",IF('Pivot elenchi'!P55="",'Pivot elenchi'!P54="",'Pivot elenchi'!P55)) -> 51210010 | M56: =IF(AND('Pivot elenchi'!Q55="",'Pivot elenchi'!Q56=""),"",IF('Pivot elenchi'!Q55="",'Pivot elenchi'!Q54="",'Pivot elenchi'!Q55)) -> SVILUPPO DIGITALE MKTG EDITORIA | N56: =IF(AND('Pivot elenchi'!R55="",'Pivot elenchi'!R56=""),"",IF('Pivot elenchi'!R55="",'Pivot elenchi'!R54="",'Pivot elenchi'!R55)) | O56: =IF(AND('Pivot elenchi'!S55="",'Pivot elenchi'!S56=""),"",IF('Pivot elenchi'!S55="",'Pivot elenchi'!S54="",'Pivot elenchi'!S55)) -> DG PUBLISHING & DIGITAL | P56: =IF(AND('Pivot elenchi'!T55="",'Pivot elenchi'!T56=""),"",IF('Pivot elenchi'!T55="",'Pivot elenchi'!T54="",'Pivot elenchi'!T55)) | Q56: =IF(AND('Pivot elenchi'!U55="",'Pivot elenchi'!U56=""),"",IF('Pivot elenchi'!U55="",'Pivot elenchi'!U54="",'Pivot elenchi'!U55)) -> DG M&B - DG PUBLISHING & DIGITAL | R56: @ilsole24ore.com | AB56: =L56 -> 51210010 | AC56: =M56 -> SVILUPPO DIGITALE MKTG EDITORIA | AD56: =N56 | AE56: =O56 -> DG PUBLISHING & DIGITAL | AF56: =P56 | AG56: =Q56 -> DG M&B - DG PUBLISHING & DIGITAL
A57: IMPIEGATO | B57: I | L57: =IF(AND('Pivot elenchi'!P56="",'Pivot elenchi'!P57=""),"",IF('Pivot elenchi'!P56="",'Pivot elenchi'!P55="",'Pivot elenchi'!P56)) -> 513000 | M57: =IF(AND('Pivot elenchi'!Q56="",'Pivot elenchi'!Q57=""),"",IF('Pivot elenchi'!Q56="",'Pivot elenchi'!Q55="",'Pivot elenchi'!Q56)) -> POLITICHE COMMERCIALI DIFF.LOG. | N57: =IF(AND('Pivot elenchi'!R56="",'Pivot elenchi'!R57=""),"",IF('Pivot elenchi'!R56="",'Pivot elenchi'!R55="",'Pivot elenchi'!R56)) | O57: =IF(AND('Pivot elenchi'!S56="",'Pivot elenchi'!S57=""),"",IF('Pivot elenchi'!S56="",'Pivot elenchi'!S55="",'Pivot elenchi'!S56)) -> DG PUBLISHING & DIGITAL | P57: =IF(AND('Pivot elenchi'!T56="",'Pivot elenchi'!T57=""),"",IF('Pivot elenchi'!T56="",'Pivot elenchi'!T55="",'Pivot elenchi'!T56)) | Q57: =IF(AND('Pivot elenchi'!U56="",'Pivot elenchi'!U57=""),"",IF('Pivot elenchi'!U56="",'Pivot elenchi'!U55="",'Pivot elenchi'!U56)) -> DG M&B - DG PUBLISHING & DIGITAL | R57: @ilsole24ore.com | AB57: =L57 -> 513000 | AC57: =M57 -> POLITICHE COMMERCIALI DIFF.LOG. | AD57: =N57 | AE57: =O57 -> DG PUBLISHING & DIGITAL | AF57: =P57 | AG57: =Q57 -> DG M&B - DG PUBLISHING & DIGITAL
A58: QUADRO | B58: Q | L58: =IF(AND('Pivot elenchi'!P57="",'Pivot elenchi'!P58=""),"",IF('Pivot elenchi'!P57="",'Pivot elenchi'!P56="",'Pivot elenchi'!P57)) -> 51320010 | M58: =IF(AND('Pivot elenchi'!Q57="",'Pivot elenchi'!Q58=""),"",IF('Pivot elenchi'!Q57="",'Pivot elenchi'!Q56="",'Pivot elenchi'!Q57)) -> LOGISTICA | N58: =IF(AND('Pivot elenchi'!R57="",'Pivot elenchi'!R58=""),"",IF('Pivot elenchi'!R57="",'Pivot elenchi'!R56="",'Pivot elenchi'!R57)) | O58: =IF(AND('Pivot elenchi'!S57="",'Pivot elenchi'!S58=""),"",IF('Pivot elenchi'!S57="",'Pivot elenchi'!S56="",'Pivot elenchi'!S57)) -> DG PUBLISHING & DIGITAL | P58: =IF(AND('Pivot elenchi'!T57="",'Pivot elenchi'!T58=""),"",IF('Pivot elenchi'!T57="",'Pivot elenchi'!T56="",'Pivot elenchi'!T57)) | Q58: =IF(AND('Pivot elenchi'!U57="",'Pivot elenchi'!U58=""),"",IF('Pivot elenchi'!U57="",'Pivot elenchi'!U56="",'Pivot elenchi'!U57)) -> DG M&B - DG PUBLISHING & DIGITAL | R58: @ilsole24ore.com | AB58: =L58 -> 51320010 | AC58: =M58 -> LOGISTICA | AD58: =N58 | AE58: =O58 -> DG PUBLISHING & DIGITAL | AF58: =P58 | AG58: =Q58 -> DG M&B - DG PUBLISHING & DIGITAL
A59: DIRIGENTE | B59: D | L59: =IF(AND('Pivot elenchi'!P58="",'Pivot elenchi'!P59=""),"",IF('Pivot elenchi'!P58="",'Pivot elenchi'!P57="",'Pivot elenchi'!P58)) -> 51320020 | M59: =IF(AND('Pivot elenchi'!Q58="",'Pivot elenchi'!Q59=""),"",IF('Pivot elenchi'!Q58="",'Pivot elenchi'!Q57="",'Pivot elenchi'!Q58)) -> DIFFUSIONE | N59: =IF(AND('Pivot elenchi'!R58="",'Pivot elenchi'!R59=""),"",IF('Pivot elenchi'!R58="",'Pivot elenchi'!R57="",'Pivot elenchi'!R58)) | O59: =IF(AND('Pivot elenchi'!S58="",'Pivot elenchi'!S59=""),"",IF('Pivot elenchi'!S58="",'Pivot elenchi'!S57="",'Pivot elenchi'!S58)) -> DG PUBLISHING & DIGITAL | P59: =IF(AND('Pivot elenchi'!T58="",'Pivot elenchi'!T59=""),"",IF('Pivot elenchi'!T58="",'Pivot elenchi'!T57="",'Pivot elenchi'!T58)) | Q59: =IF(AND('Pivot elenchi'!U58="",'Pivot elenchi'!U59=""),"",IF('Pivot elenchi'!U58="",'Pivot elenchi'!U57="",'Pivot elenchi'!U58)) -> DG M&B - DG PUBLISHING & DIGITAL | R59: @ilsole24ore.com | AB59: =L59 -> 51320020 | AC59: =M59 -> DIFFUSIONE | AD59: =N59 | AE59: =O59 -> DG PUBLISHING & DIGITAL | AF59: =P59 | AG59: =Q59 -> DG M&B - DG PUBLISHING & DIGITAL
A60: GIORNALISTA | B60: G | L60: =IF(AND('Pivot elenchi'!P59="",'Pivot elenchi'!P60=""),"",IF('Pivot elenchi'!P59="",'Pivot elenchi'!P58="",'Pivot elenchi'!P59)) -> 513400 | M60: =IF(AND('Pivot elenchi'!Q59="",'Pivot elenchi'!Q60=""),"",IF('Pivot elenchi'!Q59="",'Pivot elenchi'!Q58="",'Pivot elenchi'!Q59)) -> PIANIFICAZ. E CONTROLLO COMM.LE | N60: =IF(AND('Pivot elenchi'!R59="",'Pivot elenchi'!R60=""),"",IF('Pivot elenchi'!R59="",'Pivot elenchi'!R58="",'Pivot elenchi'!R59)) | O60: =IF(AND('Pivot elenchi'!S59="",'Pivot elenchi'!S60=""),"",IF('Pivot elenchi'!S59="",'Pivot elenchi'!S58="",'Pivot elenchi'!S59)) -> DG PUBLISHING & DIGITAL | P60: =IF(AND('Pivot elenchi'!T59="",'Pivot elenchi'!T60=""),"",IF('Pivot elenchi'!T59="",'Pivot elenchi'!T58="",'Pivot elenchi'!T59)) | Q60: =IF(AND('Pivot elenchi'!U59="",'Pivot elenchi'!U60=""),"",IF('Pivot elenchi'!U59="",'Pivot elenchi'!U58="",'Pivot elenchi'!U59)) -> DG M&B - DG PUBLISHING & DIGITAL | R60: @ilsole24ore.com | AB60: =L60 -> 513400 | AC60: =M60 -> PIANIFICAZ. E CONTROLLO COMM.LE | AD60: =N60 | AE60: =O60 -> DG PUBLISHING & DIGITAL | AF60: =P60 | AG60: =Q60 -> DG M&B - DG PUBLISHING & DIGITAL
A61: OPERAIO | B61: O | L61: =IF(AND('Pivot elenchi'!P60="",'Pivot elenchi'!P61=""),"",IF('Pivot elenchi'!P60="",'Pivot elenchi'!P59="",'Pivot elenchi'!P60)) -> 513500 | M61: =IF(AND('Pivot elenchi'!Q60="",'Pivot elenchi'!Q61=""),"",IF('Pivot elenchi'!Q60="",'Pivot elenchi'!Q59="",'Pivot elenchi'!Q60)) -> VENDITE ABBON. NUOVI E RINNOVI | N61: =IF(AND('Pivot elenchi'!R60="",'Pivot elenchi'!R61=""),"",IF('Pivot elenchi'!R60="",'Pivot elenchi'!R59="",'Pivot elenchi'!R60)) | O61: =IF(AND('Pivot elenchi'!S60="",'Pivot elenchi'!S61=""),"",IF('Pivot elenchi'!S60="",'Pivot elenchi'!S59="",'Pivot elenchi'!S60)) -> DG PUBLISHING & DIGITAL | P61: =IF(AND('Pivot elenchi'!T60="",'Pivot elenchi'!T61=""),"",IF('Pivot elenchi'!T60="",'Pivot elenchi'!T59="",'Pivot elenchi'!T60)) | Q61: =IF(AND('Pivot elenchi'!U60="",'Pivot elenchi'!U61=""),"",IF('Pivot elenchi'!U60="",'Pivot elenchi'!U59="",'Pivot elenchi'!U60)) -> DG M&B - DG PUBLISHING & DIGITAL | R61: @ilsole24ore.com | AB61: =L61 -> 513500 | AC61: =M61 -> VENDITE ABBON. NUOVI E RINNOVI | AD61: =N61 | AE61: =O61 -> DG PUBLISHING & DIGITAL | AF61: =P61 | AG61: =Q61 -> DG M&B - DG PUBLISHING & DIGITAL
A62: PRATICANTE | B62: P | L62: =IF(AND('Pivot elenchi'!P61="",'Pivot elenchi'!P62=""),"",IF('Pivot elenchi'!P61="",'Pivot elenchi'!P60="",'Pivot elenchi'!P61)) -> 514000 | M62: =IF(AND('Pivot elenchi'!Q61="",'Pivot elenchi'!Q62=""),"",IF('Pivot elenchi'!Q61="",'Pivot elenchi'!Q60="",'Pivot elenchi'!Q61)) -> DIREZIONE QUOTIDIANO | N62: =IF(AND('Pivot elenchi'!R61="",'Pivot elenchi'!R62=""),"",IF('Pivot elenchi'!R61="",'Pivot elenchi'!R60="",'Pivot elenchi'!R61)) | O62: =IF(AND('Pivot elenchi'!S61="",'Pivot elenchi'!S62=""),"",IF('Pivot elenchi'!S61="",'Pivot elenchi'!S60="",'Pivot elenchi'!S61)) -> QUOTIDIANO | P62: =IF(AND('Pivot elenchi'!T61="",'Pivot elenchi'!T62=""),"",IF('Pivot elenchi'!T61="",'Pivot elenchi'!T60="",'Pivot elenchi'!T61)) | Q62: =IF(AND('Pivot elenchi'!U61="",'Pivot elenchi'!U62=""),"",IF('Pivot elenchi'!U61="",'Pivot elenchi'!U60="",'Pivot elenchi'!U61)) -> REDAZIONI GIORNALISTICHE | R62: @ilsole24ore.com | AB62: =L62 -> 514000 | AC62: =M62 -> DIREZIONE QUOTIDIANO | AD62: =N62 | AE62: =O62 -> QUOTIDIANO | AF62: =P62 | AG62: =Q62 -> REDAZIONI GIORNALISTICHE
A63: Stage | B63: S | L63: =IF(AND('Pivot elenchi'!P62="",'Pivot elenchi'!P63=""),"",IF('Pivot elenchi'!P62="",'Pivot elenchi'!P61="",'Pivot elenchi'!P62)) -> 51400001 | M63: =IF(AND('Pivot elenchi'!Q62="",'Pivot elenchi'!Q63=""),"",IF('Pivot elenchi'!Q62="",'Pivot elenchi'!Q61="",'Pivot elenchi'!Q62)) -> DIREZIONE QUOTIDIANO | N63: =IF(AND('Pivot elenchi'!R62="",'Pivot elenchi'!R63=""),"",IF('Pivot elenchi'!R62="",'Pivot elenchi'!R61="",'Pivot elenchi'!R62)) | O63: =IF(AND('Pivot elenchi'!S62="",'Pivot elenchi'!S63=""),"",IF('Pivot elenchi'!S62="",'Pivot elenchi'!S61="",'Pivot elenchi'!S62)) -> SERVIZI GENERALI SICUREZZA E AMBIENTE | P63: =IF(AND('Pivot elenchi'!T62="",'Pivot elenchi'!T63=""),"",IF('Pivot elenchi'!T62="",'Pivot elenchi'!T61="",'Pivot elenchi'!T62)) | Q63: =IF(AND('Pivot elenchi'!U62="",'Pivot elenchi'!U63=""),"",IF('Pivot elenchi'!U62="",'Pivot elenchi'!U61="",'Pivot elenchi'!U62)) -> DIREZIONE CENTRALE PERSONALE E ORGANIZZA | R63: @ilsole24ore.com | AB63: =L63 -> 51400001 | AC63: =M63 -> DIREZIONE QUOTIDIANO | AD63: =N63 | AE63: =O63 -> SERVIZI GENERALI SICUREZZA E AMBIENTE | AF63: =P63 | AG63: =Q63 -> DIREZIONE CENTRALE PERSONALE E ORGANIZZA
A64: Contr. Somm.ne | B64: X | L64: =IF(AND('Pivot elenchi'!P63="",'Pivot elenchi'!P64=""),"",IF('Pivot elenchi'!P63="",'Pivot elenchi'!P62="",'Pivot elenchi'!P63)) -> 514100 | M64: =IF(AND('Pivot elenchi'!Q63="",'Pivot elenchi'!Q64=""),"",IF('Pivot elenchi'!Q63="",'Pivot elenchi'!Q62="",'Pivot elenchi'!Q63)) -> REDAZIONI ITALIA | N64: =IF(AND('Pivot elenchi'!R63="",'Pivot elenchi'!R64=""),"",IF('Pivot elenchi'!R63="",'Pivot elenchi'!R62="",'Pivot elenchi'!R63)) | O64: =IF(AND('Pivot elenchi'!S63="",'Pivot elenchi'!S64=""),"",IF('Pivot elenchi'!S63="",'Pivot elenchi'!S62="",'Pivot elenchi'!S63)) -> QUOTIDIANO | P64: =IF(AND('Pivot elenchi'!T63="",'Pivot elenchi'!T64=""),"",IF('Pivot elenchi'!T63="",'Pivot elenchi'!T62="",'Pivot elenchi'!T63)) | Q64: =IF(AND('Pivot elenchi'!U63="",'Pivot elenchi'!U64=""),"",IF('Pivot elenchi'!U63="",'Pivot elenchi'!U62="",'Pivot elenchi'!U63)) -> REDAZIONI GIORNALISTICHE | R64: @ilsole24ore.com | AB64: =L64 -> 514100 | AC64: =M64 -> REDAZIONI ITALIA | AD64: =N64 | AE64: =O64 -> QUOTIDIANO | AF64: =P64 | AG64: =Q64 -> REDAZIONI GIORNALISTICHE
A65: Co.Co.Co. | B65: V | L65: =IF(AND('Pivot elenchi'!P64="",'Pivot elenchi'!P65=""),"",IF('Pivot elenchi'!P64="",'Pivot elenchi'!P63="",'Pivot elenchi'!P64)) -> 514210 | M65: =IF(AND('Pivot elenchi'!Q64="",'Pivot elenchi'!Q65=""),"",IF('Pivot elenchi'!Q64="",'Pivot elenchi'!Q63="",'Pivot elenchi'!Q64)) -> REDAZIONE E CORRISP BRUXELLES | N65: =IF(AND('Pivot elenchi'!R64="",'Pivot elenchi'!R65=""),"",IF('Pivot elenchi'!R64="",'Pivot elenchi'!R63="",'Pivot elenchi'!R64)) | O65: =IF(AND('Pivot elenchi'!S64="",'Pivot elenchi'!S65=""),"",IF('Pivot elenchi'!S64="",'Pivot elenchi'!S63="",'Pivot elenchi'!S64)) -> QUOTIDIANO | P65: =IF(AND('Pivot elenchi'!T64="",'Pivot elenchi'!T65=""),"",IF('Pivot elenchi'!T64="",'Pivot elenchi'!T63="",'Pivot elenchi'!T64)) | Q65: =IF(AND('Pivot elenchi'!U64="",'Pivot elenchi'!U65=""),"",IF('Pivot elenchi'!U64="",'Pivot elenchi'!U63="",'Pivot elenchi'!U64)) -> REDAZIONI GIORNALISTICHE | R65: @ilsole24ore.com | AB65: =L65 -> 514210 | AC65: =M65 -> REDAZIONE E CORRISP BRUXELLES | AD65: =N65 | AE65: =O65 -> QUOTIDIANO | AF65: =P65 | AG65: =Q65 -> REDAZIONI GIORNALISTICHE
A66: Co.Co.Pro. | B66: W | L66: =IF(AND('Pivot elenchi'!P65="",'Pivot elenchi'!P66=""),"",IF('Pivot elenchi'!P65="",'Pivot elenchi'!P64="",'Pivot elenchi'!P65)) -> 514220 | M66: =IF(AND('Pivot elenchi'!Q65="",'Pivot elenchi'!Q66=""),"",IF('Pivot elenchi'!Q65="",'Pivot elenchi'!Q64="",'Pivot elenchi'!Q65)) -> REDAZIONE E CORRISP FRANCOFORTE | N66: =IF(AND('Pivot elenchi'!R65="",'Pivot elenchi'!R66=""),"",IF('Pivot elenchi'!R65="",'Pivot elenchi'!R64="",'Pivot elenchi'!R65)) | O66: =IF(AND('Pivot elenchi'!S65="",'Pivot elenchi'!S66=""),"",IF('Pivot elenchi'!S65="",'Pivot elenchi'!S64="",'Pivot elenchi'!S65)) -> QUOTIDIANO | P66: =IF(AND('Pivot elenchi'!T65="",'Pivot elenchi'!T66=""),"",IF('Pivot elenchi'!T65="",'Pivot elenchi'!T64="",'Pivot elenchi'!T65)) | Q66: =IF(AND('Pivot elenchi'!U65="",'Pivot elenchi'!U66=""),"",IF('Pivot elenchi'!U65="",'Pivot elenchi'!U64="",'Pivot elenchi'!U65)) -> REDAZIONI GIORNALISTICHE | R66: @ilsole24ore.com | AB66: =L66 -> 514220 | AC66: =M66 -> REDAZIONE E CORRISP FRANCOFORTE | AD66: =N66 | AE66: =O66 -> QUOTIDIANO | AF66: =P66 | AG66: =Q66 -> REDAZIONI GIORNALISTICHE
A67: Part. Iva | B67: X | L67: =IF(AND('Pivot elenchi'!P66="",'Pivot elenchi'!P67=""),"",IF('Pivot elenchi'!P66="",'Pivot elenchi'!P65="",'Pivot elenchi'!P66)) -> 514300 | M67: =IF(AND('Pivot elenchi'!Q66="",'Pivot elenchi'!Q67=""),"",IF('Pivot elenchi'!Q66="",'Pivot elenchi'!Q65="",'Pivot elenchi'!Q66)) -> REDAZIONE MILANO | N67: =IF(AND('Pivot elenchi'!R66="",'Pivot elenchi'!R67=""),"",IF('Pivot elenchi'!R66="",'Pivot elenchi'!R65="",'Pivot elenchi'!R66)) | O67: =IF(AND('Pivot elenchi'!S66="",'Pivot elenchi'!S67=""),"",IF('Pivot elenchi'!S66="",'Pivot elenchi'!S65="",'Pivot elenchi'!S66)) -> QUOTIDIANO | P67: =IF(AND('Pivot elenchi'!T66="",'Pivot elenchi'!T67=""),"",IF('Pivot elenchi'!T66="",'Pivot elenchi'!T65="",'Pivot elenchi'!T66)) | Q67: =IF(AND('Pivot elenchi'!U66="",'Pivot elenchi'!U67=""),"",IF('Pivot elenchi'!U66="",'Pivot elenchi'!U65="",'Pivot elenchi'!U66)) -> REDAZIONI GIORNALISTICHE | R67: @ilsole24ore.com | AB67: =L67 -> 514300 | AC67: =M67 -> REDAZIONE MILANO | AD67: =N67 | AE67: =O67 -> QUOTIDIANO | AF67: =P67 | AG67: =Q67 -> REDAZIONI GIORNALISTICHE
L68: =IF(AND('Pivot elenchi'!P67="",'Pivot elenchi'!P68=""),"",IF('Pivot elenchi'!P67="",'Pivot elenchi'!P66="",'Pivot elenchi'!P67)) -> 514400 | M68: =IF(AND('Pivot elenchi'!Q67="",'Pivot elenchi'!Q68=""),"",IF('Pivot elenchi'!Q67="",'Pivot elenchi'!Q66="",'Pivot elenchi'!Q67)) -> NOVA 24 | N68: =IF(AND('Pivot elenchi'!R67="",'Pivot elenchi'!R68=""),"",IF('Pivot elenchi'!R67="",'Pivot elenchi'!R66="",'Pivot elenchi'!R67)) | O68: =IF(AND('Pivot elenchi'!S67="",'Pivot elenchi'!S68=""),"",IF('Pivot elenchi'!S67="",'Pivot elenchi'!S66="",'Pivot elenchi'!S67)) -> QUOTIDIANO | P68: =IF(AND('Pivot elenchi'!T67="",'Pivot elenchi'!T68=""),"",IF('Pivot elenchi'!T67="",'Pivot elenchi'!T66="",'Pivot elenchi'!T67)) | Q68: =IF(AND('Pivot elenchi'!U67="",'Pivot elenchi'!U68=""),"",IF('Pivot elenchi'!U67="",'Pivot elenchi'!U66="",'Pivot elenchi'!U67)) -> REDAZIONI GIORNALISTICHE | R68: @ilsole24ore.com | AB68: =L68 -> 514400 | AC68: =M68 -> NOVA 24 | AD68: =N68 | AE68: =O68 -> QUOTIDIANO | AF68: =P68 | AG68: =Q68 -> REDAZIONI GIORNALISTICHE
L69: =IF(AND('Pivot elenchi'!P68="",'Pivot elenchi'!P69=""),"",IF('Pivot elenchi'!P68="",'Pivot elenchi'!P67="",'Pivot elenchi'!P68)) -> 514500 | M69: =IF(AND('Pivot elenchi'!Q68="",'Pivot elenchi'!Q69=""),"",IF('Pivot elenchi'!Q68="",'Pivot elenchi'!Q67="",'Pivot elenchi'!Q68)) -> LUNEDI' | N69: =IF(AND('Pivot elenchi'!R68="",'Pivot elenchi'!R69=""),"",IF('Pivot elenchi'!R68="",'Pivot elenchi'!R67="",'Pivot elenchi'!R68)) | O69: =IF(AND('Pivot elenchi'!S68="",'Pivot elenchi'!S69=""),"",IF('Pivot elenchi'!S68="",'Pivot elenchi'!S67="",'Pivot elenchi'!S68)) -> QUOTIDIANO | P69: =IF(AND('Pivot elenchi'!T68="",'Pivot elenchi'!T69=""),"",IF('Pivot elenchi'!T68="",'Pivot elenchi'!T67="",'Pivot elenchi'!T68)) | Q69: =IF(AND('Pivot elenchi'!U68="",'Pivot elenchi'!U69=""),"",IF('Pivot elenchi'!U68="",'Pivot elenchi'!U67="",'Pivot elenchi'!U68)) -> REDAZIONI GIORNALISTICHE | R69: @ilsole24ore.com | AB69: =L69 -> 514500 | AC69: =M69 -> LUNEDI' | AD69: =N69 | AE69: =O69 -> QUOTIDIANO | AF69: =P69 | AG69: =Q69 -> REDAZIONI GIORNALISTICHE
L70: =IF(AND('Pivot elenchi'!P69="",'Pivot elenchi'!P70=""),"",IF('Pivot elenchi'!P69="",'Pivot elenchi'!P68="",'Pivot elenchi'!P69)) -> 514600 | M70: =IF(AND('Pivot elenchi'!Q69="",'Pivot elenchi'!Q70=""),"",IF('Pivot elenchi'!Q69="",'Pivot elenchi'!Q68="",'Pivot elenchi'!Q69)) -> SEGRETERIA RED. ALTRI PERIODICI | N70: =IF(AND('Pivot elenchi'!R69="",'Pivot elenchi'!R70=""),"",IF('Pivot elenchi'!R69="",'Pivot elenchi'!R68="",'Pivot elenchi'!R69)) | O70: =IF(AND('Pivot elenchi'!S69="",'Pivot elenchi'!S70=""),"",IF('Pivot elenchi'!S69="",'Pivot elenchi'!S68="",'Pivot elenchi'!S69)) -> SERVIZI GENERALI SICUREZZA E AMBIENTE | P70: =IF(AND('Pivot elenchi'!T69="",'Pivot elenchi'!T70=""),"",IF('Pivot elenchi'!T69="",'Pivot elenchi'!T68="",'Pivot elenchi'!T69)) | Q70: =IF(AND('Pivot elenchi'!U69="",'Pivot elenchi'!U70=""),"",IF('Pivot elenchi'!U69="",'Pivot elenchi'!U68="",'Pivot elenchi'!U69)) -> DIREZIONE CENTRALE PERSONALE E ORGANIZZA | R70: @ilsole24ore.com | AB70: =L70 -> 514600 | AC70: =M70 -> SEGRETERIA RED. ALTRI PERIODICI | AD70: =N70 | AE70: =O70 -> SERVIZI GENERALI SICUREZZA E AMBIENTE | AF70: =P70 | AG70: =Q70 -> DIREZIONE CENTRALE PERSONALE E ORGANIZZA
A71: =IF('Scheda Movimento'!C28="","",'Scheda Movimento'!C28) -> Servizio (in) | B71: =IF(A71="","",VLOOKUP(A71,A73:B80,2,FALSE)) -> S | L71: =IF(AND('Pivot elenchi'!P70="",'Pivot elenchi'!P71=""),"",IF('Pivot elenchi'!P70="",'Pivot elenchi'!P69="",'Pivot elenchi'!P70)) -> 514700 | M71: =IF(AND('Pivot elenchi'!Q70="",'Pivot elenchi'!Q71=""),"",IF('Pivot elenchi'!Q70="",'Pivot elenchi'!Q69="",'Pivot elenchi'!Q70)) -> REDAZIONE ROMA | N71: =IF(AND('Pivot elenchi'!R70="",'Pivot elenchi'!R71=""),"",IF('Pivot elenchi'!R70="",'Pivot elenchi'!R69="",'Pivot elenchi'!R70)) | O71: =IF(AND('Pivot elenchi'!S70="",'Pivot elenchi'!S71=""),"",IF('Pivot elenchi'!S70="",'Pivot elenchi'!S69="",'Pivot elenchi'!S70)) -> QUOTIDIANO | P71: =IF(AND('Pivot elenchi'!T70="",'Pivot elenchi'!T71=""),"",IF('Pivot elenchi'!T70="",'Pivot elenchi'!T69="",'Pivot elenchi'!T70)) | Q71: =IF(AND('Pivot elenchi'!U70="",'Pivot elenchi'!U71=""),"",IF('Pivot elenchi'!U70="",'Pivot elenchi'!U69="",'Pivot elenchi'!U70)) -> REDAZIONI GIORNALISTICHE | R71: @ilsole24ore.com | AB71: =L71 -> 514700 | AC71: =M71 -> REDAZIONE ROMA | AD71: =N71 | AE71: =O71 -> QUOTIDIANO | AF71: =P71 | AG71: =Q71 -> REDAZIONI GIORNALISTICHE
A72: STATO | B72: COD | L72: =IF(AND('Pivot elenchi'!P71="",'Pivot elenchi'!P72=""),"",IF('Pivot elenchi'!P71="",'Pivot elenchi'!P70="",'Pivot elenchi'!P71)) -> 514800 | M72: =IF(AND('Pivot elenchi'!Q71="",'Pivot elenchi'!Q72=""),"",IF('Pivot elenchi'!Q71="",'Pivot elenchi'!Q70="",'Pivot elenchi'!Q71)) -> STRUTTURA MEDIA FACTORY ENEL | N72: =IF(AND('Pivot elenchi'!R71="",'Pivot elenchi'!R72=""),"",IF('Pivot elenchi'!R71="",'Pivot elenchi'!R70="",'Pivot elenchi'!R71)) | O72: =IF(AND('Pivot elenchi'!S71="",'Pivot elenchi'!S72=""),"",IF('Pivot elenchi'!S71="",'Pivot elenchi'!S70="",'Pivot elenchi'!S71)) -> PERSONALE GIORNALISTI, RADIO E CULTURA | P72: =IF(AND('Pivot elenchi'!T71="",'Pivot elenchi'!T72=""),"",IF('Pivot elenchi'!T71="",'Pivot elenchi'!T70="",'Pivot elenchi'!T71)) | Q72: =IF(AND('Pivot elenchi'!U71="",'Pivot elenchi'!U72=""),"",IF('Pivot elenchi'!U71="",'Pivot elenchi'!U70="",'Pivot elenchi'!U71)) -> DIREZIONE CENTRALE PERSONALE E ORGANIZZA | R72: @ilsole24ore.com | AB72: =L72 -> 514800 | AC72: =M72 -> STRUTTURA MEDIA FACTORY ENEL | AD72: =N72 | AE72: =O72 -> PERSONALE GIORNALISTI, RADIO E CULTURA | AF72: =P72 | AG72: =Q72 -> DIREZIONE CENTRALE PERSONALE E ORGANIZZA
L73: =IF(AND('Pivot elenchi'!P72="",'Pivot elenchi'!P73=""),"",IF('Pivot elenchi'!P72="",'Pivot elenchi'!P71="",'Pivot elenchi'!P72)) -> 515010 | M73: =IF(AND('Pivot elenchi'!Q72="",'Pivot elenchi'!Q73=""),"",IF('Pivot elenchi'!Q72="",'Pivot elenchi'!Q71="",'Pivot elenchi'!Q72)) -> RCO+ FINANZA E MERCATI MI | N73: =IF(AND('Pivot elenchi'!R72="",'Pivot elenchi'!R73=""),"",IF('Pivot elenchi'!R72="",'Pivot elenchi'!R71="",'Pivot elenchi'!R72)) | O73: =IF(AND('Pivot elenchi'!S72="",'Pivot elenchi'!S73=""),"",IF('Pivot elenchi'!S72="",'Pivot elenchi'!S71="",'Pivot elenchi'!S72)) -> RCO+ | P73: =IF(AND('Pivot elenchi'!T72="",'Pivot elenchi'!T73=""),"",IF('Pivot elenchi'!T72="",'Pivot elenchi'!T71="",'Pivot elenchi'!T72)) | Q73: =IF(AND('Pivot elenchi'!U72="",'Pivot elenchi'!U73=""),"",IF('Pivot elenchi'!U72="",'Pivot elenchi'!U71="",'Pivot elenchi'!U72)) -> REDAZIONI GIORNALISTICHE | R73: @ilsole24ore.com | AB73: =L73 -> 515010 | AC73: =M73 -> RCO+ FINANZA E MERCATI MI | AD73: =N73 | AE73: =O73 -> RCO+ | AF73: =P73 | AG73: =Q73 -> REDAZIONI GIORNALISTICHE
A74: Servizio (in) | B74: S | L74: =IF(AND('Pivot elenchi'!P73="",'Pivot elenchi'!P74=""),"",IF('Pivot elenchi'!P73="",'Pivot elenchi'!P72="",'Pivot elenchi'!P73)) -> 515020 | M74: =IF(AND('Pivot elenchi'!Q73="",'Pivot elenchi'!Q74=""),"",IF('Pivot elenchi'!Q73="",'Pivot elenchi'!Q72="",'Pivot elenchi'!Q73)) -> RCO+ FINANZA E MERCATI RM | N74: =IF(AND('Pivot elenchi'!R73="",'Pivot elenchi'!R74=""),"",IF('Pivot elenchi'!R73="",'Pivot elenchi'!R72="",'Pivot elenchi'!R73)) | O74: =IF(AND('Pivot elenchi'!S73="",'Pivot elenchi'!S74=""),"",IF('Pivot elenchi'!S73="",'Pivot elenchi'!S72="",'Pivot elenchi'!S73)) -> RCO+ | P74: =IF(AND('Pivot elenchi'!T73="",'Pivot elenchi'!T74=""),"",IF('Pivot elenchi'!T73="",'Pivot elenchi'!T72="",'Pivot elenchi'!T73)) | Q74: =IF(AND('Pivot elenchi'!U73="",'Pivot elenchi'!U74=""),"",IF('Pivot elenchi'!U73="",'Pivot elenchi'!U72="",'Pivot elenchi'!U73)) -> REDAZIONI GIORNALISTICHE | R74: @ilsole24ore.com | AB74: =L74 -> 515020 | AC74: =M74 -> RCO+ FINANZA E MERCATI RM | AD74: =N74 | AE74: =O74 -> RCO+ | AF74: =P74 | AG74: =Q74 -> REDAZIONI GIORNALISTICHE
A75: Fine rapporto | B75: F | L75: =IF(AND('Pivot elenchi'!P74="",'Pivot elenchi'!P75=""),"",IF('Pivot elenchi'!P74="",'Pivot elenchi'!P73="",'Pivot elenchi'!P74)) -> 515040 | M75: =IF(AND('Pivot elenchi'!Q74="",'Pivot elenchi'!Q75=""),"",IF('Pivot elenchi'!Q74="",'Pivot elenchi'!Q73="",'Pivot elenchi'!Q74)) -> RCO+ FINANZA E MERCATI PD | N75: =IF(AND('Pivot elenchi'!R74="",'Pivot elenchi'!R75=""),"",IF('Pivot elenchi'!R74="",'Pivot elenchi'!R73="",'Pivot elenchi'!R74)) | O75: =IF(AND('Pivot elenchi'!S74="",'Pivot elenchi'!S75=""),"",IF('Pivot elenchi'!S74="",'Pivot elenchi'!S73="",'Pivot elenchi'!S74)) -> RCO+ | P75: =IF(AND('Pivot elenchi'!T74="",'Pivot elenchi'!T75=""),"",IF('Pivot elenchi'!T74="",'Pivot elenchi'!T73="",'Pivot elenchi'!T74)) | Q75: =IF(AND('Pivot elenchi'!U74="",'Pivot elenchi'!U75=""),"",IF('Pivot elenchi'!U74="",'Pivot elenchi'!U73="",'Pivot elenchi'!U74)) -> REDAZIONI GIORNALISTICHE | R75: @ilsole24ore.com | AB75: =L75 -> 515040 | AC75: =M75 -> RCO+ FINANZA E MERCATI PD | AD75: =N75 | AE75: =O75 -> RCO+ | AF75: =P75 | AG75: =Q75 -> REDAZIONI GIORNALISTICHE
A76: Maternità (in) | B76: M | L76: =IF(AND('Pivot elenchi'!P75="",'Pivot elenchi'!P76=""),"",IF('Pivot elenchi'!P75="",'Pivot elenchi'!P74="",'Pivot elenchi'!P75)) -> 51511001 | M76: =IF(AND('Pivot elenchi'!Q75="",'Pivot elenchi'!Q76=""),"",IF('Pivot elenchi'!Q75="",'Pivot elenchi'!Q74="",'Pivot elenchi'!Q75)) -> SUPPORTI AGENZIA | N76: =IF(AND('Pivot elenchi'!R75="",'Pivot elenchi'!R76=""),"",IF('Pivot elenchi'!R75="",'Pivot elenchi'!R74="",'Pivot elenchi'!R75)) | O76: =IF(AND('Pivot elenchi'!S75="",'Pivot elenchi'!S76=""),"",IF('Pivot elenchi'!S75="",'Pivot elenchi'!S74="",'Pivot elenchi'!S75)) -> SERVIZI GENERALI SICUREZZA E AMBIENTE | P76: =IF(AND('Pivot elenchi'!T75="",'Pivot elenchi'!T76=""),"",IF('Pivot elenchi'!T75="",'Pivot elenchi'!T74="",'Pivot elenchi'!T75)) | Q76: =IF(AND('Pivot elenchi'!U75="",'Pivot elenchi'!U76=""),"",IF('Pivot elenchi'!U75="",'Pivot elenchi'!U74="",'Pivot elenchi'!U75)) -> DIREZIONE CENTRALE PERSONALE E ORGANIZZA | R76: @ilsole24ore.com | AB76: =L76 -> 51511001 | AC76: =M76 -> SUPPORTI AGENZIA | AD76: =N76 | AE76: =O76 -> SERVIZI GENERALI SICUREZZA E AMBIENTE | AF76: =P76 | AG76: =Q76 -> DIREZIONE CENTRALE PERSONALE E ORGANIZZA
A77: Aspettativa (in) | B77: A | L77: =IF(AND('Pivot elenchi'!P76="",'Pivot elenchi'!P77=""),"",IF('Pivot elenchi'!P76="",'Pivot elenchi'!P75="",'Pivot elenchi'!P76)) -> 516000 | M77: =IF(AND('Pivot elenchi'!Q76="",'Pivot elenchi'!Q77=""),"",IF('Pivot elenchi'!Q76="",'Pivot elenchi'!Q75="",'Pivot elenchi'!Q76)) -> ON LINE REDAZIONE | N77: =IF(AND('Pivot elenchi'!R76="",'Pivot elenchi'!R77=""),"",IF('Pivot elenchi'!R76="",'Pivot elenchi'!R75="",'Pivot elenchi'!R76)) | O77: =IF(AND('Pivot elenchi'!S76="",'Pivot elenchi'!S77=""),"",IF('Pivot elenchi'!S76="",'Pivot elenchi'!S75="",'Pivot elenchi'!S76)) -> QUOTIDIANO | P77: =IF(AND('Pivot elenchi'!T76="",'Pivot elenchi'!T77=""),"",IF('Pivot elenchi'!T76="",'Pivot elenchi'!T75="",'Pivot elenchi'!T76)) | Q77: =IF(AND('Pivot elenchi'!U76="",'Pivot elenchi'!U77=""),"",IF('Pivot elenchi'!U76="",'Pivot elenchi'!U75="",'Pivot elenchi'!U76)) -> REDAZIONI GIORNALISTICHE | R77: @ilsole24ore.com | AB77: =L77 -> 516000 | AC77: =M77 -> ON LINE REDAZIONE | AD77: =N77 | AE77: =O77 -> QUOTIDIANO | AF77: =P77 | AG77: =Q77 -> REDAZIONI GIORNALISTICHE
L78: =IF(AND('Pivot elenchi'!P77="",'Pivot elenchi'!P78=""),"",IF('Pivot elenchi'!P77="",'Pivot elenchi'!P76="",'Pivot elenchi'!P77)) -> 518200 | M78: =IF(AND('Pivot elenchi'!Q77="",'Pivot elenchi'!Q78=""),"",IF('Pivot elenchi'!Q77="",'Pivot elenchi'!Q76="",'Pivot elenchi'!Q77)) -> HOW TO SPEND IT | N78: =IF(AND('Pivot elenchi'!R77="",'Pivot elenchi'!R78=""),"",IF('Pivot elenchi'!R77="",'Pivot elenchi'!R76="",'Pivot elenchi'!R77)) | O78: =IF(AND('Pivot elenchi'!S77="",'Pivot elenchi'!S78=""),"",IF('Pivot elenchi'!S77="",'Pivot elenchi'!S76="",'Pivot elenchi'!S77)) -> ALTRE TESTATE | P78: =IF(AND('Pivot elenchi'!T77="",'Pivot elenchi'!T78=""),"",IF('Pivot elenchi'!T77="",'Pivot elenchi'!T76="",'Pivot elenchi'!T77)) | Q78: =IF(AND('Pivot elenchi'!U77="",'Pivot elenchi'!U78=""),"",IF('Pivot elenchi'!U77="",'Pivot elenchi'!U76="",'Pivot elenchi'!U77)) -> REDAZIONI GIORNALISTICHE | R78: @ilsole24ore.com | AB78: =L78 -> 518200 | AC78: =M78 -> HOW TO SPEND IT | AD78: =N78 | AE78: =O78 -> ALTRE TESTATE | AF78: =P78 | AG78: =Q78 -> REDAZIONI GIORNALISTICHE
L79: =IF(AND('Pivot elenchi'!P78="",'Pivot elenchi'!P79=""),"",IF('Pivot elenchi'!P78="",'Pivot elenchi'!P77="",'Pivot elenchi'!P78)) -> 51820001 | M79: =IF(AND('Pivot elenchi'!Q78="",'Pivot elenchi'!Q79=""),"",IF('Pivot elenchi'!Q78="",'Pivot elenchi'!Q77="",'Pivot elenchi'!Q78)) -> HOW TO SPEND IT | N79: =IF(AND('Pivot elenchi'!R78="",'Pivot elenchi'!R79=""),"",IF('Pivot elenchi'!R78="",'Pivot elenchi'!R77="",'Pivot elenchi'!R78)) | O79: =IF(AND('Pivot elenchi'!S78="",'Pivot elenchi'!S79=""),"",IF('Pivot elenchi'!S78="",'Pivot elenchi'!S77="",'Pivot elenchi'!S78)) -> SERVIZI GENERALI SICUREZZA E AMBIENTE | P79: =IF(AND('Pivot elenchi'!T78="",'Pivot elenchi'!T79=""),"",IF('Pivot elenchi'!T78="",'Pivot elenchi'!T77="",'Pivot elenchi'!T78)) | Q79: =IF(AND('Pivot elenchi'!U78="",'Pivot elenchi'!U79=""),"",IF('Pivot elenchi'!U78="",'Pivot elenchi'!U77="",'Pivot elenchi'!U78)) -> DIREZIONE CENTRALE PERSONALE E ORGANIZZA | R79: @ilsole24ore.com | AB79: =L79 -> 51820001 | AC79: =M79 -> HOW TO SPEND IT | AD79: =N79 | AE79: =O79 -> SERVIZI GENERALI SICUREZZA E AMBIENTE | AF79: =P79 | AG79: =Q79 -> DIREZIONE CENTRALE PERSONALE E ORGANIZZA
L80: =IF(AND('Pivot elenchi'!P79="",'Pivot elenchi'!P80=""),"",IF('Pivot elenchi'!P79="",'Pivot elenchi'!P78="",'Pivot elenchi'!P79)) -> 610000 | M80: =IF(AND('Pivot elenchi'!Q79="",'Pivot elenchi'!Q80=""),"",IF('Pivot elenchi'!Q79="",'Pivot elenchi'!Q78="",'Pivot elenchi'!Q79)) -> DG SYSTEM 24 | N80: =IF(AND('Pivot elenchi'!R79="",'Pivot elenchi'!R80=""),"",IF('Pivot elenchi'!R79="",'Pivot elenchi'!R78="",'Pivot elenchi'!R79)) | O80: =IF(AND('Pivot elenchi'!S79="",'Pivot elenchi'!S80=""),"",IF('Pivot elenchi'!S79="",'Pivot elenchi'!S78="",'Pivot elenchi'!S79)) -> DG SYSTEM 24 | P80: =IF(AND('Pivot elenchi'!T79="",'Pivot elenchi'!T80=""),"",IF('Pivot elenchi'!T79="",'Pivot elenchi'!T78="",'Pivot elenchi'!T79)) | Q80: =IF(AND('Pivot elenchi'!U79="",'Pivot elenchi'!U80=""),"",IF('Pivot elenchi'!U79="",'Pivot elenchi'!U78="",'Pivot elenchi'!U79)) -> DG M&B - DG SYSTEM 24 | R80: @ilsole24ore.com | AB80: =L80 -> 610000 | AC80: =M80 -> DG SYSTEM 24 | AD80: =N80 | AE80: =O80 -> DG SYSTEM 24 | AF80: =P80 | AG80: =Q80 -> DG M&B - DG SYSTEM 24
L81: =IF(AND('Pivot elenchi'!P80="",'Pivot elenchi'!P81=""),"",IF('Pivot elenchi'!P80="",'Pivot elenchi'!P79="",'Pivot elenchi'!P80)) -> 611310 | M81: =IF(AND('Pivot elenchi'!Q80="",'Pivot elenchi'!Q81=""),"",IF('Pivot elenchi'!Q80="",'Pivot elenchi'!Q79="",'Pivot elenchi'!Q80)) -> PIANIF. E IMPAGINAZ. QUOTIDIANO | N81: =IF(AND('Pivot elenchi'!R80="",'Pivot elenchi'!R81=""),"",IF('Pivot elenchi'!R80="",'Pivot elenchi'!R79="",'Pivot elenchi'!R80)) | O81: =IF(AND('Pivot elenchi'!S80="",'Pivot elenchi'!S81=""),"",IF('Pivot elenchi'!S80="",'Pivot elenchi'!S79="",'Pivot elenchi'!S80)) -> SYSTEM 24 - OPERATIONS | P81: =IF(AND('Pivot elenchi'!T80="",'Pivot elenchi'!T81=""),"",IF('Pivot elenchi'!T80="",'Pivot elenchi'!T79="",'Pivot elenchi'!T80)) | Q81: =IF(AND('Pivot elenchi'!U80="",'Pivot elenchi'!U81=""),"",IF('Pivot elenchi'!U80="",'Pivot elenchi'!U79="",'Pivot elenchi'!U80)) -> DG M&B - DG SYSTEM 24 | R81: @ilsole24ore.com | AB81: =L81 -> 611310 | AC81: =M81 -> PIANIF. E IMPAGINAZ. QUOTIDIANO | AD81: =N81 | AE81: =O81 -> SYSTEM 24 - OPERATIONS | AF81: =P81 | AG81: =Q81 -> DG M&B - DG SYSTEM 24
A82: =IF('Scheda Movimento'!C31="","",'Scheda Movimento'!C31) -> IMPIEGATO CON USO VDT | B82: =IF(A82="","",VLOOKUP(A82,A84:B112,2,FALSE)) -> IMP_VDT | L82: =IF(AND('Pivot elenchi'!P81="",'Pivot elenchi'!P82=""),"",IF('Pivot elenchi'!P81="",'Pivot elenchi'!P80="",'Pivot elenchi'!P81)) -> 61131010 | M82: =IF(AND('Pivot elenchi'!Q81="",'Pivot elenchi'!Q82=""),"",IF('Pivot elenchi'!Q81="",'Pivot elenchi'!Q80="",'Pivot elenchi'!Q81)) -> OPERATIONS EDITORIALE ADVERTISI | N82: =IF(AND('Pivot elenchi'!R81="",'Pivot elenchi'!R82=""),"",IF('Pivot elenchi'!R81="",'Pivot elenchi'!R80="",'Pivot elenchi'!R81)) | O82: =IF(AND('Pivot elenchi'!S81="",'Pivot elenchi'!S82=""),"",IF('Pivot elenchi'!S81="",'Pivot elenchi'!S80="",'Pivot elenchi'!S81)) -> SYSTEM 24 - OPERATIONS | P82: =IF(AND('Pivot elenchi'!T81="",'Pivot elenchi'!T82=""),"",IF('Pivot elenchi'!T81="",'Pivot elenchi'!T80="",'Pivot elenchi'!T81)) | Q82: =IF(AND('Pivot elenchi'!U81="",'Pivot elenchi'!U82=""),"",IF('Pivot elenchi'!U81="",'Pivot elenchi'!U80="",'Pivot elenchi'!U81)) -> DG M&B - DG SYSTEM 24 | R82: @ilsole24ore.com | AB82: =L82 -> 61131010 | AC82: =M82 -> OPERATIONS EDITORIALE ADVERTISI | AD82: =N82 | AE82: =O82 -> SYSTEM 24 - OPERATIONS | AF82: =P82 | AG82: =Q82 -> DG M&B - DG SYSTEM 24
A83: MANSIONE (sicurezza lavoro) | B83: COD | L83: =IF(AND('Pivot elenchi'!P82="",'Pivot elenchi'!P83=""),"",IF('Pivot elenchi'!P82="",'Pivot elenchi'!P81="",'Pivot elenchi'!P82)) -> 611320 | M83: =IF(AND('Pivot elenchi'!Q82="",'Pivot elenchi'!Q83=""),"",IF('Pivot elenchi'!Q82="",'Pivot elenchi'!Q81="",'Pivot elenchi'!Q82)) -> PIANIF. E IMPAG. PERIOD E RADIO | N83: =IF(AND('Pivot elenchi'!R82="",'Pivot elenchi'!R83=""),"",IF('Pivot elenchi'!R82="",'Pivot elenchi'!R81="",'Pivot elenchi'!R82)) | O83: =IF(AND('Pivot elenchi'!S82="",'Pivot elenchi'!S83=""),"",IF('Pivot elenchi'!S82="",'Pivot elenchi'!S81="",'Pivot elenchi'!S82)) -> SYSTEM 24 - OPERATIONS | P83: =IF(AND('Pivot elenchi'!T82="",'Pivot elenchi'!T83=""),"",IF('Pivot elenchi'!T82="",'Pivot elenchi'!T81="",'Pivot elenchi'!T82)) | Q83: =IF(AND('Pivot elenchi'!U82="",'Pivot elenchi'!U83=""),"",IF('Pivot elenchi'!U82="",'Pivot elenchi'!U81="",'Pivot elenchi'!U82)) -> DG M&B - DG SYSTEM 24 | R83: @ilsole24ore.com | AB83: =L83 -> 611320 | AC83: =M83 -> PIANIF. E IMPAG. PERIOD E RADIO | AD83: =N83 | AE83: =O83 -> SYSTEM 24 - OPERATIONS | AF83: =P83 | AG83: =Q83 -> DG M&B - DG SYSTEM 24
L84: =IF(AND('Pivot elenchi'!P83="",'Pivot elenchi'!P84=""),"",IF('Pivot elenchi'!P83="",'Pivot elenchi'!P82="",'Pivot elenchi'!P83)) -> 611330 | M84: =IF(AND('Pivot elenchi'!Q83="",'Pivot elenchi'!Q84=""),"",IF('Pivot elenchi'!Q83="",'Pivot elenchi'!Q82="",'Pivot elenchi'!Q83)) -> GESTIONE PROVVIGIONE AGENTI | N84: =IF(AND('Pivot elenchi'!R83="",'Pivot elenchi'!R84=""),"",IF('Pivot elenchi'!R83="",'Pivot elenchi'!R82="",'Pivot elenchi'!R83)) | O84: =IF(AND('Pivot elenchi'!S83="",'Pivot elenchi'!S84=""),"",IF('Pivot elenchi'!S83="",'Pivot elenchi'!S82="",'Pivot elenchi'!S83)) -> SYSTEM 24 - OPERATIONS | P84: =IF(AND('Pivot elenchi'!T83="",'Pivot elenchi'!T84=""),"",IF('Pivot elenchi'!T83="",'Pivot elenchi'!T82="",'Pivot elenchi'!T83)) | Q84: =IF(AND('Pivot elenchi'!U83="",'Pivot elenchi'!U84=""),"",IF('Pivot elenchi'!U83="",'Pivot elenchi'!U82="",'Pivot elenchi'!U83)) -> DG M&B - DG SYSTEM 24 | R84: @ilsole24ore.com | AB84: =L84 -> 611330 | AC84: =M84 -> GESTIONE PROVVIGIONE AGENTI | AD84: =N84 | AE84: =O84 -> SYSTEM 24 - OPERATIONS | AF84: =P84 | AG84: =Q84 -> DG M&B - DG SYSTEM 24
A85: ADDETTO SERV. GEN. (Centr.no, Uff. Posta, Portineria) | B85: ADD_GEN | L85: =IF(AND('Pivot elenchi'!P84="",'Pivot elenchi'!P85=""),"",IF('Pivot elenchi'!P84="",'Pivot elenchi'!P83="",'Pivot elenchi'!P84)) -> 612050 | M85: =IF(AND('Pivot elenchi'!Q84="",'Pivot elenchi'!Q85=""),"",IF('Pivot elenchi'!Q84="",'Pivot elenchi'!Q83="",'Pivot elenchi'!Q84)) -> MARKETING SYSTEM 24 | N85: =IF(AND('Pivot elenchi'!R84="",'Pivot elenchi'!R85=""),"",IF('Pivot elenchi'!R84="",'Pivot elenchi'!R83="",'Pivot elenchi'!R84)) | O85: =IF(AND('Pivot elenchi'!S84="",'Pivot elenchi'!S85=""),"",IF('Pivot elenchi'!S84="",'Pivot elenchi'!S83="",'Pivot elenchi'!S84)) -> MARKETING SYSTEM24 | P85: =IF(AND('Pivot elenchi'!T84="",'Pivot elenchi'!T85=""),"",IF('Pivot elenchi'!T84="",'Pivot elenchi'!T83="",'Pivot elenchi'!T84)) | Q85: =IF(AND('Pivot elenchi'!U84="",'Pivot elenchi'!U85=""),"",IF('Pivot elenchi'!U84="",'Pivot elenchi'!U83="",'Pivot elenchi'!U84)) -> DG M&B - DG SYSTEM 24 | R85: @ilsole24ore.com | AB85: =L85 -> 612050 | AC85: =M85 -> MARKETING SYSTEM 24 | AD85: =N85 | AE85: =O85 -> MARKETING SYSTEM24 | AF85: =P85 | AG85: =Q85 -> DG M&B - DG SYSTEM 24
A86: ADDETTO AI SERV. E SUPPORTI REDAZIONALI | B86: ADD_RED | L86: =IF(AND('Pivot elenchi'!P85="",'Pivot elenchi'!P86=""),"",IF('Pivot elenchi'!P85="",'Pivot elenchi'!P84="",'Pivot elenchi'!P85)) -> 61207010 | M86: =IF(AND('Pivot elenchi'!Q85="",'Pivot elenchi'!Q86=""),"",IF('Pivot elenchi'!Q85="",'Pivot elenchi'!Q84="",'Pivot elenchi'!Q85)) -> SVILUPPO DIGITAL ADVERTISING | N86: =IF(AND('Pivot elenchi'!R85="",'Pivot elenchi'!R86=""),"",IF('Pivot elenchi'!R85="",'Pivot elenchi'!R84="",'Pivot elenchi'!R85)) | O86: =IF(AND('Pivot elenchi'!S85="",'Pivot elenchi'!S86=""),"",IF('Pivot elenchi'!S85="",'Pivot elenchi'!S84="",'Pivot elenchi'!S85)) -> DIGITAL ADVERTISING | P86: =IF(AND('Pivot elenchi'!T85="",'Pivot elenchi'!T86=""),"",IF('Pivot elenchi'!T85="",'Pivot elenchi'!T84="",'Pivot elenchi'!T85)) | Q86: =IF(AND('Pivot elenchi'!U85="",'Pivot elenchi'!U86=""),"",IF('Pivot elenchi'!U85="",'Pivot elenchi'!U84="",'Pivot elenchi'!U85)) -> DG M&B - DG SYSTEM 24 | R86: @ilsole24ore.com | AB86: =L86 -> 61207010 | AC86: =M86 -> SVILUPPO DIGITAL ADVERTISING | AD86: =N86 | AE86: =O86 -> DIGITAL ADVERTISING | AF86: =P86 | AG86: =Q86 -> DG M&B - DG SYSTEM 24
A87: ASS.TE DI REDAZIONE (TUTTI)/ ASS.TE PROD. PROGR. RADIO | B87: ASS_RED | L87: =IF(AND('Pivot elenchi'!P86="",'Pivot elenchi'!P87=""),"",IF('Pivot elenchi'!P86="",'Pivot elenchi'!P85="",'Pivot elenchi'!P86)) -> 61207020 | M87: =IF(AND('Pivot elenchi'!Q86="",'Pivot elenchi'!Q87=""),"",IF('Pivot elenchi'!Q86="",'Pivot elenchi'!Q85="",'Pivot elenchi'!Q86)) -> DIGITAL MARKETING ADVERTISING | N87: =IF(AND('Pivot elenchi'!R86="",'Pivot elenchi'!R87=""),"",IF('Pivot elenchi'!R86="",'Pivot elenchi'!R85="",'Pivot elenchi'!R86)) | O87: =IF(AND('Pivot elenchi'!S86="",'Pivot elenchi'!S87=""),"",IF('Pivot elenchi'!S86="",'Pivot elenchi'!S85="",'Pivot elenchi'!S86)) -> DIGITAL ADVERTISING | P87: =IF(AND('Pivot elenchi'!T86="",'Pivot elenchi'!T87=""),"",IF('Pivot elenchi'!T86="",'Pivot elenchi'!T85="",'Pivot elenchi'!T86)) | Q87: =IF(AND('Pivot elenchi'!U86="",'Pivot elenchi'!U87=""),"",IF('Pivot elenchi'!U86="",'Pivot elenchi'!U85="",'Pivot elenchi'!U86)) -> DG M&B - DG SYSTEM 24 | R87: @ilsole24ore.com | AB87: =L87 -> 61207020 | AC87: =M87 -> DIGITAL MARKETING ADVERTISING | AD87: =N87 | AE87: =O87 -> DIGITAL ADVERTISING | AF87: =P87 | AG87: =Q87 -> DG M&B - DG SYSTEM 24
A88: GIORNALISTA | B88: GIOR | L88: =IF(AND('Pivot elenchi'!P87="",'Pivot elenchi'!P88=""),"",IF('Pivot elenchi'!P87="",'Pivot elenchi'!P86="",'Pivot elenchi'!P87)) -> 612100 | M88: =IF(AND('Pivot elenchi'!Q87="",'Pivot elenchi'!Q88=""),"",IF('Pivot elenchi'!Q87="",'Pivot elenchi'!Q86="",'Pivot elenchi'!Q87)) -> VENDITE ADVT TIPOLOGIA DI SERV. | N88: =IF(AND('Pivot elenchi'!R87="",'Pivot elenchi'!R88=""),"",IF('Pivot elenchi'!R87="",'Pivot elenchi'!R86="",'Pivot elenchi'!R87)) | O88: =IF(AND('Pivot elenchi'!S87="",'Pivot elenchi'!S88=""),"",IF('Pivot elenchi'!S87="",'Pivot elenchi'!S86="",'Pivot elenchi'!S87)) -> ADVERTISING STAMPA | P88: =IF(AND('Pivot elenchi'!T87="",'Pivot elenchi'!T88=""),"",IF('Pivot elenchi'!T87="",'Pivot elenchi'!T86="",'Pivot elenchi'!T87)) | Q88: =IF(AND('Pivot elenchi'!U87="",'Pivot elenchi'!U88=""),"",IF('Pivot elenchi'!U87="",'Pivot elenchi'!U86="",'Pivot elenchi'!U87)) -> DG M&B - DG SYSTEM 24 | R88: @ilsole24ore.com | AB88: =L88 -> 612100 | AC88: =M88 -> VENDITE ADVT TIPOLOGIA DI SERV. | AD88: =N88 | AE88: =O88 -> ADVERTISING STAMPA | AF88: =P88 | AG88: =Q88 -> DG M&B - DG SYSTEM 24
A89: GIORNALISTA CONDUTTORE (Radio 24) | B89: GIOR_CON | L89: =IF(AND('Pivot elenchi'!P88="",'Pivot elenchi'!P89=""),"",IF('Pivot elenchi'!P88="",'Pivot elenchi'!P87="",'Pivot elenchi'!P88)) -> 612300 | M89: =IF(AND('Pivot elenchi'!Q88="",'Pivot elenchi'!Q89=""),"",IF('Pivot elenchi'!Q88="",'Pivot elenchi'!Q87="",'Pivot elenchi'!Q88)) -> ANALISI E RICERCHE SYSTEM24 | N89: =IF(AND('Pivot elenchi'!R88="",'Pivot elenchi'!R89=""),"",IF('Pivot elenchi'!R88="",'Pivot elenchi'!R87="",'Pivot elenchi'!R88)) | O89: =IF(AND('Pivot elenchi'!S88="",'Pivot elenchi'!S89=""),"",IF('Pivot elenchi'!S88="",'Pivot elenchi'!S87="",'Pivot elenchi'!S88)) -> MARKETING SYSTEM24 | P89: =IF(AND('Pivot elenchi'!T88="",'Pivot elenchi'!T89=""),"",IF('Pivot elenchi'!T88="",'Pivot elenchi'!T87="",'Pivot elenchi'!T88)) | Q89: =IF(AND('Pivot elenchi'!U88="",'Pivot elenchi'!U89=""),"",IF('Pivot elenchi'!U88="",'Pivot elenchi'!U87="",'Pivot elenchi'!U88)) -> DG M&B - DG SYSTEM 24 | R89: @ilsole24ore.com | AB89: =L89 -> 612300 | AC89: =M89 -> ANALISI E RICERCHE SYSTEM24 | AD89: =N89 | AE89: =O89 -> MARKETING SYSTEM24 | AF89: =P89 | AG89: =Q89 -> DG M&B - DG SYSTEM 24
A90: GIORNALISTA CONDUTTORE GR (Radio 24) | B90: GIOR_CON_GR | L90: =IF(AND('Pivot elenchi'!P89="",'Pivot elenchi'!P90=""),"",IF('Pivot elenchi'!P89="",'Pivot elenchi'!P88="",'Pivot elenchi'!P89)) -> 613950 | M90: =IF(AND('Pivot elenchi'!Q89="",'Pivot elenchi'!Q90=""),"",IF('Pivot elenchi'!Q89="",'Pivot elenchi'!Q88="",'Pivot elenchi'!Q89)) -> VENDITE CENTRI MEDIA E AGENZIE | N90: =IF(AND('Pivot elenchi'!R89="",'Pivot elenchi'!R90=""),"",IF('Pivot elenchi'!R89="",'Pivot elenchi'!R88="",'Pivot elenchi'!R89)) | O90: =IF(AND('Pivot elenchi'!S89="",'Pivot elenchi'!S90=""),"",IF('Pivot elenchi'!S89="",'Pivot elenchi'!S88="",'Pivot elenchi'!S89)) -> DIREZIONE ADVERTISING CENTRI MEDIA | P90: =IF(AND('Pivot elenchi'!T89="",'Pivot elenchi'!T90=""),"",IF('Pivot elenchi'!T89="",'Pivot elenchi'!T88="",'Pivot elenchi'!T89)) | Q90: =IF(AND('Pivot elenchi'!U89="",'Pivot elenchi'!U90=""),"",IF('Pivot elenchi'!U89="",'Pivot elenchi'!U88="",'Pivot elenchi'!U89)) -> DG M&B - DG SYSTEM 24 | R90: @ilsole24ore.com | AB90: =L90 -> 613950 | AC90: =M90 -> VENDITE CENTRI MEDIA E AGENZIE | AD90: =N90 | AE90: =O90 -> DIREZIONE ADVERTISING CENTRI MEDIA | AF90: =P90 | AG90: =Q90 -> DG M&B - DG SYSTEM 24
A91: GORNALISTA IN AREE SPECIALI | B91: GIOR_INV | L91: =IF(AND('Pivot elenchi'!P90="",'Pivot elenchi'!P91=""),"",IF('Pivot elenchi'!P90="",'Pivot elenchi'!P89="",'Pivot elenchi'!P90)) -> 614000 | M91: =IF(AND('Pivot elenchi'!Q90="",'Pivot elenchi'!Q91=""),"",IF('Pivot elenchi'!Q90="",'Pivot elenchi'!Q89="",'Pivot elenchi'!Q90)) -> OPERATIONS SYSTEM 24 | N91: =IF(AND('Pivot elenchi'!R90="",'Pivot elenchi'!R91=""),"",IF('Pivot elenchi'!R90="",'Pivot elenchi'!R89="",'Pivot elenchi'!R90)) | O91: =IF(AND('Pivot elenchi'!S90="",'Pivot elenchi'!S91=""),"",IF('Pivot elenchi'!S90="",'Pivot elenchi'!S89="",'Pivot elenchi'!S90)) -> SYSTEM 24 - OPERATIONS | P91: =IF(AND('Pivot elenchi'!T90="",'Pivot elenchi'!T91=""),"",IF('Pivot elenchi'!T90="",'Pivot elenchi'!T89="",'Pivot elenchi'!T90)) | Q91: =IF(AND('Pivot elenchi'!U90="",'Pivot elenchi'!U91=""),"",IF('Pivot elenchi'!U90="",'Pivot elenchi'!U89="",'Pivot elenchi'!U90)) -> DG M&B - DG SYSTEM 24 | R91: @ilsole24ore.com | AB91: =L91 -> 614000 | AC91: =M91 -> OPERATIONS SYSTEM 24 | AD91: =N91 | AE91: =O91 -> SYSTEM 24 - OPERATIONS | AF91: =P91 | AG91: =Q91 -> DG M&B - DG SYSTEM 24
A92: IMPIEGATO CON USO DI VDT CON MENO DI 20 ORE | B92: IMP | L92: =IF(AND('Pivot elenchi'!P91="",'Pivot elenchi'!P92=""),"",IF('Pivot elenchi'!P91="",'Pivot elenchi'!P90="",'Pivot elenchi'!P91)) -> 61400010 | M92: =IF(AND('Pivot elenchi'!Q91="",'Pivot elenchi'!Q92=""),"",IF('Pivot elenchi'!Q91="",'Pivot elenchi'!Q90="",'Pivot elenchi'!Q91)) -> SALES PLANNING & REPORTING | N92: =IF(AND('Pivot elenchi'!R91="",'Pivot elenchi'!R92=""),"",IF('Pivot elenchi'!R91="",'Pivot elenchi'!R90="",'Pivot elenchi'!R91)) | O92: =IF(AND('Pivot elenchi'!S91="",'Pivot elenchi'!S92=""),"",IF('Pivot elenchi'!S91="",'Pivot elenchi'!S90="",'Pivot elenchi'!S91)) -> SYSTEM 24 - OPERATIONS | P92: =IF(AND('Pivot elenchi'!T91="",'Pivot elenchi'!T92=""),"",IF('Pivot elenchi'!T91="",'Pivot elenchi'!T90="",'Pivot elenchi'!T91)) | Q92: =IF(AND('Pivot elenchi'!U91="",'Pivot elenchi'!U92=""),"",IF('Pivot elenchi'!U91="",'Pivot elenchi'!U90="",'Pivot elenchi'!U91)) -> DG M&B - DG SYSTEM 24 | R92: @ilsole24ore.com | AB92: =L92 -> 61400010 | AC92: =M92 -> SALES PLANNING & REPORTING | AD92: =N92 | AE92: =O92 -> SYSTEM 24 - OPERATIONS | AF92: =P92 | AG92: =Q92 -> DG M&B - DG SYSTEM 24
A93: IMPIEGATO ORGANIZZAZIONE EVENTI (24 ORE Cultura) | B93: IMP_ADD_EV | L93: =IF(AND('Pivot elenchi'!P92="",'Pivot elenchi'!P93=""),"",IF('Pivot elenchi'!P92="",'Pivot elenchi'!P91="",'Pivot elenchi'!P92)) -> 61400020 | M93: =IF(AND('Pivot elenchi'!Q92="",'Pivot elenchi'!Q93=""),"",IF('Pivot elenchi'!Q92="",'Pivot elenchi'!Q91="",'Pivot elenchi'!Q92)) -> SEGRETERIA COMMERCIALE | N93: =IF(AND('Pivot elenchi'!R92="",'Pivot elenchi'!R93=""),"",IF('Pivot elenchi'!R92="",'Pivot elenchi'!R91="",'Pivot elenchi'!R92)) | O93: =IF(AND('Pivot elenchi'!S92="",'Pivot elenchi'!S93=""),"",IF('Pivot elenchi'!S92="",'Pivot elenchi'!S91="",'Pivot elenchi'!S92)) -> SYSTEM 24 - OPERATIONS | P93: =IF(AND('Pivot elenchi'!T92="",'Pivot elenchi'!T93=""),"",IF('Pivot elenchi'!T92="",'Pivot elenchi'!T91="",'Pivot elenchi'!T92)) | Q93: =IF(AND('Pivot elenchi'!U92="",'Pivot elenchi'!U93=""),"",IF('Pivot elenchi'!U92="",'Pivot elenchi'!U91="",'Pivot elenchi'!U92)) -> DG M&B - DG SYSTEM 24 | R93: @ilsole24ore.com | AB93: =L93 -> 61400020 | AC93: =M93 -> SEGRETERIA COMMERCIALE | AD93: =N93 | AE93: =O93 -> SYSTEM 24 - OPERATIONS | AF93: =P93 | AG93: =Q93 -> DG M&B - DG SYSTEM 24
A94: IMPIEGATO CON USO AUTO | B94: IMP_AUT | L94: =IF(AND('Pivot elenchi'!P93="",'Pivot elenchi'!P94=""),"",IF('Pivot elenchi'!P93="",'Pivot elenchi'!P92="",'Pivot elenchi'!P93)) -> 61400030 | M94: =IF(AND('Pivot elenchi'!Q93="",'Pivot elenchi'!Q94=""),"",IF('Pivot elenchi'!Q93="",'Pivot elenchi'!Q92="",'Pivot elenchi'!Q93)) -> SUPPORTI SEGRETARIALI | N94: =IF(AND('Pivot elenchi'!R93="",'Pivot elenchi'!R94=""),"",IF('Pivot elenchi'!R93="",'Pivot elenchi'!R92="",'Pivot elenchi'!R93)) | O94: =IF(AND('Pivot elenchi'!S93="",'Pivot elenchi'!S94=""),"",IF('Pivot elenchi'!S93="",'Pivot elenchi'!S92="",'Pivot elenchi'!S93)) -> SYSTEM 24 - OPERATIONS | P94: =IF(AND('Pivot elenchi'!T93="",'Pivot elenchi'!T94=""),"",IF('Pivot elenchi'!T93="",'Pivot elenchi'!T92="",'Pivot elenchi'!T93)) | Q94: =IF(AND('Pivot elenchi'!U93="",'Pivot elenchi'!U94=""),"",IF('Pivot elenchi'!U93="",'Pivot elenchi'!U92="",'Pivot elenchi'!U93)) -> DG M&B - DG SYSTEM 24 | R94: @ilsole24ore.com | AB94: =L94 -> 61400030 | AC94: =M94 -> SUPPORTI SEGRETARIALI | AD94: =N94 | AE94: =O94 -> SYSTEM 24 - OPERATIONS | AF94: =P94 | AG94: =Q94 -> DG M&B - DG SYSTEM 24
A95: IMPEPIEGATO VDT CON MANSIONE TECNICHE (Sic. e Logistica) | B95: IMP_TEC | L95: =IF(AND('Pivot elenchi'!P94="",'Pivot elenchi'!P95=""),"",IF('Pivot elenchi'!P94="",'Pivot elenchi'!P93="",'Pivot elenchi'!P94)) -> 615000 | M95: =IF(AND('Pivot elenchi'!Q94="",'Pivot elenchi'!Q95=""),"",IF('Pivot elenchi'!Q94="",'Pivot elenchi'!Q93="",'Pivot elenchi'!Q94)) -> PIANIFICAZIONE WEB | N95: =IF(AND('Pivot elenchi'!R94="",'Pivot elenchi'!R95=""),"",IF('Pivot elenchi'!R94="",'Pivot elenchi'!R93="",'Pivot elenchi'!R94)) | O95: =IF(AND('Pivot elenchi'!S94="",'Pivot elenchi'!S95=""),"",IF('Pivot elenchi'!S94="",'Pivot elenchi'!S93="",'Pivot elenchi'!S94)) -> SYSTEM 24 - OPERATIONS | P95: =IF(AND('Pivot elenchi'!T94="",'Pivot elenchi'!T95=""),"",IF('Pivot elenchi'!T94="",'Pivot elenchi'!T93="",'Pivot elenchi'!T94)) | Q95: =IF(AND('Pivot elenchi'!U94="",'Pivot elenchi'!U95=""),"",IF('Pivot elenchi'!U94="",'Pivot elenchi'!U93="",'Pivot elenchi'!U94)) -> DG M&B - DG SYSTEM 24 | R95: @ilsole24ore.com | AB95: =L95 -> 615000 | AC95: =M95 -> PIANIFICAZIONE WEB | AD95: =N95 | AE95: =O95 -> SYSTEM 24 - OPERATIONS | AF95: =P95 | AG95: =Q95 -> DG M&B - DG SYSTEM 24
A96: IMPIEGATO CON USO VDT | B96: IMP_VDT | L96: =IF(AND('Pivot elenchi'!P95="",'Pivot elenchi'!P96=""),"",IF('Pivot elenchi'!P95="",'Pivot elenchi'!P94="",'Pivot elenchi'!P95)) -> 61500010 | M96: =IF(AND('Pivot elenchi'!Q95="",'Pivot elenchi'!Q96=""),"",IF('Pivot elenchi'!Q95="",'Pivot elenchi'!Q94="",'Pivot elenchi'!Q95)) -> PROGRAMMATIC | N96: =IF(AND('Pivot elenchi'!R95="",'Pivot elenchi'!R96=""),"",IF('Pivot elenchi'!R95="",'Pivot elenchi'!R94="",'Pivot elenchi'!R95)) | O96: =IF(AND('Pivot elenchi'!S95="",'Pivot elenchi'!S96=""),"",IF('Pivot elenchi'!S95="",'Pivot elenchi'!S94="",'Pivot elenchi'!S95)) -> SYSTEM 24 - OPERATIONS | P96: =IF(AND('Pivot elenchi'!T95="",'Pivot elenchi'!T96=""),"",IF('Pivot elenchi'!T95="",'Pivot elenchi'!T94="",'Pivot elenchi'!T95)) | Q96: =IF(AND('Pivot elenchi'!U95="",'Pivot elenchi'!U96=""),"",IF('Pivot elenchi'!U95="",'Pivot elenchi'!U94="",'Pivot elenchi'!U95)) -> DG M&B - DG SYSTEM 24 | R96: @ilsole24ore.com | AB96: =L96 -> 61500010 | AC96: =M96 -> PROGRAMMATIC | AD96: =N96 | AE96: =O96 -> SYSTEM 24 - OPERATIONS | AF96: =P96 | AG96: =Q96 -> DG M&B - DG SYSTEM 24
... A109: TELELAVORATORE | B109: TELAV | L109: =IF(AND('Pivot elenchi'!P108="",'Pivot elenchi'!P109=""),"",IF('Pivot elenchi'!P108="",'Pivot elenchi'!P107="",'Pivot elenchi'!P108)) -> A16335 | M109: =IF(AND('Pivot elenchi'!Q108="",'Pivot elenchi'!Q109=""),"",IF('Pivot elenchi'!Q108="",'Pivot elenchi'!Q107="",'Pivot elenchi'!Q108)) -> RCO+ ECONOMIA E SERVIZI | N109: =IF(AND('Pivot elenchi'!R108="",'Pivot elenchi'!R109=""),"",IF('Pivot elenchi'!R108="",'Pivot elenchi'!R107="",'Pivot elenchi'!R108)) | O109: =IF(AND('Pivot elenchi'!S108="",'Pivot elenchi'!S109=""),"",IF('Pivot elenchi'!S108="",'Pivot elenchi'!S107="",'Pivot elenchi'!S108)) -> RCO+ | P109: =IF(AND('Pivot elenchi'!T108="",'Pivot elenchi'!T109=""),"",IF('Pivot elenchi'!T108="",'Pivot elenchi'!T107="",'Pivot elenchi'!T108)) | Q109: =IF(AND('Pivot elenchi'!U108="",'Pivot elenchi'!U109=""),"",IF('Pivot elenchi'!U108="",'Pivot elenchi'!U107="",'Pivot elenchi'!U108)) -> REDAZIONI GIORNALISTICHE | R109: @ilsole24ore.com | AB109: =L109 -> A16335 | AC109: =M109 -> RCO+ ECONOMIA E SERVIZI | AD109: =N109 | AE109: =O109 -> RCO+ | AF109: =P109 | AG109: =Q109 -> REDAZIONI GIORNALISTICHE
L110: =IF(AND('Pivot elenchi'!P109="",'Pivot elenchi'!P110=""),"",IF('Pivot elenchi'!P109="",'Pivot elenchi'!P108="",'Pivot elenchi'!P109)) -> B1000030 | M110: =IF(AND('Pivot elenchi'!Q109="",'Pivot elenchi'!Q110=""),"",IF('Pivot elenchi'!Q109="",'Pivot elenchi'!Q108="",'Pivot elenchi'!Q109)) -> VENDITE PROFESSIONISTI E PA LOC | N110: =IF(AND('Pivot elenchi'!R109="",'Pivot elenchi'!R110=""),"",IF('Pivot elenchi'!R109="",'Pivot elenchi'!R108="",'Pivot elenchi'!R109)) | O110: =IF(AND('Pivot elenchi'!S109="",'Pivot elenchi'!S110=""),"",IF('Pivot elenchi'!S109="",'Pivot elenchi'!S108="",'Pivot elenchi'!S109)) -> DIR.COM. SERVIZI PROFESSIONALI | P110: =IF(AND('Pivot elenchi'!T109="",'Pivot elenchi'!T110=""),"",IF('Pivot elenchi'!T109="",'Pivot elenchi'!T108="",'Pivot elenchi'!T109)) | Q110: =IF(AND('Pivot elenchi'!U109="",'Pivot elenchi'!U110=""),"",IF('Pivot elenchi'!U109="",'Pivot elenchi'!U108="",'Pivot elenchi'!U109)) -> DG SERVIZI PROFESSIONALI E FORMAZIONE | R110: @ilsole24ore.com | AB110: =L110 -> B1000030 | AC110: =M110 -> VENDITE PROFESSIONISTI E PA LOC | AD110: =N110 | AE110: =O110 -> DIR.COM. SERVIZI PROFESSIONALI | AF110: =P110 | AG110: =Q110 -> DG SERVIZI PROFESSIONALI E FORMAZIONE
L111: =IF(AND('Pivot elenchi'!P110="",'Pivot elenchi'!P111=""),"",IF('Pivot elenchi'!P110="",'Pivot elenchi'!P109="",'Pivot elenchi'!P110)) -> B10130 | M111: =IF(AND('Pivot elenchi'!Q110="",'Pivot elenchi'!Q111=""),"",IF('Pivot elenchi'!Q110="",'Pivot elenchi'!Q109="",'Pivot elenchi'!Q110)) -> SUPPORTO COMMERCIALE E SALES AC | N111: =IF(AND('Pivot elenchi'!R110="",'Pivot elenchi'!R111=""),"",IF('Pivot elenchi'!R110="",'Pivot elenchi'!R109="",'Pivot elenchi'!R110)) | O111: =IF(AND('Pivot elenchi'!S110="",'Pivot elenchi'!S111=""),"",IF('Pivot elenchi'!S110="",'Pivot elenchi'!S109="",'Pivot elenchi'!S110)) -> DIR.COM. SERVIZI PROFESSIONALI | P111: =IF(AND('Pivot elenchi'!T110="",'Pivot elenchi'!T111=""),"",IF('Pivot elenchi'!T110="",'Pivot elenchi'!T109="",'Pivot elenchi'!T110)) | Q111: =IF(AND('Pivot elenchi'!U110="",'Pivot elenchi'!U111=""),"",IF('Pivot elenchi'!U110="",'Pivot elenchi'!U109="",'Pivot elenchi'!U110)) -> DG SERVIZI PROFESSIONALI E FORMAZIONE | R111: @ilsole24ore.com | AB111: =L111 -> B10130 | AC111: =M111 -> SUPPORTO COMMERCIALE E SALES AC | AD111: =N111 | AE111: =O111 -> DIR.COM. SERVIZI PROFESSIONALI | AF111: =P111 | AG111: =Q111 -> DG SERVIZI PROFESSIONALI E FORMAZIONE
L112: =IF(AND('Pivot elenchi'!P111="",'Pivot elenchi'!P112=""),"",IF('Pivot elenchi'!P111="",'Pivot elenchi'!P110="",'Pivot elenchi'!P111)) -> B10140 | M112: =IF(AND('Pivot elenchi'!Q111="",'Pivot elenchi'!Q112=""),"",IF('Pivot elenchi'!Q111="",'Pivot elenchi'!Q110="",'Pivot elenchi'!Q111)) -> SVILUPPO CANALI E INIZIATIVE SP | N112: =IF(AND('Pivot elenchi'!R111="",'Pivot elenchi'!R112=""),"",IF('Pivot elenchi'!R111="",'Pivot elenchi'!R110="",'Pivot elenchi'!R111)) | O112: =IF(AND('Pivot elenchi'!S111="",'Pivot elenchi'!S112=""),"",IF('Pivot elenchi'!S111="",'Pivot elenchi'!S110="",'Pivot elenchi'!S111)) -> OPERATIONS E CUSTOMER ENGAGEMENT | P112: =IF(AND('Pivot elenchi'!T111="",'Pivot elenchi'!T112=""),"",IF('Pivot elenchi'!T111="",'Pivot elenchi'!T110="",'Pivot elenchi'!T111)) | Q112: =IF(AND('Pivot elenchi'!U111="",'Pivot elenchi'!U112=""),"",IF('Pivot elenchi'!U111="",'Pivot elenchi'!U110="",'Pivot elenchi'!U111)) -> DG SERVIZI PROFESSIONALI E FORMAZIONE | R112: @ilsole24ore.com | AB112: =L112 -> B10140 | AC112: =M112 -> SVILUPPO CANALI E INIZIATIVE SP | AD112: =N112 | AE112: =O112 -> OPERATIONS E CUSTOMER ENGAGEMENT | AF112: =P112 | AG112: =Q112 -> DG SERVIZI PROFESSIONALI E FORMAZIONE
L113: =IF(AND('Pivot elenchi'!P112="",'Pivot elenchi'!P113=""),"",IF('Pivot elenchi'!P112="",'Pivot elenchi'!P111="",'Pivot elenchi'!P112)) -> B1014010 | M113: =IF(AND('Pivot elenchi'!Q112="",'Pivot elenchi'!Q113=""),"",IF('Pivot elenchi'!Q112="",'Pivot elenchi'!Q111="",'Pivot elenchi'!Q112)) -> OPERATIONS E CUSTOMER ENGAGEMENT | N113: =IF(AND('Pivot elenchi'!R112="",'Pivot elenchi'!R113=""),"",IF('Pivot elenchi'!R112="",'Pivot elenchi'!R111="",'Pivot elenchi'!R112)) | O113: =IF(AND('Pivot elenchi'!S112="",'Pivot elenchi'!S113=""),"",IF('Pivot elenchi'!S112="",'Pivot elenchi'!S111="",'Pivot elenchi'!S112)) -> OPERATIONS E CUSTOMER ENGAGEMENT | P113: =IF(AND('Pivot elenchi'!T112="",'Pivot elenchi'!T113=""),"",IF('Pivot elenchi'!T112="",'Pivot elenchi'!T111="",'Pivot elenchi'!T112)) | Q113: =IF(AND('Pivot elenchi'!U112="",'Pivot elenchi'!U113=""),"",IF('Pivot elenchi'!U112="",'Pivot elenchi'!U111="",'Pivot elenchi'!U112)) -> DG SERVIZI PROFESSIONALI E FORMAZIONE | R113: @ilsole24ore.com | AB113: =L113 -> B1014010 | AC113: =M113 -> OPERATIONS E CUSTOMER ENGAGEMENT | AD113: =N113 | AE113: =O113 -> OPERATIONS E CUSTOMER ENGAGEMENT | AF113: =P113 | AG113: =Q113 -> DG SERVIZI PROFESSIONALI E FORMAZIONE
...

Sheet Pivot elenchi
C1: Conteggio di CDDICEFI | Q1: (più elementi)
B2: Num | C2: CDAZIEND | D2: NOMESOC | E2: Totale | G2: Num | H2: CDSEDEXX | I2: Indirizzo | J2: CDPROLAV | O2: Collegate
B3: 1 | C3: 15 | D3: IL SOLE 24 ORE S.P.A. | G3: 1 | H3: 19 | I3: VIA TORTONA 56 - MILANO (MI) | J3: MILANO
B4: 2 | C4: 28 | D4: 24 ORE CULTURA S.R.L. | G4: 2 | H4: 31 | I4: PIAZZA INDIPENDENZA 23 B/C - ROMA (RM) | J4: ROMA | O4: Num | P4: CDCCOSTO | Q4: Desccdc | R4: CodSottoArea | S4: DescrSottoArea | T4: Codarea | U4: DescrArea | V4: Totale
B5: 3 | C5: 35 | D5: IL SOLE 24 ORE EVENTI S.R.L. | G5: 3 | H5: 33 | I5: VIA NIZZA 142 - ROMA (RM) | J5: ROMA | O5: 1 | P5: 011000 | Q5: CORPORATE | S5: CORPORATE | U5: CORPORATE
B6: 4 | C6: 2015 | D6: IL SOLE 24 ORE SPA | G6: 4 | H6: 34 | I6: VIALE SARCA 223 - MILANO (MI) | J6: MILANO | O6: 2 | P6: 011200 | Q6: DG INNOVAZIONE E SOSTENIBILITA' | S6: DG INNOVAZIONE E SOSTENIBILITA' | U6: DG INNOVAZIONE E SOSTENIBILITA'
B7: 5 | C7: 2028 | D7: COLLABORATORI 24ORE CULTURA | G7: 5 | H7: 50 | I7: VIA DAVIDE BERTOLOTTI 7 - TORINO (TO) | J7: TORINO | O7: 3 | P7: 012000 | Q7: AFFARI LEGALI E SOCIETARI | S7: AFFARI LEGALI E SOCIETARI | U7: AFFARI LEGALI E SOCIETARI
B8: 6 | C8: 4015 | D8: IL SOLE 24 ORE SPA | G8: 6 | H8: 65 | I8: VIA SOLTERI 38 - TRENTO (TN) | J8: TRENTO | O8: 4 | P8: 013000 | Q8: INVESTOR RELATIONS | S8: INVESTOR RELATIONS | U8: AMMINISTRAZIONE, FINANZA E CONTROLLO
B9: 7 | C9: 1010 | D9: SOLE STAGE | G9: 7 | H9: 66 | I9: DOMICILIO COLLABORATORE - () | O9: 5 | P9: 015000 | Q9: DG SERVIZI PROFESSIONALI | S9: DG SERVIZI PROFESSIONALI E FORMAZIONE | U9: DG SERVIZI PROFESSIONALI E FORMAZIONE
B10: 8 | G10: 8 | H10: 68 | I10: VIA DELLE LIBERTA' 12 - VENEZIA (VE) | J10: VENEZIA | O10: 6 | P10: 016100 | Q10: INTERNAL AUDITING | S10: INTERNAL AUDITING | U10: CORPORATE
B11: 9 | G11: 9 | H11: 72 | I11: VIA ALESSANDRO VOLTA 44 - PALERMO (PA) | J11: PALERMO | O11: 7 | P11: 016110 | Q11: PRIVACY E SICUREZZA DATI | S11: AFFARI LEGALI E SOCIETARI | U11: AFFARI LEGALI E SOCIETARI
B12: 10 | G12: 10 | H12: 79 | I12: PIAZZA DEI MARTIRI 58 - NAPOLI (NA) | J12: NAPOLI | O12: 8 | P12: 210000 | Q12: AMMINISTRAZIONE, FINANZA E CONTROLLO | S12: AMMINISTRAZIONE, FINANZA E CONTROLLO | U12: AMMINISTRAZIONE, FINANZA E CONTROLLO
B13: 11 | G13: 11 | H13: 80 | I13: VIALE IV NOVEMBRE 6 - GENOVA (GE) | J13: GENOVA | O13: 9 | P13: 21000001 | Q13: FISCALITA' | S13: FISCALITA' | U13: AMMINISTRAZIONE, FINANZA E CONTROLLO
B14: 12 | G14: 12 | H14: 99 | I14: Corrisp. ESTERO | J14: EE | O14: 10 | P14: 214000 | Q14: PIANIFICAZIONE E CONTROLLO DI G | S14: PIANIFICAZIONE E CONTROLLO | U14: AMMINISTRAZIONE, FINANZA E CONTROLLO
B15: 13 | G15: 13 | O15: 11 | P15: 215000 | Q15: BILANCIO | S15: AMMINISTRAZIONE E BILANCIO | U15: AMMINISTRAZIONE, FINANZA E CONTROLLO
B16: 14 | G16: 14 | O16: 12 | P16: 215100 | Q16: CREDIT MANAGEMENT | S16: FINANZA, TESORERIA E RISK MANAGEMENT | U16: AMMINISTRAZIONE, FINANZA E CONTROLLO
B17: 15 | G17: 15 | O17: 13 | P17: 21520011 | Q17: CONTABILITA' GENERALE | S17: AMMINISTRAZIONE E BILANCIO | U17: AMMINISTRAZIONE, FINANZA E CONTROLLO
B18: 16 | G18: 16 | O18: 14 | P18: 21520012 | Q18: CONTABILITA' FORNITORI | S18: AMMINISTRAZIONE E BILANCIO | U18: AMMINISTRAZIONE, FINANZA E CONTROLLO
G19: 17 | O19: 15 | P19: 21520013 | Q19: CONTABILITA' CLIENTI | S19: AMMINISTRAZIONE E BILANCIO | U19: AMMINISTRAZIONE, FINANZA E CONTROLLO
G20: 18 | O20: 16 | P20: 215500 | Q20: FINANZA, TESORERIA E RISK MAN | S20: FINANZA, TESORERIA E RISK MANAGEMENT | U20: AMMINISTRAZIONE, FINANZA E CONTROLLO
G21: 19 | O21: 17 | P21: 21550001 | Q21: TESORERIA E RISK MANAGEMENT | S21: FINANZA, TESORERIA E RISK MANAGEMENT | U21: AMMINISTRAZIONE, FINANZA E CONTROLLO
O22: 18 | P22: 310000 | Q22: DIR. CENTR. PERSONALE E ORG. | S22: DIREZIONE PERSONALE | U22: DIREZIONE CENTRALE PERSONALE E ORGANIZZA
O23: 19 | P23: 31000010 | Q23: GEST.PERSONALE DIR.FUNZ.CENTR. | S23: DIREZIONE PERSONALE | U23: DIREZIONE CENTRALE PERSONALE E ORGANIZZA
O24: 20 | P24: 31000020 | Q24: ORGANIZZAZIONE | S24: DIREZIONE PERSONALE | U24: DIREZIONE CENTRALE PERSONALE E ORGANIZZA
O25: 21 | P25: 311000 | Q25: GEST.PERSONALE DIR.IT E BUSINES | S25: DIREZIONE PERSONALE | U25: DIREZIONE CENTRALE PERSONALE E ORGANIZZA
O26: 22 | P26: 312000 | Q26: NORME E AMMINISTR DEL PERSONALE | S26: DIREZIONE PERSONALE | U26: DIREZIONE CENTRALE PERSONALE E ORGANIZZA
O27: 23 | P27: 412620 | Q27: COORDINAMENTO TECNICO PRODUTTIV | S27: OPERATIONS DG P&D | U27: DG M&B - DG PUBLISHING & DIGITAL
O28: 24 | P28: 412700 | Q28: PREP. EDITORIALE PROFESSIONALE | S28: OPERATIONS E CUSTOMER ENGAGEMENT | U28: DG SERVIZI PROFESSIONALI E FORMAZIONE
O29: 25 | P29: 413000 | Q29: ACQUISTI | S29: ACQUISTI | U29: DIREZIONE CENTRALE PERSONALE E ORGANIZZA
O30: 26 | P30: 414000 | Q30: SERVIZI GENERALI SICUREZZA E AM | S30: SERVIZI GENERALI SICUREZZA E AMBIENTE | U30: DIREZIONE CENTRALE PERSONALE E ORGANIZZA
O31: 27 | P31: 41400001 | Q31: SUPPORTO TECNICO E HSE | S31: SERVIZI GENERALI SICUREZZA E AMBIENTE | U31: DIREZIONE CENTRALE PERSONALE E ORGANIZZA
O32: 28 | P32: 414100 | Q32: COORDINAMENTO OPERATIVO | S32: SERVIZI GENERALI SICUREZZA E AMBIENTE | U32: DIREZIONE CENTRALE PERSONALE E ORGANIZZA
O33: 29 | P33: 415110 | Q33: SISTEMI INFORMATICI GESTIONALI | S33: SISTEMI INFORMATICI GESTIONALI | U33: DG I&S - DIR INFORMATION TECHNOLOGY
... O152: 148 | P152: W1953020 | Q152: COMMERCIALE MOSTRE | S152: 24 ORE CULTURA | U152: 24 ORE CULTURA
O153: 149
O154: 150
O155: 151
O156: 152
O157: 153
O158: 154
O159: 155
O160: 156
O161: 157
O162: 158
O163: 159
O164: 160
... O228: 224
